Workbook
Name CriticalThreshold: MatrixImpact!$G$2
Name LastRMC: Header!$D$20
Name LogarithmBase: MatrixImpact!$G$3
Name NbObjectives: Objectives!$G$8
Name ReportingPeriod: Parameters!$E$10
Name ReportingUnits: Parameters!$A$2:$C$5
Name RiskIdBeginsWith: Parameters!$A$2
Name SelectedBU: Header!$H$10
Name Timeframe: Parameters!$E$3:$E$8
Name timehorizon: Parameters!$E$13:$E$15
Name ValidationDate: Header!$D$14

Sheet 7-Instructions
A1: CORE v7 INTEGRATED RISK & OPPORTUNITY MANAGEMENT — USER GUIDE
A40: INTEGRATED WORKFLOW (v7)
A41: Step 1: | B41: Complete Calibration (org profile dropdowns). All CORE coefficients auto-calculate.
A42: Step 2: | B42: Complete Company_RI and Company_SMI (sub-component scores 0-10).
A43: Step 3: | B43: Enter risks in Top 10 Risks sheet (ID, Title, Causes, Impact 1-5, Likelihood 1-5, Trend).
A44: Step 4: | B44: RADAR auto-populates from Top 10 Risks with full CORE calculation chain.
A45: Step 5: | B45: Complete Risk Control sheet (ownership, limits, assessment, controls, monitoring).
A46: Step 6: | B46: FORGE Decision Quality auto-calculates from Risk Control. RE, Containment, R-TTS follow.
A47: Step 7: | B47: Enter FORGE Severity (1-10) per crisis for R-TTS and Urgency Index to compute.
A48: Step 8: | B48: Complete Risk Interaction Map. Coherence Density and Von Neumann Entropy auto-update.
A49: Step 9: | B49: Enter opportunities in Opportunities sheet. Review Dashboard for integrated view.

Sheet Header
E3: Risk Management Reporting
E5: Select:
E6: Emerging Risk Assessment (RADAR) | I6: =TRUE() -> TRUE
E7: Enterprise Risk Assessment (FORGE) | I7: =FALSE() -> FALSE
C10: Reporting Unit: | H10: 3
C12: Reporting Period: | D12: 2 | F12: To be filled in by Corporate Risk Management:
C14: Validation Date: | F14: Review Date:
C16: CEO: | F16: Reviewer: | H16: 1
C18: RM Contact:
H19: Please send this report to:
C20: Last Risk Management meeting:

Sheet Calibration
A1: CORE v6.0 — Organizational Calibration System | G1: User input
A2: Select characteristics → coefficients auto-calculate
H3: To be selected
A4: SECTION A: PRIMARY ORGANIZATIONAL PROFILE | H4: Calculated
A5: Characteristic | B5: Selection | C5: Weight | D5: Impact | E5: Description | H5: Linked to cell
A6: Industry Sector | B6: Manufacturing | C6: 0.25 | E6: Primary classification
A7: Company Maturity | B7: Established (>10 years) | C7: 0.2 | E7: Lifecycle stage
A8: Risk Appetite | B8: Moderate | C8: 0.2 | E8: Conservative/Moderate/Aggressive
A9: Geographic Scope | B9: Multi-National | C9: 0.15 | E9: Market footprint
A10: Regulatory Environment | B10: Heavy | C10: 0.1 | E10: Regulatory intensity
A11: Digital Maturity | B11: Advanced | C11: 0.1 | E11: Technology integration
A14: SECTION B: DERIVED COEFFICIENTS
A15: Coefficient | B15: Symbol | C15: Value | D15: Range | E15: Used In
A16: Velocity Multiplier | B16: α | C16: =ROUND(0.5+1.5*(C6*IF(B6="Financial Services",0.9,IF(B6="Technology",0.85,IF(B6="Healthcare",0.55,IF(B6="Manufacturing",0.4,IF(B6="Energy",0.35,IF(B6="Retail",0.5,0.3))))))+C9*IF(B9="Global",0.8,IF(B9="Multi-National",0.6,IF(B9="Regional",0.35,0.15)))+C7*IF(B7="Startup (<3 years)",0.8,IF(B7="Growth (3-10 years)",0.6,IF(B7="Established (>10 years)",0.4,0.25))))/(C6+C9+C7),2) -> 1.18 | D16: 0.5–2.0 | E16: TTS, EW-TTS
A17: Impact Scaling | B17: β | C17: =ROUND(0.5+1*(C10*IF(B10="Extreme",0.9,IF(B10="Heavy",0.7,IF(B10="Moderate",0.45,0.2)))+C7*IF(B7="Legacy (>50 years)",0.8,IF(B7="Established (>10 years)",0.6,IF(B7="Growth (3-10 years)",0.35,0.2)))+C6*IF(B6="Financial Services",0.8,IF(B6="Technology",0.6,IF(B6="Healthcare",0.7,IF(B6="Manufacturing",0.5,IF(B6="Energy",0.7,IF(B6="Retail",0.4,0.8)))))))/(C10+C7+C6),2) -> 1.07 | D17: 0.5–1.5 | E17: Normalization
A18: Phase Proximity Base | B18: Φ₀ | C18: =ROUND(0.3+0.5*(C7*IF(B7="Startup (<3 years)",0.85,IF(B7="Growth (3-10 years)",0.65,IF(B7="Established (>10 years)",0.4,0.3)))+C6*IF(B6="Financial Services",0.75,IF(B6="Technology",0.7,IF(B6="Healthcare",0.5,IF(B6="Manufacturing",0.4,IF(B6="Energy",0.5,IF(B6="Retail",0.5,0.35))))))+C11*IF(B11="Basic",0.6,IF(B11="Intermediate",0.45,IF(B11="Advanced",0.35,0.3))))/(C7+C6+C11),2) -> 0.5 | D18: 0.3–0.8 | E18: EW-TTS
A19: Coherence Decay | B19: λ_c | C19: =ROUND(C9*IF(B9="Global",0.02,IF(B9="Multi-National",0.05,IF(B9="Regional",0.1,0.16)))+C6*IF(B6="Financial Services",0.03,IF(B6="Technology",0.05,IF(B6="Healthcare",0.08,IF(B6="Manufacturing",0.1,IF(B6="Energy",0.07,IF(B6="Retail",0.12,0.09))))))+C10*IF(B10="Extreme",0.04,IF(B10="Heavy",0.06,IF(B10="Moderate",0.1,0.15))),3) -> 0.039 | D19: 0.01–0.20 | E19: Density Matrix
A20: Palmer Noise Base | B20: η₀ | C20: =ROUND(C11*IF(B11="Basic",0.28,IF(B11="Intermediate",0.2,IF(B11="Advanced",0.13,0.08)))+C6*IF(B6="Financial Services",0.12,IF(B6="Technology",0.1,IF(B6="Healthcare",0.18,IF(B6="Manufacturing",0.2,IF(B6="Energy",0.22,IF(B6="Retail",0.15,0.16))))))+C8*IF(B8="Conservative",0.2,IF(B8="Moderate",0.15,0.1)),3) -> 0.093 | D20: 0.05–0.30 | E20: Stochastic resonance
A21: Max Velocity | B21: v_max | C21: =ROUND((C6+C11)*IF(B6="Financial Services",10,IF(B6="Technology",9,IF(B6="Healthcare",7,IF(B6="Manufacturing",6,IF(B6="Energy",5,IF(B6="Retail",7,4))))))/(C6+C11)+C11*IF(B11="Digital-Native",1.5,IF(B11="Advanced",0.8,IF(B11="Intermediate",0.3,0)))/(C6+C11),1) -> 6.2 | D21: 3–10 | E21: Lorentz Factor
A22: Conformal Boundary CCORD | B22: S | C22: 1 | D22: 0.5–2.0 | E22: |x|+|t|≤S
A23: Risk Appetite Factor | B23: RAF | C23: =IF(B8="Conservative",0.3,IF(B8="Moderate",0.5,0.8)) -> 0.5 | D23: 0.1–0.9 | E23: Zone thresholds
A24: MC Simulation Runs | B24: N_MC | C24: 50 | D24: 10–1000 | E24: Ensemble size
A25: Confidence Level | B25: CL | C25: 0.95 | D25: 0.80–0.99 | E25: VaR percentile
A26: Conformal Time Scale | B26: κ_t | C26: =ROUND(1.5+1.5*(C6*IF(B6="Financial Services",0.8,IF(B6="Technology",0.7,IF(B6="Healthcare",0.4,IF(B6="Manufacturing",0.3,IF(B6="Energy",0.3,IF(B6="Retail",0.5,0.2))))))+C8*IF(B8="Aggressive",0.7,IF(B8="Moderate",0.4,0.2)))/(C6+C8),2) -> 2.02 | D26: 1.5–3.0 | E26: TANH compression
A28: SECTION C: RISK CATEGORIES
A29: Category | B29: Code | C29: RADAR Scope | D29: FORGE Scope | E29: Opportunity Scope
A30: Operational | B30: OPS | C30: Process failures, supply chain | D30: Safety recalls, shutdowns | E30: Process optimization
A31: Technology | B31: TECH | C31: Cyber threats, system failures | D31: Data breaches, IT outages | E31: Digital transformation
A32: Regulatory | B32: REG | C32: Emerging regulation | D32: Enforcement actions | E32: Regulatory arbitrage
A33: Strategic | B33: STR | C33: Market shifts, competition | D33: Partnership collapse | E33: M&A, consolidation
A34: Financial | B34: FIN | C34: Currency, credit, liquidity | D34: Insolvency, margin calls | E34: Capital deployment
A35: ESG | B35: ESG | C35: Climate, social, governance | D35: Environmental contamination | E35: Sustainability leadership
A36: Geopolitical | B36: GEO | C36: Trade tensions, sanctions | D36: Asset seizure, conflict | E36: Geographic diversification
A37: Reputational | B37: REP | C37: Brand erosion, media | D37: Crisis communications | E37: Brand strengthening
A40: SECTION D: DROPDOWN SCALE DEFINITIONS
A41: Scale | B41: Values | C41: Sheet | D41: Type | E41: Notes
A42: Velocity (1-10) | B42: 1=Glacial → 10=Instant | C42: RADAR | D42: Input | E42: Propagation speed
A43: Severity (1-10) | B43: 1=Negligible → 10=Catastrophic | C43: FORGE | D43: Input | E43: Crisis severity
A44: Strategic Fit (1-10) | B44: 1=Misaligned → 10=Perfect | C44: Opportunities | D44: Input | E44: Alignment
A45: Phase Proximity (0-1) | B45: 0=Distant → 1=Crystallized | C45: RADAR | D45: Input | E45: Temporal proximity
A46: Coherence Factor (0-1) | B46: 0=Independent → 1=Coupled | C46: RADAR | D46: Input | E46: Inter-risk coupling
A47: Response Eff. (0-1) | B47: 0=None → 0.9=Excellent | C47: FORGE | D47: Calculated | E47: From org inputs
A48: Resource Factor (0-1) | B48: 0=None → 0.9=Full | C48: FORGE | D48: Calculated | E48: From org inputs
A49: Status | B49: MONITORING/PREPARING/ACTIVE/RESOLVED | C49: FORGE | D49: Input | E49: Lifecycle stage
A50: Category | B50: OPS/TECH/REG/STR/FIN/ESG/GEO/REP | C50: All sheets | D50: Input | E50: Risk classification
A53: SECTION E: CALIBRATION DERIVATION MAP — How Section A drives Section B
A54: Coefficient | B54: Primary Driver(s) | C54: Formula Logic | D54: Current Value
A55: α (Velocity) | B55: Industry(0.25)+Geographic(0.15)+Maturity(0.20) | C55: 0.5 + 1.5 × weighted_avg(ind_vel, geo_scope, mat_speed) | D55: =C16 -> 1.18
A56: β (Impact) | B56: Regulatory(0.10)+Maturity(0.20)+Industry(0.25) | C56: 0.5 + 1.0 × weighted_avg(reg_intensity, mat_inertia, ind_impact) | D56: =C17 -> 1.07
A57: Φ₀ (Phase Prox) | B57: Maturity(0.20)+Industry(0.25)+Digital(0.10) | C57: 0.3 + 0.5 × weighted_avg(mat_volatility, ind_phase, dig_sensitivity) | D57: =C18 -> 0.5
A58: λ_c (Coherence) | B58: Geographic(0.15)+Industry(0.25)+Regulatory(0.10) | C58: weighted_avg(geo_decay, ind_interconnect, reg_coupling) | D58: =C19 -> 0.039
A59: η₀ (Palmer Noise) | B59: Digital(0.10)+Industry(0.25)+RiskAppetite(0.20) | C59: weighted_avg(dig_noise, ind_volatility, appetite_uncertainty) | D59: =C20 -> 0.093
A60: v_max | B60: Industry(0.25)+Digital(0.10) | C60: Industry base velocity + digital acceleration bonus | D60: =C21 -> 6.2
A61: RAF | B61: Risk Appetite(0.20) | C61: Direct: Conservative=0.3, Moderate=0.5, Aggressive=0.8 | D61: =C23 -> 0.5
A62: κ_t (Time Scale) | B62: Industry(0.25)+Risk Appetite(0.20) | C62: 1.5 + 1.5 × weighted_avg(ind_urgency, appetite_compression) | D62: =C26 -> 2.02

Sheet CORE
A1: CORE v6.0 — Master Framework
A2: Horizon Event Risk Opportunity Dynamics — Company-Level Properties
A4: GLOBAL PARAMETERS
A5: Parameter | B5: Value | C5: Unit | D5: Min | E5: Max | F5: Default | G5: Notes
A6: Company Name | B6: Hypothetical Corp | G6: Entity under analysis
A7: Analysis Date | B7: 2026-03-04 | G7: Assessment date
A8: Max Impact Exposure | B8: 1000 | C8: €M | D8: 1 | E8: 10000 | F8: 1000 | G8: Upper bound for normalization
A9: Confidence Level | B9: 0.95 | D9: 0.8 | E9: 0.99 | F9: 0.95 | G9: MC VaR percentile
A10: Simulation Runs | B10: 50 | D10: 10 | E10: 1000 | F10: 50 | G10: MC ensemble size
A11: Palmer Noise | B11: =Calibration!C20 -> 0.093 | D11: 0 | E11: 0.5 | F11: 0.15 | G11: Stochastic resonance
A12: Phase Prox Threshold | B12: 0.7 | D12: 0 | E12: 1 | F12: 0.7 | G12: EW-TTS activation
A13: Coherence Decay | B13: =Calibration!C19 -> 0.039 | D13: 0 | E13: 0.2 | F13: 0.05 | G13: λ temporal decay
A14: Conformal Boundary S | B14: 1 | D14: 0.5 | E14: 2 | F14: 1 | G14: |x|+|t|≤S
A15: Max Velocity | B15: =Calibration!C21 -> 6.2 | D15: 3 | E15: 10 | F15: 8 | G15: Lorentz denominator
A16: Risk Appetite | B16: =Calibration!C23 -> 0.5 | D16: 0.1 | E16: 0.9 | F16: 0.5 | G16: Zone thresholds
A19: IMPACT NORMALIZATION (€M → Score 0-10)
A20: Formula: | B20: MIN(20, MAX(1, 2×LN(Impact_€M + 1)))
A21: €M | B21: Score | C21: Interpretation
A22: 0.5 | B22: =MIN(20,MAX(1,2*LN(A22+1))) -> 1 | C22: Minimal
A23: 5 | B23: =MIN(20,MAX(1,2*LN(A23+1))) -> 3.5835189 | C23: Low
A24: 25 | B24: =MIN(20,MAX(1,2*LN(A24+1))) -> 6.5161931 | C24: Moderate
A25: 100 | B25: =MIN(20,MAX(1,2*LN(A25+1))) -> 9.230241 | C25: Major
A26: 500 | B26: =MIN(20,MAX(1,2*LN(A26+1))) -> 12.433212 | C26: Critical
A27: 1000 | B27: =MIN(20,MAX(1,2*LN(A27+1))) -> 13.81751 | C27: Catastrophic
A28: 2000 | B28: =MIN(20,MAX(1,2*LN(A28+1))) -> 15.202805 | C28: Maximum
A30: RESILIENCE INDEX (RI) — from Company_RI
A31: Component | B31: Weight | C31: Score | D31: Weighted
A32: Control Effectiveness | B32: 0.35 | C32: =Company_RI!D10 -> 7.2 | D32: =B32*C32 -> 2.52
A33: Recovery Capability | B33: 0.25 | C33: =Company_RI!D11 -> 6.5 | D33: =B33*C33 -> 1.625
A34: Resource Adequacy | B34: 0.2 | C34: =Company_RI!D12 -> 7.8 | D34: =B34*C34 -> 1.56
A35: Adaptive Capacity | B35: 0.2 | C35: =Company_RI!D13 -> 5.9 | D35: =B35*C35 -> 1.18
A36: RESILIENCE INDEX (RI) | D36: =SUM(D32:D35) -> 6.885 | F36: Scale: 0-10
A38: STRATEGIC MOBILITY INDEX (SMI) — from Company_SMI
A39: Component | B39: Weight | C39: Score | D39: Weighted
A40: Market Positioning | B40: 0.3 | C40: =Company_SMI!D10 -> 6.8 | D40: =B40*C40 -> 2.04
A41: Strategic Capital | B41: 0.3 | C41: =Company_SMI!D11 -> 7.1 | D41: =B41*C41 -> 2.13
A42: Innovation Capability | B42: 0.25 | C42: =Company_SMI!D12 -> 5.5 | D42: =B42*C42 -> 1.375
A43: Strategic Flexibility | B43: 0.15 | C43: =Company_SMI!D13 -> 6.2 | D43: =B43*C43 -> 0.93
A44: STRATEGIC MOBILITY INDEX (SMI) | D44: =SUM(D40:D43) -> 6.475 | F44: Scale: 0-10
A46: RI–SMI DUALITY DIAGNOSTIC
A47: Metric | B47: Value | C47: Interpretation
A48: RI (Potential Energy) | B48: =D36 -> 6.885 | C48: =IF(D36>=7,"High Resilience",IF(D36>=4,"Moderate","Low")) -> Moderate
A49: SMI (Kinetic Energy) | B49: =D44 -> 6.475 | C49: =IF(D44>=7,"High Mobility",IF(D44>=4,"Moderate","Low")) -> Moderate
A50: RI–SMI Ratio | B50: =IF(D44>0,D36/D44,0) -> 1.0633205 | C50: =IF(B50>1.2,"Defense-Heavy",IF(B50<0.8,"Offense-Heavy","Balanced")) -> Balanced
A51: Total Energy | B51: =D36+D44 -> 13.36 | C51: =IF(B51>=14,"Dominant",IF(B51>=10,"Strong",IF(B51>=6,"Average","Vulnerable"))) -> Strong
A52: Gap |RI-SMI| | B52: =ABS(D36-D44) -> 0.41 | C52: =IF(B52>3,"Critical imbalance",IF(B52>1.5,"Notable gap","Well balanced")) -> Well balanced
A53: Posture | B53: =IF(AND(D36>=5.5,D44>=5.5),"BLACK PHOENIX",IF(AND(D36>=5.5,D44<5.5),"INCUMBENT DEFENDER",IF(AND(D36<5.5,D44>=5.5),"DISRUPTIVE CHALLENGER","DOUBLE EXPOSURE"))) -> BLACK PHOENIX | C53: =IF(B53="BLACK PHOENIX","Optimal: high resilience + high mobility",IF(B53="INCUMBENT DEFENDER","Strong defense, weak offense",IF(B53="DISRUPTIVE CHALLENGER","Strong offense, weak defense","Vulnerable both"))) -> Optimal: high resilience + high mobility

Sheet Company_RI
A1: Resilience Index (RI) — Detailed Calculation
A2: Potential Energy | Empirical: 8-crisis analysis | Feeds FORGE
A4: SECTION A: CRISIS-FREQUENCY WEIGHT DERIVATION
A5: Crisis | B5: Year | C5: CE? | D5: RC? | E5: RA? | F5: AC? | G5: Primary Cause
A6: ENRON | B6: 2001 | C6: 1 | D6: 0 | E6: 0 | F6: 1 | G6: Control collapse
A7: 2008 Financial | B7: 2008 | C7: 1 | D7: 1 | E7: 1 | F7: 0 | G7: Systemic control+resource
A8: Deepwater Horizon | B8: 2010 | C8: 1 | D8: 1 | E8: 0 | F8: 0 | G8: Safety control+recovery
A9: Boeing MAX | B9: 2019 | C9: 1 | D9: 0 | E9: 0 | F9: 1 | G9: Design control+adaptive
A10: COVID-19 | B10: 2020 | C10: 0 | D10: =F20 -> 7.2 | E10: 1 | F10: 1 | G10: Recovery+resource+adaptation
A11: SVB | B11: 2023 | C11: 1 | D11: =F21 -> 6.5 | E11: 1 | F11: 0 | G11: Risk control+liquidity
A12: Wirecard | B12: 2020 | C12: 1 | D12: =F22 -> 7.8 | E12: 0 | F12: 0 | G12: Fundamental control fraud
A13: Credit Suisse | B13: 2023 | C13: 1 | D13: =F23 -> 5.9 | E13: 1 | F13: 1 | G13: All dimensions
A14: FREQUENCY | C14: =SUM(C6:C13) -> 7 | D14: =SUM(D6:D13) -> 29.4 | E14: =SUM(E6:E13) -> 4 | F14: =SUM(F6:F13) -> 4
A15: WEIGHT | C15: =C14/SUM(C14:F14) -> 0.15765766 | D15: =D14/SUM(C14:F14) -> 0.66216216 | E15: =E14/SUM(C14:F14) -> 0.09009009 | F15: =F14/SUM(C14:F14) -> 0.09009009
A16: APPLIED | C16: 0.35 | D16: 0.25 | E16: 0.2 | F16: 0.2 | G16: Rounded
A18: SECTION B: COMPONENT SCORING
A19: Component | B19: Weight | C19: Sub-1 | D19: Sub-2 | E19: Sub-3 | F19: Score (0-10) | G19: Method
A20: Control Effectiveness | B20: =CORE!B32 -> 0.35 | C20: Audit score | D20: Process maturity | E20: Compliance rate | F20: 7.2 | G20: Avg 3 sub-metrics
A21: Recovery Capability | B21: =CORE!B33 -> 0.25 | C21: RTO achievement | D21: BCP test success | E21: Backup coverage | F21: 6.5 | G21: Recovery performance
A22: Resource Adequacy | B22: =CORE!B34 -> 0.2 | C22: Cash/revenue | D22: Insurance coverage | E22: Credit headroom | F22: 7.8 | G22: Financial buffer
A23: Adaptive Capacity | B23: =CORE!B35 -> 0.2 | C23: Learning rate | D23: Pivot speed | E23: Scenario depth | F23: 5.9 | G23: Change responsiveness
A25: RESILIENCE INDEX (RI) | F25: =SUMPRODUCT(B20:B23,F20:F23) -> 6.885
A27: SECTION C: RI-DERIVED PARAMETERS (→ FORGE)
A28: Parameter | B28: Symbol | C28: Formula | D28: Value | E28: Used In
A29: Containment Index | B29: CI | C29: RI/10 | D29: =F25/10 -> 0.6885 | E29: FORGE R-TTS
A30: Palmer Noise B | B30: η_B | C30: 0.1+0.3×(1-CI) | D30: =0.1+0.3*(1-D29) -> 0.19345 | E30: FORGE MC
A31: R-TTS Decay Rate | B31: λ | C31: RI/180 | D31: =F25/180 -> 0.03825 | E31: FORGE recovery
A32: Recovery Modifier | B32: R_mod | C32: 1+(1-RI/10) | D32: =1+(1-F25/10) -> 1.3115 | E32: FORGE time
A35: SECTION D: IMPROVEMENT LEVER SENSITIVITY
A36: Component | B36: Current | C36: RI if +1pt | D36: RI Δ | E36: Weight | F36: Δ/Weight | G36: Priority
A37: Control Effectiveness | B37: =F20 -> 7.2 | C37: =F25+B20*1 -> 7.235 | D37: =C37-F25 -> 0.35 | E37: 0.35 | F37: =D37/E37 -> 1 | G37: =IF(D37>0.3,"HIGH",IF(D37>0.2,"MODERATE","LOW")) -> HIGH
A38: Recovery Capability | B38: =F21 -> 6.5 | C38: =F25+B21*1 -> 7.135 | D38: =C38-F25 -> 0.25 | E38: 0.25 | F38: =D38/E38 -> 1 | G38: =IF(D38>0.3,"HIGH",IF(D38>0.2,"MODERATE","LOW")) -> MODERATE
A39: Resource Adequacy | B39: =F22 -> 7.8 | C39: =F25+B22*1 -> 7.085 | D39: =C39-F25 -> 0.2 | E39: 0.2 | F39: =D39/E39 -> 1 | G39: =IF(D39>0.3,"HIGH",IF(D39>0.2,"MODERATE","LOW")) -> LOW
A40: Adaptive Capacity | B40: =F23 -> 5.9 | C40: =F25+B23*1 -> 7.085 | D40: =C40-F25 -> 0.2 | E40: 0.2 | F40: =D40/E40 -> 1 | G40: =IF(D40>0.3,"HIGH",IF(D40>0.2,"MODERATE","LOW")) -> LOW

Sheet Company_SMI
A1: Strategic Mobility Index (SMI) — Detailed Calculation
A2: Kinetic Energy | Empirical: 5 opportunity-capture cases | Feeds Opportunities
A4: SECTION A: OPPORTUNITY-CAPTURE WEIGHT DERIVATION
A5: Case | B5: Year | C5: MP? | D5: SC? | E5: IC? | F5: SF? | G5: Mechanism
A6: Goldman 2008 | B6: 2008 | C6: 1 | D6: 1 | E6: 0 | F6: 1 | G6: Position+capital
A7: Apple iPhone | B7: 2007 | C7: 1 | D7: 1 | E7: 1 | F7: 0 | G7: Vision+R&D+execution
A8: Tesla EV | B8: 2015 | C8: 1 | D8: 0 | E8: 1 | F8: 1 | G8: Position+innovation
A9: Zoom COVID | B9: 2020 | C9: 0 | D9: 1 | E9: 1 | F9: 1 | G9: Capital+speed+flex
A10: NVIDIA AI | B10: 2023 | C10: 1 | D10: =F17 -> 6.8 | E10: 1 | F10: 0 | G10: Position+capital+innov
A11: FREQUENCY | C11: =SUM(C6:C10) -> 4 | D11: =F18 -> 7.1 | E11: =SUM(E6:E10) -> 4 | F11: =SUM(F6:F10) -> 3
A12: WEIGHT | C12: =C11/SUM(C11:F11) -> 0.22099448 | D12: =F19 -> 5.5 | E12: =E11/SUM(C11:F11) -> 0.22099448 | F12: =F11/SUM(C11:F11) -> 0.16574586
A13: APPLIED | C13: 0.3 | D13: =F20 -> 6.2 | E13: 0.25 | F13: 0.15 | G13: Symmetric MP-SC
A15: SECTION B: COMPONENT SCORING
A16: Component | B16: Weight | C16: Sub-1 | D16: Sub-2 | E16: Sub-3 | F16: Score | G16: Method
A17: Market Positioning | B17: 0.3 | C17: Market share trend | D17: Brand strength | E17: Distribution reach | F17: 6.8 | G17: Competitive composite
A18: Strategic Capital | B18: 0.3 | C18: R&D spend ratio | D18: Talent pipeline | E18: IP portfolio | F18: 7.1 | G18: Investment index
A19: Innovation Capability | B19: 0.25 | C19: Time-to-market | D19: Prototype velocity | E19: Digital maturity | F19: 5.5 | G19: Innovation pipeline
A20: Strategic Flexibility | B20: 0.15 | C20: Pivot speed | D20: Legacy constraints | E20: Decision cycle | F20: 6.2 | G20: Agility measure
A22: STRATEGIC MOBILITY INDEX (SMI) | F22: =SUMPRODUCT(B17:B20,F17:F20) -> 6.475
A24: SECTION C: SMI-DERIVED PARAMETERS (→ Opportunities)
A25: Parameter | B25: Symbol | C25: Formula | D25: Value | E25: Used In
A26: OTS Amplification | B26: A_OTS | C26: 1+SMI×0.05 | D26: =1+F22*0.05 -> 1.32375 | E26: Capture multiplier
A27: Palmer Noise Opp | B27: η_O | C27: 0.1+0.3×(1-SMI/10) | D27: =0.1+0.3*(1-F22/10) -> 0.20575 | E27: Opp MC
A28: Capture Velocity | B28: v_cap | C28: SMI/10 | D28: =F22/10 -> 0.6475 | E28: Capture speed
A29: Momentum | B29: p | C29: SMI×v_cap | D29: =F22*(F22/10) -> 4.1925625 | E29: Mass×velocity
A32: SECTION D: BLACK PHOENIX MATRIX
A33: Current RI: | B33: =CORE!D36 -> 6.885 | C33: Current SMI: | D33: =F22 -> 6.475 | E33: Posture: | F33: =CORE!B53 -> BLACK PHOENIX
A35: Quadrant | B35: RI | C35: SMI | D35: Description | E35: Example | F35: Strategy
A36: BLACK PHOENIX | B36: ≥5.5 | C36: ≥5.5 | D36: High resilience + high mobility | E36: Apple post-2007 | F36: Maintain and exploit
A37: INCUMBENT DEFENDER | B37: ≥5.5 | C37: <5.5 | D37: Strong defense, weak offense | E37: IBM pre-cloud | F37: Build SMI urgently
A38: DISRUPTIVE CHALLENGER | B38: <5.5 | C38: ≥5.5 | D38: Strong offense, weak defense | E38: Tesla 2015-19 | F38: Shore up RI
A39: DOUBLE EXPOSURE | B39: <5.5 | C39: <5.5 | D39: Vulnerable both | E39: Kodak 2000s | F39: Emergency restructure

Sheet Objectives
A1: =FALSE() -> FALSE
C3: =IF(SelectedBU="","",INDEX(ReportingUnits,SelectedBU,1)) -> Company 3 | G3: Objectives
C7: Time Horizon:
C8: What is the timeframe for which risks and opportunities have been identified and likelihood of occurrence is defined? | G8: 3
C11: List of the main objectives taken into consideration to identify the priority risks and opportunities
C13: Objectives (Priority Issues, Orientation Letter, etc) | D13: Strategic Priorities | E13: Operational performance | F13: License to operate | G13: Measures / Targets (Budget, Financial Figures, etc)
C43: =COUNTA(C$14:C42) -> 0
C44: Stakeholders interests (Corporate responsibility) have been considered to identify the risks

Sheet Risk Thresholds
C3: =IF(SelectedBU="","",INDEX(ReportingUnits,SelectedBU,1)) -> Company 3 | J3: Risk Scale Matrix
C6: Financial Impact Scale
F7: Loss of Cash Flow | K7: Probability Scale | M7: P Scale | N7: PMín | O7: PMáx
C8: As-planned Scenario (Base Case) = 12 months FCF target | E8: Negligible | F8: Minor | G8: Moderate | H8: Major | I8: Critical | M8: 1 | N8: 0 | O8: 0.1
E9: ="up to "&FIXED(E10,0,FALSE())&" mio USD" -> up to 2 mio USD | F9: ="from "&FIXED(E10,0,FALSE())&" to "&FIXED(F10,0,FALSE())&" mio USD" -> from 2 to 5 mio USD | G9: ="from "&FIXED(F10,0,FALSE())&" to "&FIXED(G10,0,FALSE())&" mio USD" -> from 5 to 10 mio USD | H9: ="from "&FIXED(G10,0,FALSE())&" to "&FIXED(H10,0,FALSE())&" mio USD" -> from 10 to 30 mio USD | I9: ="above "&FIXED(MatrixImpact!I13,0,FALSE())&" mio USD" -> above 30 mio USD | M9: 2 | N9: =O8 -> 0.1 | O9: 0.3
E10: =MatrixImpact!I10 -> 2 | F10: =MatrixImpact!I11 -> 5 | G10: =MatrixImpact!I12 -> 10 | H10: =MatrixImpact!I13 -> 30 | I10: 30 | J10: =IFERROR("= "&TEXT(I10/C9,"0.0%")&" base case","") | M10: 3 | N10: =O9 -> 0.3 | O10: 0.5
M11: 4 | N11: =O10 -> 0.5 | O11: 0.9
M12: 5 | N12: =O11 -> 0.9 | O12: 1
E13: Financial
F14: Maximum
F15: Catastrophic
E16: =FIXED(MatrixImpact!I13,0,FALSE())&" mio Euro" -> 30 mio Euro | F16: 5) Critical
E17: =G10 -> 10 | F17: 4) Major
E18: =F10 -> 5 | F18: 3) Moderate
E19: =E10 -> 2 | F19: 2) Minor
E20: 0 | F20: 1) Negligible | G20: =MatrixImpact!C4 -> 0 | H20: =MatrixImpact!C5 -> 0.1 | I20: =MatrixImpact!C6 -> 0.3 | J20: =MatrixImpact!C7 -> 0.5 | K20: =MatrixImpact!C8 -> 0.9 | L20: 1
G21: ="1: Rare: very unlikely to occur during the "&Parameters!E17 -> 1: Rare: very unlikely to occur during the next 3 - 5 years | H21: ="2: Not impossible to occur during the "&Parameters!E17 -> 2: Not impossible to occur during the next 3 - 5 years | I21: ="3: Possible: can be expected at least once in the "&Parameters!E17 -> 3: Possible: can be expected at least once in the next 3 - 5 years | J21: ="4: Likely to arise once during the "&Parameters!E17 -> 4: Likely to arise once during the next 3 - 5 years | K21: ="5: Almost certain: will occur several times during the "&Parameters!E17 -> 5: Almost certain: will occur several times during the next 3 - 5 years
C22: Non-Financial Impacts
D24: 1) Negligible | F24: 2) Minor | H24: 3) Moderate | J24: 4) Major | L24: 5) Critical
C25: Damage to physical integrity of the people | D25: - Person requires first aid treatment (eg cold compress, band aid etc) | F25: - Person requires medical treatment (such as prescribed medication, stitches or sutures etc) | H25: - Person is unable to perform all normal duties (modified or restricted work) | J25: - Single fatality or permanently disabling injury or illness (such as amputation, noise induced hearing loss, etc.) | L25: - Multiple fatalities of and/or extensive health impact on staff, contractors or public
C26: Loss of motivation & Degradation of social climate | D26: - Degradation of professional climate without impact on productivity | F26: - Temporary decrease in employee productivity | H26: - Long lasting decrease in employee productivity - Abnormally high staff turnover | J26: - Some key executives leave the group - Social conflict causing the interruption of the activity | L26: - A large number of key executives leave the group - Social conflict causing a long term stoppage of the activity
C27: Personal Liability (civil or criminal) for company executive | D27: - No personal liability | F27: - Subpoena - Police investigation | H27: - Financial penalty - Police custody | J27: - Suspended jail sentence for Employees or Executive - Loss of civil rights | L27: - Jail for employees, executive or directors
C28: Environmental | D28: - Environmental incident requiring information of public authorities | F28: - Environmental incident with limited action required | H28: - Environmental harm with medium term recovery (> 5 years) and/or requiring moderate rectification | J28: - Environmental harm with long term recovery (>10 years) and/or requiring significant rectification | L28: - Catastrophic and/or irreversible environmental harm
C29: Image | D29: - Minimal impact on reputation | F29: - Intra-industry knowledge of incident without media attention | H29: - Adverse local media coverage - Concerns on performance by financial analysts or shareholders | J29: - Adverse national media coverage - Significant decrease of shareholder support - Poor reputation as an employer | L29: - Adverse global media coverage - Major loss of shareholder support - Major boycott campaign

Sheet Top 10 Risks
C3: =IF(SelectedBU="","",INDEX(ReportingUnits,SelectedBU,1)) -> Company 3 | H3: ="Top 10 Risks that could occur within the "&Parameters!E17 -> Top 10 Risks that could occur within the next 3 - 5 years
C6: RikId | D6: Risk Title (with a light description) | E6: Causes and Factors (risk main causes and/or factors) | F6: Risk Owner | H6: Risk Assessment | K6: Future Direction (next quarter) | L6: Risk Management Plans | N6: ="Explanatory Comments as compared to the previous Quarterly reporting" -> Explanatory Comments as compared to the previous Quarterly reporting
F7: Name | G7: Function | H7: Impact | J7: Likelihood (Probability) | L7: Commitment to Additional Actions | M7: Due Date
H8: Financial | I8: Non-Financial
C9: 1
C10: 2
C11: 3
C12: 4
C13: 5
C14: 6
C15: 7
C16: 8
C17: 9
C18: 10
C19: 11
C20: 12
... C58: 50
D59: =COUNTA(D9:D58) -> 0 | E59: =COUNTA(E9:E58) -> 0 | F59: =COUNTA(F9:F58) -> 0 | G59: =COUNTA(G9:G58) -> 0

Sheet Top 10 Risks (Page 2)
C3: =IF(SelectedBU="","",INDEX(ReportingUnits,SelectedBU,1)) -> Company 3 | J3: ="Top 10 Risks that could occur within the "&Parameters!E17 -> Top 10 Risks that could occur within the next 3 - 5 years
C6: RiskId | D6: Risk Title (with a light description) | E6: Risk Response | F6: Who should know about the Risk? (outside the reporting unit) | H6: Who should know about mitigations? (outside the reporting unit) | J6: Assurance Providers | L6: Uncertainty about Financial Impact | O6: Financial Impact on MRF | P6: Details of the Calculation | Q6: Targeted Level of risks after implementation of mitigations
F7: Name | G7: Function | H7: Name | I7: Function | J7: Name | K7: Function | L7: Best case | M7: Most Credible | N7: Worst Case | Q7: Targeted Probability | R7: Targeted Impact
C9: =INDIRECT(ADDRESS(ROW(),COLUMN(),1,1,"Top 10 Risks")) -> 1 | D9: =INDIRECT(ADDRESS(ROW(),COLUMN(),1,1,"Top 10 Risks")) -> 0 | M9: =INDIRECT(ADDRESS(ROW(),8,1,1,"Top 10 Risks")) -> 0
C10: =INDIRECT(ADDRESS(ROW(),COLUMN(),1,1,"Top 10 Risks")) -> 2 | D10: =INDIRECT(ADDRESS(ROW(),COLUMN(),1,1,"Top 10 Risks")) -> 0 | M10: =INDIRECT(ADDRESS(ROW(),8,1,1,"Top 10 Risks")) -> 0
C11: =INDIRECT(ADDRESS(ROW(),COLUMN(),1,1,"Top 10 Risks")) -> 3 | D11: =INDIRECT(ADDRESS(ROW(),COLUMN(),1,1,"Top 10 Risks")) -> 0 | M11: =INDIRECT(ADDRESS(ROW(),8,1,1,"Top 10 Risks")) -> 0
C12: =INDIRECT(ADDRESS(ROW(),COLUMN(),1,1,"Top 10 Risks")) -> 4 | D12: =INDIRECT(ADDRESS(ROW(),COLUMN(),1,1,"Top 10 Risks")) -> 0 | M12: =INDIRECT(ADDRESS(ROW(),8,1,1,"Top 10 Risks")) -> 0
C13: =INDIRECT(ADDRESS(ROW(),COLUMN(),1,1,"Top 10 Risks")) -> 5 | D13: =INDIRECT(ADDRESS(ROW(),COLUMN(),1,1,"Top 10 Risks")) -> 0 | M13: =INDIRECT(ADDRESS(ROW(),8,1,1,"Top 10 Risks")) -> 0
C14: =INDIRECT(ADDRESS(ROW(),COLUMN(),1,1,"Top 10 Risks")) -> 6 | D14: =INDIRECT(ADDRESS(ROW(),COLUMN(),1,1,"Top 10 Risks")) -> 0 | M14: =INDIRECT(ADDRESS(ROW(),8,1,1,"Top 10 Risks")) -> 0
C15: =INDIRECT(ADDRESS(ROW(),COLUMN(),1,1,"Top 10 Risks")) -> 7 | D15: =INDIRECT(ADDRESS(ROW(),COLUMN(),1,1,"Top 10 Risks")) -> 0 | M15: =INDIRECT(ADDRESS(ROW(),8,1,1,"Top 10 Risks")) -> 0
C16: =INDIRECT(ADDRESS(ROW(),COLUMN(),1,1,"Top 10 Risks")) -> 8 | D16: =INDIRECT(ADDRESS(ROW(),COLUMN(),1,1,"Top 10 Risks")) -> 0 | M16: =INDIRECT(ADDRESS(ROW(),8,1,1,"Top 10 Risks")) -> 0
C17: =INDIRECT(ADDRESS(ROW(),COLUMN(),1,1,"Top 10 Risks")) -> 9 | D17: =INDIRECT(ADDRESS(ROW(),COLUMN(),1,1,"Top 10 Risks")) -> 0 | M17: =INDIRECT(ADDRESS(ROW(),8,1,1,"Top 10 Risks")) -> 0
C18: =INDIRECT(ADDRESS(ROW(),COLUMN(),1,1,"Top 10 Risks")) -> 10 | D18: =INDIRECT(ADDRESS(ROW(),COLUMN(),1,1,"Top 10 Risks")) -> 0 | M18: =INDIRECT(ADDRESS(ROW(),8,1,1,"Top 10 Risks")) -> 0
C19: =INDIRECT(ADDRESS(ROW(),COLUMN(),1,1,"Top 10 Risks")) -> 11 | D19: =INDIRECT(ADDRESS(ROW(),COLUMN(),1,1,"Top 10 Risks")) -> 0 | M19: =INDIRECT(ADDRESS(ROW(),8,1,1,"Top 10 Risks")) -> 0
C20: =INDIRECT(ADDRESS(ROW(),COLUMN(),1,1,"Top 10 Risks")) -> 12 | D20: =INDIRECT(ADDRESS(ROW(),COLUMN(),1,1,"Top 10 Risks")) -> 0 | M20: =INDIRECT(ADDRESS(ROW(),8,1,1,"Top 10 Risks")) -> 0
... C58: =INDIRECT(ADDRESS(ROW(),COLUMN(),1,1,"Top 10 Risks")) -> 50 | D58: =INDIRECT(ADDRESS(ROW(),COLUMN(),1,1,"Top 10 Risks")) -> 0 | M58: =INDIRECT(ADDRESS(ROW(),8,1,1,"Top 10 Risks")) -> 0
D59: =COUNTA(D9:D58)-COUNTIF(D9:D58,"") -> 50 | E59: =COUNTA(E9:E58) -> 0 | J59: =COUNTA(J9:J58) -> 0 | K59: =COUNTA(K9:K58) -> 0

Sheet RADAR
A1: RADAR — Risk Assessment Detection & Alert Register (v6.1 Full Calculation Chain)
A2: Each column = one verifiable calculation step | Blue = Input | Black = Formula | Green = Cross-sheet reference
A3: IDENTIFICATION | D3: RISK QUANTIFICATION | H3: VELOCITY & LORENTZ | K3: TIME & EARLY WARNING | P3: PHASE DIAGNOSTICS | R3: ENTROPY & URGENCY | U3: PALMER NOISE & MC BOUNDS | Y3: CLASSIFICATION & NOTES
D4: Input (0-1) | E4: Input | F4: MIN(10,MAX(1, 2×LN(€M+1))) | G4: Prob × Impact | H4: Input (1-10) | I4: H / Calib!C21 | J4: 1/√(1- MIN(v/v,0.95)²) | K4: (10-Vel)×3 | L4: Input (0-1) | M4: Input (0-1) | N4: TTS×Φ×C | O4: EW-TTS / γ | P4: MIN(1,MAX(0, (10-LEW)/10)) | Q4: 1 - PI | R4: Coh_Den!D16 | S4: S / S_max | T4: PI × γ × (2-S_ratio) | U4: η₀+0.3× (1-Freedom) | V4: LEW×(1- 1.645×η) | W4: LEW-TTS | X4: LEW×(1+ 1.645×η) | Y4: Based on Urgency Idx | Z4: Input | AA4: Input
A5: ID | B5: Risk Name | C5: Category | D5: Prob | E5: Impact (€M) | F5: Impact Score | G5: Exp Loss (€M) | H5: Velocity | I5: v / v_max | J5: Lorentz Factor γ | K5: TTS (months) | L5: Phase Prox | M5: Coh Factor | N5: EW-TTS | O5: Lorentz EW-TTS | P5: Phase Index | Q5: Freedom Index | R5: Entropy S | S5: Entropy Ratio | T5: Urgency Index | U5: Palmer Noise η | V5: MC P10 | W5: MC P50 | X5: MC P90 | Y5: Priority | Z5: Signal Str | AA5: Det Conf | AB5: Notes
A6: =IF('Top 10 Risks'!D9="","",'Top 10 Risks'!C9) | B6: =IF('Top 10 Risks'!D9="","",'Top 10 Risks'!D9) | C6: OPS | D6: =IF('Top 10 Risks'!D9="","",IF('Top 10 Risks'!J9=1,0.05,IF('Top 10 Risks'!J9=2,0.2,IF('Top 10 Risks'!J9=3,0.4,IF('Top 10 Risks'!J9=4,0.7,IF('Top 10 Risks'!J9=5,0.95,"")))))) | E6: =IF('Top 10 Risks'!D9="","",IF('Top 10 Risks'!H9=1,MatrixImpact!I10/2,IF('Top 10 Risks'!H9=2,SQRT(MatrixImpact!I10*MatrixImpact!I11),IF('Top 10 Risks'!H9=3,SQRT(MatrixImpact!I11*MatrixImpact!I12),IF('Top 10 Risks'!H9=4,SQRT(MatrixImpact!I12*MatrixImpact!I13),IF('Top 10 Risks'!H9=5,MatrixImpact!I13*1.5,"")))))) | F6: =IF(E6="","",MIN(10,MAX(1,2*LN(E6+1)))) | G6: =IF(D6="","",D6*E6) | H6: =IF('Top 10 Risks'!D9="","",IF('Top 10 Risks'!K9=1,7,IF('Top 10 Risks'!K9=2,5,IF('Top 10 Risks'!K9=3,3,IF('Top 10 Risks'!K9=4,9,5))))) | I6: =IF(H6="","",H6/Calibration!$C$21) | J6: =IF(I6="","",1/SQRT(1-MIN(I6,0.95)^2)) | K6: =IF(H6="","",(10-H6)*3) | L6: =IF(D6="","",MIN(0.95,D6*1.2)) | M6: =IF('Top 10 Risks'!D9="","",MIN(1,SUM('Risk Interaction Map'!E8:AI8)/MAX(1,COUNTA('Top 10 Risks'!D$9:D$39)-1))) | N6: =IF(K6="","",K6*L6*M6) | O6: =IF(N6="","",N6/J6) | P6: =IF(O6="","",MIN(1,MAX(0,(10-O6)/10))) | Q6: =IF(P6="","",1-P6) | R6: =Coherence_Density!$D$16 -> 1.0199813 | S6: =Coherence_Density!$D$18 -> 0.63375 | T6: =IF(P6="","",P6*J6*(2-S6)) | U6: =IF(Q6="","",Calibration!$C$20+0.3*(1-Q6)) | V6: =IF(O6="","",O6*(1-1.645*U6)) | W6: =IF(O6="","",O6) | X6: =IF(O6="","",O6*(1+1.645*U6)) | Y6: =IF(T6="","",IF(T6>=1.5,"CRITICAL",IF(T6>=1,"HIGH",IF(T6>=0.5,"MEDIUM","LOW")))) | Z6: 0.78 | AA6: 0.85 | AB6: =IF('Top 10 Risks'!E9="","",'Top 10 Risks'!E9)
A7: =IF('Top 10 Risks'!D10="","",'Top 10 Risks'!C10) | B7: =IF('Top 10 Risks'!D10="","",'Top 10 Risks'!D10) | C7: REG | D7: =IF('Top 10 Risks'!D10="","",IF('Top 10 Risks'!J10=1,0.05,IF('Top 10 Risks'!J10=2,0.2,IF('Top 10 Risks'!J10=3,0.4,IF('Top 10 Risks'!J10=4,0.7,IF('Top 10 Risks'!J10=5,0.95,"")))))) | E7: =IF('Top 10 Risks'!D10="","",IF('Top 10 Risks'!H10=1,MatrixImpact!I10/2,IF('Top 10 Risks'!H10=2,SQRT(MatrixImpact!I10*MatrixImpact!I11),IF('Top 10 Risks'!H10=3,SQRT(MatrixImpact!I11*MatrixImpact!I12),IF('Top 10 Risks'!H10=4,SQRT(MatrixImpact!I12*MatrixImpact!I13),IF('Top 10 Risks'!H10=5,MatrixImpact!I13*1.5,"")))))) | F7: =IF(E7="","",MIN(10,MAX(1,2*LN(E7+1)))) | G7: =IF(D7="","",D7*E7) | H7: =IF('Top 10 Risks'!D10="","",IF('Top 10 Risks'!K10=1,7,IF('Top 10 Risks'!K10=2,5,IF('Top 10 Risks'!K10=3,3,IF('Top 10 Risks'!K10=4,9,5))))) | I7: =IF(H7="","",H7/Calibration!$C$21) | J7: =IF(I7="","",1/SQRT(1-MIN(I7,0.95)^2)) | K7: =IF(H7="","",(10-H7)*3) | L7: =IF(D7="","",MIN(0.95,D7*1.2)) | M7: =IF('Top 10 Risks'!D10="","",MIN(1,SUM('Risk Interaction Map'!E9:AI9)/MAX(1,COUNTA('Top 10 Risks'!D$9:D$39)-1))) | N7: =IF(K7="","",K7*L7*M7) | O7: =IF(N7="","",N7/J7) | P7: =IF(O7="","",MIN(1,MAX(0,(10-O7)/10))) | Q7: =IF(P7="","",1-P7) | R7: =Coherence_Density!$D$16 -> 1.0199813 | S7: =Coherence_Density!$D$18 -> 0.63375 | T7: =IF(P7="","",P7*J7*(2-S7)) | U7: =IF(Q7="","",Calibration!$C$20+0.3*(1-Q7)) | V7: =IF(O7="","",O7*(1-1.645*U7)) | W7: =IF(O7="","",O7) | X7: =IF(O7="","",O7*(1+1.645*U7)) | Y7: =IF(T7="","",IF(T7>=1.5,"CRITICAL",IF(T7>=1,"HIGH",IF(T7>=0.5,"MEDIUM","LOW")))) | Z7: 0.65 | AA7: 0.8 | AB7: =IF('Top 10 Risks'!E10="","",'Top 10 Risks'!E10)
A8: =IF('Top 10 Risks'!D11="","",'Top 10 Risks'!C11) | B8: =IF('Top 10 Risks'!D11="","",'Top 10 Risks'!D11) | C8: TECH | D8: =IF('Top 10 Risks'!D11="","",IF('Top 10 Risks'!J11=1,0.05,IF('Top 10 Risks'!J11=2,0.2,IF('Top 10 Risks'!J11=3,0.4,IF('Top 10 Risks'!J11=4,0.7,IF('Top 10 Risks'!J11=5,0.95,"")))))) | E8: =IF('Top 10 Risks'!D11="","",IF('Top 10 Risks'!H11=1,MatrixImpact!I10/2,IF('Top 10 Risks'!H11=2,SQRT(MatrixImpact!I10*MatrixImpact!I11),IF('Top 10 Risks'!H11=3,SQRT(MatrixImpact!I11*MatrixImpact!I12),IF('Top 10 Risks'!H11=4,SQRT(MatrixImpact!I12*MatrixImpact!I13),IF('Top 10 Risks'!H11=5,MatrixImpact!I13*1.5,"")))))) | F8: =IF(E8="","",MIN(10,MAX(1,2*LN(E8+1)))) | G8: =IF(D8="","",D8*E8) | H8: =IF('Top 10 Risks'!D11="","",IF('Top 10 Risks'!K11=1,7,IF('Top 10 Risks'!K11=2,5,IF('Top 10 Risks'!K11=3,3,IF('Top 10 Risks'!K11=4,9,5))))) | I8: =IF(H8="","",H8/Calibration!$C$21) | J8: =IF(I8="","",1/SQRT(1-MIN(I8,0.95)^2)) | K8: =IF(H8="","",(10-H8)*3) | L8: =IF(D8="","",MIN(0.95,D8*1.2)) | M8: =IF('Top 10 Risks'!D11="","",MIN(1,SUM('Risk Interaction Map'!E10:AI10)/MAX(1,COUNTA('Top 10 Risks'!D$9:D$39)-1))) | N8: =IF(K8="","",K8*L8*M8) | O8: =IF(N8="","",N8/J8) | P8: =IF(O8="","",MIN(1,MAX(0,(10-O8)/10))) | Q8: =IF(P8="","",1-P8) | R8: =Coherence_Density!$D$16 -> 1.0199813 | S8: =Coherence_Density!$D$18 -> 0.63375 | T8: =IF(P8="","",P8*J8*(2-S8)) | U8: =IF(Q8="","",Calibration!$C$20+0.3*(1-Q8)) | V8: =IF(O8="","",O8*(1-1.645*U8)) | W8: =IF(O8="","",O8) | X8: =IF(O8="","",O8*(1+1.645*U8)) | Y8: =IF(T8="","",IF(T8>=1.5,"CRITICAL",IF(T8>=1,"HIGH",IF(T8>=0.5,"MEDIUM","LOW")))) | Z8: 0.82 | AA8: 0.9 | AB8: =IF('Top 10 Risks'!E11="","",'Top 10 Risks'!E11)
A9: =IF('Top 10 Risks'!D12="","",'Top 10 Risks'!C12) | B9: =IF('Top 10 Risks'!D12="","",'Top 10 Risks'!D12) | D9: =IF('Top 10 Risks'!D12="","",IF('Top 10 Risks'!J12=1,0.05,IF('Top 10 Risks'!J12=2,0.2,IF('Top 10 Risks'!J12=3,0.4,IF('Top 10 Risks'!J12=4,0.7,IF('Top 10 Risks'!J12=5,0.95,"")))))) | E9: =IF('Top 10 Risks'!D12="","",IF('Top 10 Risks'!H12=1,MatrixImpact!I10/2,IF('Top 10 Risks'!H12=2,SQRT(MatrixImpact!I10*MatrixImpact!I11),IF('Top 10 Risks'!H12=3,SQRT(MatrixImpact!I11*MatrixImpact!I12),IF('Top 10 Risks'!H12=4,SQRT(MatrixImpact!I12*MatrixImpact!I13),IF('Top 10 Risks'!H12=5,MatrixImpact!I13*1.5,"")))))) | F9: =IF(E9="","",MIN(10,MAX(1,2*LN(E9+1)))) | G9: =IF(D9="","",D9*E9) | H9: =IF('Top 10 Risks'!D12="","",IF('Top 10 Risks'!K12=1,7,IF('Top 10 Risks'!K12=2,5,IF('Top 10 Risks'!K12=3,3,IF('Top 10 Risks'!K12=4,9,5))))) | I9: =IF(H9="","",H9/Calibration!$C$21) | J9: =IF(I9="","",1/SQRT(1-MIN(I9,0.95)^2)) | K9: =IF(H9="","",(10-H9)*3) | L9: =IF(D9="","",MIN(0.95,D9*1.2)) | M9: =IF('Top 10 Risks'!D12="","",MIN(1,SUM('Risk Interaction Map'!E11:AI11)/MAX(1,COUNTA('Top 10 Risks'!D$9:D$39)-1))) | N9: =IF(K9="","",K9*L9*M9) | O9: =IF(N9="","",N9/J9) | P9: =IF(O9="","",MIN(1,MAX(0,(10-O9)/10))) | Q9: =IF(P9="","",1-P9) | R9: =Coherence_Density!$D$16 -> 1.0199813 | S9: =Coherence_Density!$D$18 -> 0.63375 | T9: =IF(P9="","",P9*J9*(2-S9)) | U9: =IF(Q9="","",Calibration!$C$20+0.3*(1-Q9)) | V9: =IF(O9="","",O9*(1-1.645*U9)) | W9: =IF(O9="","",O9) | X9: =IF(O9="","",O9*(1+1.645*U9)) | Y9: =IF(T9="","",IF(T9>=1.5,"CRITICAL",IF(T9>=1,"HIGH",IF(T9>=0.5,"MEDIUM","LOW")))) | AB9: =IF('Top 10 Risks'!E12="","",'Top 10 Risks'!E12)
A10: =IF('Top 10 Risks'!D13="","",'Top 10 Risks'!C13) | B10: =IF('Top 10 Risks'!D13="","",'Top 10 Risks'!D13) | D10: =IF('Top 10 Risks'!D13="","",IF('Top 10 Risks'!J13=1,0.05,IF('Top 10 Risks'!J13=2,0.2,IF('Top 10 Risks'!J13=3,0.4,IF('Top 10 Risks'!J13=4,0.7,IF('Top 10 Risks'!J13=5,0.95,"")))))) | E10: =IF('Top 10 Risks'!D13="","",IF('Top 10 Risks'!H13=1,MatrixImpact!I10/2,IF('Top 10 Risks'!H13=2,SQRT(MatrixImpact!I10*MatrixImpact!I11),IF('Top 10 Risks'!H13=3,SQRT(MatrixImpact!I11*MatrixImpact!I12),IF('Top 10 Risks'!H13=4,SQRT(MatrixImpact!I12*MatrixImpact!I13),IF('Top 10 Risks'!H13=5,MatrixImpact!I13*1.5,"")))))) | F10: =IF(E10="","",MIN(10,MAX(1,2*LN(E10+1)))) | G10: =IF(D10="","",D10*E10) | H10: =IF('Top 10 Risks'!D13="","",IF('Top 10 Risks'!K13=1,7,IF('Top 10 Risks'!K13=2,5,IF('Top 10 Risks'!K13=3,3,IF('Top 10 Risks'!K13=4,9,5))))) | I10: =IF(H10="","",H10/Calibration!$C$21) | J10: =IF(I10="","",1/SQRT(1-MIN(I10,0.95)^2)) | K10: =IF(H10="","",(10-H10)*3) | L10: =IF(D10="","",MIN(0.95,D10*1.2)) | M10: =IF('Top 10 Risks'!D13="","",MIN(1,SUM('Risk Interaction Map'!E12:AI12)/MAX(1,COUNTA('Top 10 Risks'!D$9:D$39)-1))) | N10: =IF(K10="","",K10*L10*M10) | O10: =IF(N10="","",N10/J10) | P10: =IF(O10="","",MIN(1,MAX(0,(10-O10)/10))) | Q10: =IF(P10="","",1-P10) | R10: =Coherence_Density!$D$16 -> 1.0199813 | S10: =Coherence_Density!$D$18 -> 0.63375 | T10: =IF(P10="","",P10*J10*(2-S10)) | U10: =IF(Q10="","",Calibration!$C$20+0.3*(1-Q10)) | V10: =IF(O10="","",O10*(1-1.645*U10)) | W10: =IF(O10="","",O10) | X10: =IF(O10="","",O10*(1+1.645*U10)) | Y10: =IF(T10="","",IF(T10>=1.5,"CRITICAL",IF(T10>=1,"HIGH",IF(T10>=0.5,"MEDIUM","LOW")))) | AB10: =IF('Top 10 Risks'!E13="","",'Top 10 Risks'!E13)
A11: =IF('Top 10 Risks'!D14="","",'Top 10 Risks'!C14) | B11: =IF('Top 10 Risks'!D14="","",'Top 10 Risks'!D14) | D11: =IF('Top 10 Risks'!D14="","",IF('Top 10 Risks'!J14=1,0.05,IF('Top 10 Risks'!J14=2,0.2,IF('Top 10 Risks'!J14=3,0.4,IF('Top 10 Risks'!J14=4,0.7,IF('Top 10 Risks'!J14=5,0.95,"")))))) | E11: =IF('Top 10 Risks'!D14="","",IF('Top 10 Risks'!H14=1,MatrixImpact!I10/2,IF('Top 10 Risks'!H14=2,SQRT(MatrixImpact!I10*MatrixImpact!I11),IF('Top 10 Risks'!H14=3,SQRT(MatrixImpact!I11*MatrixImpact!I12),IF('Top 10 Risks'!H14=4,SQRT(MatrixImpact!I12*MatrixImpact!I13),IF('Top 10 Risks'!H14=5,MatrixImpact!I13*1.5,"")))))) | F11: =IF(E11="","",MIN(10,MAX(1,2*LN(E11+1)))) | G11: =IF(D11="","",D11*E11) | H11: =IF('Top 10 Risks'!D14="","",IF('Top 10 Risks'!K14=1,7,IF('Top 10 Risks'!K14=2,5,IF('Top 10 Risks'!K14=3,3,IF('Top 10 Risks'!K14=4,9,5))))) | I11: =IF(H11="","",H11/Calibration!$C$21) | J11: =IF(I11="","",1/SQRT(1-MIN(I11,0.95)^2)) | K11: =IF(H11="","",(10-H11)*3) | L11: =IF(D11="","",MIN(0.95,D11*1.2)) | M11: =IF('Top 10 Risks'!D14="","",MIN(1,SUM('Risk Interaction Map'!E13:AI13)/MAX(1,COUNTA('Top 10 Risks'!D$9:D$39)-1))) | N11: =IF(K11="","",K11*L11*M11) | O11: =IF(N11="","",N11/J11) | P11: =IF(O11="","",MIN(1,MAX(0,(10-O11)/10))) | Q11: =IF(P11="","",1-P11) | R11: =Coherence_Density!$D$16 -> 1.0199813 | S11: =Coherence_Density!$D$18 -> 0.63375 | T11: =IF(P11="","",P11*J11*(2-S11)) | U11: =IF(Q11="","",Calibration!$C$20+0.3*(1-Q11)) | V11: =IF(O11="","",O11*(1-1.645*U11)) | W11: =IF(O11="","",O11) | X11: =IF(O11="","",O11*(1+1.645*U11)) | Y11: =IF(T11="","",IF(T11>=1.5,"CRITICAL",IF(T11>=1,"HIGH",IF(T11>=0.5,"MEDIUM","LOW")))) | AB11: =IF('Top 10 Risks'!E14="","",'Top 10 Risks'!E14)
A12: =IF('Top 10 Risks'!D15="","",'Top 10 Risks'!C15) | B12: =IF('Top 10 Risks'!D15="","",'Top 10 Risks'!D15) | D12: =IF('Top 10 Risks'!D15="","",IF('Top 10 Risks'!J15=1,0.05,IF('Top 10 Risks'!J15=2,0.2,IF('Top 10 Risks'!J15=3,0.4,IF('Top 10 Risks'!J15=4,0.7,IF('Top 10 Risks'!J15=5,0.95,"")))))) | E12: =IF('Top 10 Risks'!D15="","",IF('Top 10 Risks'!H15=1,MatrixImpact!I10/2,IF('Top 10 Risks'!H15=2,SQRT(MatrixImpact!I10*MatrixImpact!I11),IF('Top 10 Risks'!H15=3,SQRT(MatrixImpact!I11*MatrixImpact!I12),IF('Top 10 Risks'!H15=4,SQRT(MatrixImpact!I12*MatrixImpact!I13),IF('Top 10 Risks'!H15=5,MatrixImpact!I13*1.5,"")))))) | F12: =IF(E12="","",MIN(10,MAX(1,2*LN(E12+1)))) | G12: =IF(D12="","",D12*E12) | H12: =IF('Top 10 Risks'!D15="","",IF('Top 10 Risks'!K15=1,7,IF('Top 10 Risks'!K15=2,5,IF('Top 10 Risks'!K15=3,3,IF('Top 10 Risks'!K15=4,9,5))))) | I12: =IF(H12="","",H12/Calibration!$C$21) | J12: =IF(I12="","",1/SQRT(1-MIN(I12,0.95)^2)) | K12: =IF(H12="","",(10-H12)*3) | L12: =IF(D12="","",MIN(0.95,D12*1.2)) | M12: =IF('Top 10 Risks'!D15="","",MIN(1,SUM('Risk Interaction Map'!E14:AI14)/MAX(1,COUNTA('Top 10 Risks'!D$9:D$39)-1))) | N12: =IF(K12="","",K12*L12*M12) | O12: =IF(N12="","",N12/J12) | P12: =IF(O12="","",MIN(1,MAX(0,(10-O12)/10))) | Q12: =IF(P12="","",1-P12) | R12: =Coherence_Density!$D$16 -> 1.0199813 | S12: =Coherence_Density!$D$18 -> 0.63375 | T12: =IF(P12="","",P12*J12*(2-S12)) | U12: =IF(Q12="","",Calibration!$C$20+0.3*(1-Q12)) | V12: =IF(O12="","",O12*(1-1.645*U12)) | W12: =IF(O12="","",O12) | X12: =IF(O12="","",O12*(1+1.645*U12)) | Y12: =IF(T12="","",IF(T12>=1.5,"CRITICAL",IF(T12>=1,"HIGH",IF(T12>=0.5,"MEDIUM","LOW")))) | AB12: =IF('Top 10 Risks'!E15="","",'Top 10 Risks'!E15)
A13: =IF('Top 10 Risks'!D16="","",'Top 10 Risks'!C16) | B13: =IF('Top 10 Risks'!D16="","",'Top 10 Risks'!D16) | D13: =IF('Top 10 Risks'!D16="","",IF('Top 10 Risks'!J16=1,0.05,IF('Top 10 Risks'!J16=2,0.2,IF('Top 10 Risks'!J16=3,0.4,IF('Top 10 Risks'!J16=4,0.7,IF('Top 10 Risks'!J16=5,0.95,"")))))) | E13: =IF('Top 10 Risks'!D16="","",IF('Top 10 Risks'!H16=1,MatrixImpact!I10/2,IF('Top 10 Risks'!H16=2,SQRT(MatrixImpact!I10*MatrixImpact!I11),IF('Top 10 Risks'!H16=3,SQRT(MatrixImpact!I11*MatrixImpact!I12),IF('Top 10 Risks'!H16=4,SQRT(MatrixImpact!I12*MatrixImpact!I13),IF('Top 10 Risks'!H16=5,MatrixImpact!I13*1.5,"")))))) | F13: =IF(E13="","",MIN(10,MAX(1,2*LN(E13+1)))) | G13: =IF(D13="","",D13*E13) | H13: =IF('Top 10 Risks'!D16="","",IF('Top 10 Risks'!K16=1,7,IF('Top 10 Risks'!K16=2,5,IF('Top 10 Risks'!K16=3,3,IF('Top 10 Risks'!K16=4,9,5))))) | I13: =IF(H13="","",H13/Calibration!$C$21) | J13: =IF(I13="","",1/SQRT(1-MIN(I13,0.95)^2)) | K13: =IF(H13="","",(10-H13)*3) | L13: =IF(D13="","",MIN(0.95,D13*1.2)) | M13: =IF('Top 10 Risks'!D16="","",MIN(1,SUM('Risk Interaction Map'!E15:AI15)/MAX(1,COUNTA('Top 10 Risks'!D$9:D$39)-1))) | N13: =IF(K13="","",K13*L13*M13) | O13: =IF(N13="","",N13/J13) | P13: =IF(O13="","",MIN(1,MAX(0,(10-O13)/10))) | Q13: =IF(P13="","",1-P13) | R13: =Coherence_Density!$D$16 -> 1.0199813 | S13: =Coherence_Density!$D$18 -> 0.63375 | T13: =IF(P13="","",P13*J13*(2-S13)) | U13: =IF(Q13="","",Calibration!$C$20+0.3*(1-Q13)) | V13: =IF(O13="","",O13*(1-1.645*U13)) | W13: =IF(O13="","",O13) | X13: =IF(O13="","",O13*(1+1.645*U13)) | Y13: =IF(T13="","",IF(T13>=1.5,"CRITICAL",IF(T13>=1,"HIGH",IF(T13>=0.5,"MEDIUM","LOW")))) | AB13: =IF('Top 10 Risks'!E16="","",'Top 10 Risks'!E16)
A14: =IF('Top 10 Risks'!D17="","",'Top 10 Risks'!C17) | B14: =IF('Top 10 Risks'!D17="","",'Top 10 Risks'!D17) | D14: =IF('Top 10 Risks'!D17="","",IF('Top 10 Risks'!J17=1,0.05,IF('Top 10 Risks'!J17=2,0.2,IF('Top 10 Risks'!J17=3,0.4,IF('Top 10 Risks'!J17=4,0.7,IF('Top 10 Risks'!J17=5,0.95,"")))))) | E14: =IF('Top 10 Risks'!D17="","",IF('Top 10 Risks'!H17=1,MatrixImpact!I10/2,IF('Top 10 Risks'!H17=2,SQRT(MatrixImpact!I10*MatrixImpact!I11),IF('Top 10 Risks'!H17=3,SQRT(MatrixImpact!I11*MatrixImpact!I12),IF('Top 10 Risks'!H17=4,SQRT(MatrixImpact!I12*MatrixImpact!I13),IF('Top 10 Risks'!H17=5,MatrixImpact!I13*1.5,"")))))) | F14: =IF(E14="","",MIN(10,MAX(1,2*LN(E14+1)))) | G14: =IF(D14="","",D14*E14) | H14: =IF('Top 10 Risks'!D17="","",IF('Top 10 Risks'!K17=1,7,IF('Top 10 Risks'!K17=2,5,IF('Top 10 Risks'!K17=3,3,IF('Top 10 Risks'!K17=4,9,5))))) | I14: =IF(H14="","",H14/Calibration!$C$21) | J14: =IF(I14="","",1/SQRT(1-MIN(I14,0.95)^2)) | K14: =IF(H14="","",(10-H14)*3) | L14: =IF(D14="","",MIN(0.95,D14*1.2)) | M14: =IF('Top 10 Risks'!D17="","",MIN(1,SUM('Risk Interaction Map'!E16:AI16)/MAX(1,COUNTA('Top 10 Risks'!D$9:D$39)-1))) | N14: =IF(K14="","",K14*L14*M14) | O14: =IF(N14="","",N14/J14) | P14: =IF(O14="","",MIN(1,MAX(0,(10-O14)/10))) | Q14: =IF(P14="","",1-P14) | R14: =Coherence_Density!$D$16 -> 1.0199813 | S14: =Coherence_Density!$D$18 -> 0.63375 | T14: =IF(P14="","",P14*J14*(2-S14)) | U14: =IF(Q14="","",Calibration!$C$20+0.3*(1-Q14)) | V14: =IF(O14="","",O14*(1-1.645*U14)) | W14: =IF(O14="","",O14) | X14: =IF(O14="","",O14*(1+1.645*U14)) | Y14: =IF(T14="","",IF(T14>=1.5,"CRITICAL",IF(T14>=1,"HIGH",IF(T14>=0.5,"MEDIUM","LOW")))) | AB14: =IF('Top 10 Risks'!E17="","",'Top 10 Risks'!E17)
A15: =IF('Top 10 Risks'!D18="","",'Top 10 Risks'!C18) | B15: =IF('Top 10 Risks'!D18="","",'Top 10 Risks'!D18) | D15: =IF('Top 10 Risks'!D18="","",IF('Top 10 Risks'!J18=1,0.05,IF('Top 10 Risks'!J18=2,0.2,IF('Top 10 Risks'!J18=3,0.4,IF('Top 10 Risks'!J18=4,0.7,IF('Top 10 Risks'!J18=5,0.95,"")))))) | E15: =IF('Top 10 Risks'!D18="","",IF('Top 10 Risks'!H18=1,MatrixImpact!I10/2,IF('Top 10 Risks'!H18=2,SQRT(MatrixImpact!I10*MatrixImpact!I11),IF('Top 10 Risks'!H18=3,SQRT(MatrixImpact!I11*MatrixImpact!I12),IF('Top 10 Risks'!H18=4,SQRT(MatrixImpact!I12*MatrixImpact!I13),IF('Top 10 Risks'!H18=5,MatrixImpact!I13*1.5,"")))))) | F15: =IF(E15="","",MIN(10,MAX(1,2*LN(E15+1)))) | G15: =IF(D15="","",D15*E15) | H15: =IF('Top 10 Risks'!D18="","",IF('Top 10 Risks'!K18=1,7,IF('Top 10 Risks'!K18=2,5,IF('Top 10 Risks'!K18=3,3,IF('Top 10 Risks'!K18=4,9,5))))) | I15: =IF(H15="","",H15/Calibration!$C$21) | J15: =IF(I15="","",1/SQRT(1-MIN(I15,0.95)^2)) | K15: =IF(H15="","",(10-H15)*3) | L15: =IF(D15="","",MIN(0.95,D15*1.2)) | M15: =IF('Top 10 Risks'!D18="","",MIN(1,SUM('Risk Interaction Map'!E17:AI17)/MAX(1,COUNTA('Top 10 Risks'!D$9:D$39)-1))) | N15: =IF(K15="","",K15*L15*M15) | O15: =IF(N15="","",N15/J15) | P15: =IF(O15="","",MIN(1,MAX(0,(10-O15)/10))) | Q15: =IF(P15="","",1-P15) | R15: =Coherence_Density!$D$16 -> 1.0199813 | S15: =Coherence_Density!$D$18 -> 0.63375 | T15: =IF(P15="","",P15*J15*(2-S15)) | U15: =IF(Q15="","",Calibration!$C$20+0.3*(1-Q15)) | V15: =IF(O15="","",O15*(1-1.645*U15)) | W15: =IF(O15="","",O15) | X15: =IF(O15="","",O15*(1+1.645*U15)) | Y15: =IF(T15="","",IF(T15>=1.5,"CRITICAL",IF(T15>=1,"HIGH",IF(T15>=0.5,"MEDIUM","LOW")))) | AB15: =IF('Top 10 Risks'!E18="","",'Top 10 Risks'!E18)
A16: =IF('Top 10 Risks'!D19="","",'Top 10 Risks'!C19) | B16: =IF('Top 10 Risks'!D19="","",'Top 10 Risks'!D19) | D16: =IF('Top 10 Risks'!D19="","",IF('Top 10 Risks'!J19=1,0.05,IF('Top 10 Risks'!J19=2,0.2,IF('Top 10 Risks'!J19=3,0.4,IF('Top 10 Risks'!J19=4,0.7,IF('Top 10 Risks'!J19=5,0.95,"")))))) | E16: =IF('Top 10 Risks'!D19="","",IF('Top 10 Risks'!H19=1,MatrixImpact!I10/2,IF('Top 10 Risks'!H19=2,SQRT(MatrixImpact!I10*MatrixImpact!I11),IF('Top 10 Risks'!H19=3,SQRT(MatrixImpact!I11*MatrixImpact!I12),IF('Top 10 Risks'!H19=4,SQRT(MatrixImpact!I12*MatrixImpact!I13),IF('Top 10 Risks'!H19=5,MatrixImpact!I13*1.5,"")))))) | F16: =IF(E16="","",MIN(10,MAX(1,2*LN(E16+1)))) | G16: =IF(D16="","",D16*E16) | H16: =IF('Top 10 Risks'!D19="","",IF('Top 10 Risks'!K19=1,7,IF('Top 10 Risks'!K19=2,5,IF('Top 10 Risks'!K19=3,3,IF('Top 10 Risks'!K19=4,9,5))))) | I16: =IF(H16="","",H16/Calibration!$C$21) | J16: =IF(I16="","",1/SQRT(1-MIN(I16,0.95)^2)) | K16: =IF(H16="","",(10-H16)*3) | L16: =IF(D16="","",MIN(0.95,D16*1.2)) | M16: =IF('Top 10 Risks'!D19="","",MIN(1,SUM('Risk Interaction Map'!E18:AI18)/MAX(1,COUNTA('Top 10 Risks'!D$9:D$39)-1))) | N16: =IF(K16="","",K16*L16*M16) | O16: =IF(N16="","",N16/J16) | P16: =IF(O16="","",MIN(1,MAX(0,(10-O16)/10))) | Q16: =IF(P16="","",1-P16) | R16: =Coherence_Density!$D$16 -> 1.0199813 | S16: =Coherence_Density!$D$18 -> 0.63375 | T16: =IF(P16="","",P16*J16*(2-S16)) | U16: =IF(Q16="","",Calibration!$C$20+0.3*(1-Q16)) | V16: =IF(O16="","",O16*(1-1.645*U16)) | W16: =IF(O16="","",O16) | X16: =IF(O16="","",O16*(1+1.645*U16)) | Y16: =IF(T16="","",IF(T16>=1.5,"CRITICAL",IF(T16>=1,"HIGH",IF(T16>=0.5,"MEDIUM","LOW")))) | AB16: =IF('Top 10 Risks'!E19="","",'Top 10 Risks'!E19)
A17: =IF('Top 10 Risks'!D20="","",'Top 10 Risks'!C20) | B17: =IF('Top 10 Risks'!D20="","",'Top 10 Risks'!D20) | D17: =IF('Top 10 Risks'!D20="","",IF('Top 10 Risks'!J20=1,0.05,IF('Top 10 Risks'!J20=2,0.2,IF('Top 10 Risks'!J20=3,0.4,IF('Top 10 Risks'!J20=4,0.7,IF('Top 10 Risks'!J20=5,0.95,"")))))) | E17: =IF('Top 10 Risks'!D20="","",IF('Top 10 Risks'!H20=1,MatrixImpact!I10/2,IF('Top 10 Risks'!H20=2,SQRT(MatrixImpact!I10*MatrixImpact!I11),IF('Top 10 Risks'!H20=3,SQRT(MatrixImpact!I11*MatrixImpact!I12),IF('Top 10 Risks'!H20=4,SQRT(MatrixImpact!I12*MatrixImpact!I13),IF('Top 10 Risks'!H20=5,MatrixImpact!I13*1.5,"")))))) | F17: =IF(E17="","",MIN(10,MAX(1,2*LN(E17+1)))) | G17: =IF(D17="","",D17*E17) | H17: =IF('Top 10 Risks'!D20="","",IF('Top 10 Risks'!K20=1,7,IF('Top 10 Risks'!K20=2,5,IF('Top 10 Risks'!K20=3,3,IF('Top 10 Risks'!K20=4,9,5))))) | I17: =IF(H17="","",H17/Calibration!$C$21) | J17: =IF(I17="","",1/SQRT(1-MIN(I17,0.95)^2)) | K17: =IF(H17="","",(10-H17)*3) | L17: =IF(D17="","",MIN(0.95,D17*1.2)) | M17: =IF('Top 10 Risks'!D20="","",MIN(1,SUM('Risk Interaction Map'!E19:AI19)/MAX(1,COUNTA('Top 10 Risks'!D$9:D$39)-1))) | N17: =IF(K17="","",K17*L17*M17) | O17: =IF(N17="","",N17/J17) | P17: =IF(O17="","",MIN(1,MAX(0,(10-O17)/10))) | Q17: =IF(P17="","",1-P17) | R17: =Coherence_Density!$D$16 -> 1.0199813 | S17: =Coherence_Density!$D$18 -> 0.63375 | T17: =IF(P17="","",P17*J17*(2-S17)) | U17: =IF(Q17="","",Calibration!$C$20+0.3*(1-Q17)) | V17: =IF(O17="","",O17*(1-1.645*U17)) | W17: =IF(O17="","",O17) | X17: =IF(O17="","",O17*(1+1.645*U17)) | Y17: =IF(T17="","",IF(T17>=1.5,"CRITICAL",IF(T17>=1,"HIGH",IF(T17>=0.5,"MEDIUM","LOW")))) | AB17: =IF('Top 10 Risks'!E20="","",'Top 10 Risks'!E20)
A18: =IF('Top 10 Risks'!D21="","",'Top 10 Risks'!C21) | B18: =IF('Top 10 Risks'!D21="","",'Top 10 Risks'!D21) | D18: =IF('Top 10 Risks'!D21="","",IF('Top 10 Risks'!J21=1,0.05,IF('Top 10 Risks'!J21=2,0.2,IF('Top 10 Risks'!J21=3,0.4,IF('Top 10 Risks'!J21=4,0.7,IF('Top 10 Risks'!J21=5,0.95,"")))))) | E18: =IF('Top 10 Risks'!D21="","",IF('Top 10 Risks'!H21=1,MatrixImpact!I10/2,IF('Top 10 Risks'!H21=2,SQRT(MatrixImpact!I10*MatrixImpact!I11),IF('Top 10 Risks'!H21=3,SQRT(MatrixImpact!I11*MatrixImpact!I12),IF('Top 10 Risks'!H21=4,SQRT(MatrixImpact!I12*MatrixImpact!I13),IF('Top 10 Risks'!H21=5,MatrixImpact!I13*1.5,"")))))) | F18: =IF(E18="","",MIN(10,MAX(1,2*LN(E18+1)))) | G18: =IF(D18="","",D18*E18) | H18: =IF('Top 10 Risks'!D21="","",IF('Top 10 Risks'!K21=1,7,IF('Top 10 Risks'!K21=2,5,IF('Top 10 Risks'!K21=3,3,IF('Top 10 Risks'!K21=4,9,5))))) | I18: =IF(H18="","",H18/Calibration!$C$21) | J18: =IF(I18="","",1/SQRT(1-MIN(I18,0.95)^2)) | K18: =IF(H18="","",(10-H18)*3) | L18: =IF(D18="","",MIN(0.95,D18*1.2)) | M18: =IF('Top 10 Risks'!D21="","",MIN(1,SUM('Risk Interaction Map'!E20:AI20)/MAX(1,COUNTA('Top 10 Risks'!D$9:D$39)-1))) | N18: =IF(K18="","",K18*L18*M18) | O18: =IF(N18="","",N18/J18) | P18: =IF(O18="","",MIN(1,MAX(0,(10-O18)/10))) | Q18: =IF(P18="","",1-P18) | R18: =Coherence_Density!$D$16 -> 1.0199813 | S18: =Coherence_Density!$D$18 -> 0.63375 | T18: =IF(P18="","",P18*J18*(2-S18)) | U18: =IF(Q18="","",Calibration!$C$20+0.3*(1-Q18)) | V18: =IF(O18="","",O18*(1-1.645*U18)) | W18: =IF(O18="","",O18) | X18: =IF(O18="","",O18*(1+1.645*U18)) | Y18: =IF(T18="","",IF(T18>=1.5,"CRITICAL",IF(T18>=1,"HIGH",IF(T18>=0.5,"MEDIUM","LOW")))) | AB18: =IF('Top 10 Risks'!E21="","",'Top 10 Risks'!E21)
A19: =IF('Top 10 Risks'!D22="","",'Top 10 Risks'!C22) | B19: =IF('Top 10 Risks'!D22="","",'Top 10 Risks'!D22) | D19: =IF('Top 10 Risks'!D22="","",IF('Top 10 Risks'!J22=1,0.05,IF('Top 10 Risks'!J22=2,0.2,IF('Top 10 Risks'!J22=3,0.4,IF('Top 10 Risks'!J22=4,0.7,IF('Top 10 Risks'!J22=5,0.95,"")))))) | E19: =IF('Top 10 Risks'!D22="","",IF('Top 10 Risks'!H22=1,MatrixImpact!I10/2,IF('Top 10 Risks'!H22=2,SQRT(MatrixImpact!I10*MatrixImpact!I11),IF('Top 10 Risks'!H22=3,SQRT(MatrixImpact!I11*MatrixImpact!I12),IF('Top 10 Risks'!H22=4,SQRT(MatrixImpact!I12*MatrixImpact!I13),IF('Top 10 Risks'!H22=5,MatrixImpact!I13*1.5,"")))))) | F19: =IF(E19="","",MIN(10,MAX(1,2*LN(E19+1)))) | G19: =IF(D19="","",D19*E19) | H19: =IF('Top 10 Risks'!D22="","",IF('Top 10 Risks'!K22=1,7,IF('Top 10 Risks'!K22=2,5,IF('Top 10 Risks'!K22=3,3,IF('Top 10 Risks'!K22=4,9,5))))) | I19: =IF(H19="","",H19/Calibration!$C$21) | J19: =IF(I19="","",1/SQRT(1-MIN(I19,0.95)^2)) | K19: =IF(H19="","",(10-H19)*3) | L19: =IF(D19="","",MIN(0.95,D19*1.2)) | M19: =IF('Top 10 Risks'!D22="","",MIN(1,SUM('Risk Interaction Map'!E21:AI21)/MAX(1,COUNTA('Top 10 Risks'!D$9:D$39)-1))) | N19: =IF(K19="","",K19*L19*M19) | O19: =IF(N19="","",N19/J19) | P19: =IF(O19="","",MIN(1,MAX(0,(10-O19)/10))) | Q19: =IF(P19="","",1-P19) | R19: =Coherence_Density!$D$16 -> 1.0199813 | S19: =Coherence_Density!$D$18 -> 0.63375 | T19: =IF(P19="","",P19*J19*(2-S19)) | U19: =IF(Q19="","",Calibration!$C$20+0.3*(1-Q19)) | V19: =IF(O19="","",O19*(1-1.645*U19)) | W19: =IF(O19="","",O19) | X19: =IF(O19="","",O19*(1+1.645*U19)) | Y19: =IF(T19="","",IF(T19>=1.5,"CRITICAL",IF(T19>=1,"HIGH",IF(T19>=0.5,"MEDIUM","LOW")))) | AB19: =IF('Top 10 Risks'!E22="","",'Top 10 Risks'!E22)
A20: =IF('Top 10 Risks'!D23="","",'Top 10 Risks'!C23) | B20: =IF('Top 10 Risks'!D23="","",'Top 10 Risks'!D23) | D20: =IF('Top 10 Risks'!D23="","",IF('Top 10 Risks'!J23=1,0.05,IF('Top 10 Risks'!J23=2,0.2,IF('Top 10 Risks'!J23=3,0.4,IF('Top 10 Risks'!J23=4,0.7,IF('Top 10 Risks'!J23=5,0.95,"")))))) | E20: =IF('Top 10 Risks'!D23="","",IF('Top 10 Risks'!H23=1,MatrixImpact!I10/2,IF('Top 10 Risks'!H23=2,SQRT(MatrixImpact!I10*MatrixImpact!I11),IF('Top 10 Risks'!H23=3,SQRT(MatrixImpact!I11*MatrixImpact!I12),IF('Top 10 Risks'!H23=4,SQRT(MatrixImpact!I12*MatrixImpact!I13),IF('Top 10 Risks'!H23=5,MatrixImpact!I13*1.5,"")))))) | F20: =IF(E20="","",MIN(10,MAX(1,2*LN(E20+1)))) | G20: =IF(D20="","",D20*E20) | H20: =IF('Top 10 Risks'!D23="","",IF('Top 10 Risks'!K23=1,7,IF('Top 10 Risks'!K23=2,5,IF('Top 10 Risks'!K23=3,3,IF('Top 10 Risks'!K23=4,9,5))))) | I20: =IF(H20="","",H20/Calibration!$C$21) | J20: =IF(I20="","",1/SQRT(1-MIN(I20,0.95)^2)) | K20: =IF(H20="","",(10-H20)*3) | L20: =IF(D20="","",MIN(0.95,D20*1.2)) | M20: =IF('Top 10 Risks'!D23="","",MIN(1,SUM('Risk Interaction Map'!E22:AI22)/MAX(1,COUNTA('Top 10 Risks'!D$9:D$39)-1))) | N20: =IF(K20="","",K20*L20*M20) | O20: =IF(N20="","",N20/J20) | P20: =IF(O20="","",MIN(1,MAX(0,(10-O20)/10))) | Q20: =IF(P20="","",1-P20) | R20: =Coherence_Density!$D$16 -> 1.0199813 | S20: =Coherence_Density!$D$18 -> 0.63375 | T20: =IF(P20="","",P20*J20*(2-S20)) | U20: =IF(Q20="","",Calibration!$C$20+0.3*(1-Q20)) | V20: =IF(O20="","",O20*(1-1.645*U20)) | W20: =IF(O20="","",O20) | X20: =IF(O20="","",O20*(1+1.645*U20)) | Y20: =IF(T20="","",IF(T20>=1.5,"CRITICAL",IF(T20>=1,"HIGH",IF(T20>=0.5,"MEDIUM","LOW")))) | AB20: =IF('Top 10 Risks'!E23="","",'Top 10 Risks'!E23)
A21: =IF('Top 10 Risks'!D24="","",'Top 10 Risks'!C24) | B21: =IF('Top 10 Risks'!D24="","",'Top 10 Risks'!D24) | D21: =IF('Top 10 Risks'!D24="","",IF('Top 10 Risks'!J24=1,0.05,IF('Top 10 Risks'!J24=2,0.2,IF('Top 10 Risks'!J24=3,0.4,IF('Top 10 Risks'!J24=4,0.7,IF('Top 10 Risks'!J24=5,0.95,"")))))) | E21: =IF('Top 10 Risks'!D24="","",IF('Top 10 Risks'!H24=1,MatrixImpact!I10/2,IF('Top 10 Risks'!H24=2,SQRT(MatrixImpact!I10*MatrixImpact!I11),IF('Top 10 Risks'!H24=3,SQRT(MatrixImpact!I11*MatrixImpact!I12),IF('Top 10 Risks'!H24=4,SQRT(MatrixImpact!I12*MatrixImpact!I13),IF('Top 10 Risks'!H24=5,MatrixImpact!I13*1.5,"")))))) | F21: =IF(E21="","",MIN(10,MAX(1,2*LN(E21+1)))) | G21: =IF(D21="","",D21*E21) | H21: =IF('Top 10 Risks'!D24="","",IF('Top 10 Risks'!K24=1,7,IF('Top 10 Risks'!K24=2,5,IF('Top 10 Risks'!K24=3,3,IF('Top 10 Risks'!K24=4,9,5))))) | I21: =IF(H21="","",H21/Calibration!$C$21) | J21: =IF(I21="","",1/SQRT(1-MIN(I21,0.95)^2)) | K21: =IF(H21="","",(10-H21)*3) | L21: =IF(D21="","",MIN(0.95,D21*1.2)) | M21: =IF('Top 10 Risks'!D24="","",MIN(1,SUM('Risk Interaction Map'!E23:AI23)/MAX(1,COUNTA('Top 10 Risks'!D$9:D$39)-1))) | N21: =IF(K21="","",K21*L21*M21) | O21: =IF(N21="","",N21/J21) | P21: =IF(O21="","",MIN(1,MAX(0,(10-O21)/10))) | Q21: =IF(P21="","",1-P21) | R21: =Coherence_Density!$D$16 -> 1.0199813 | S21: =Coherence_Density!$D$18 -> 0.63375 | T21: =IF(P21="","",P21*J21*(2-S21)) | U21: =IF(Q21="","",Calibration!$C$20+0.3*(1-Q21)) | V21: =IF(O21="","",O21*(1-1.645*U21)) | W21: =IF(O21="","",O21) | X21: =IF(O21="","",O21*(1+1.645*U21)) | Y21: =IF(T21="","",IF(T21>=1.5,"CRITICAL",IF(T21>=1,"HIGH",IF(T21>=0.5,"MEDIUM","LOW")))) | AB21: =IF('Top 10 Risks'!E24="","",'Top 10 Risks'!E24)
A22: =IF('Top 10 Risks'!D25="","",'Top 10 Risks'!C25) | B22: =IF('Top 10 Risks'!D25="","",'Top 10 Risks'!D25) | D22: =IF('Top 10 Risks'!D25="","",IF('Top 10 Risks'!J25=1,0.05,IF('Top 10 Risks'!J25=2,0.2,IF('Top 10 Risks'!J25=3,0.4,IF('Top 10 Risks'!J25=4,0.7,IF('Top 10 Risks'!J25=5,0.95,"")))))) | E22: =IF('Top 10 Risks'!D25="","",IF('Top 10 Risks'!H25=1,MatrixImpact!I10/2,IF('Top 10 Risks'!H25=2,SQRT(MatrixImpact!I10*MatrixImpact!I11),IF('Top 10 Risks'!H25=3,SQRT(MatrixImpact!I11*MatrixImpact!I12),IF('Top 10 Risks'!H25=4,SQRT(MatrixImpact!I12*MatrixImpact!I13),IF('Top 10 Risks'!H25=5,MatrixImpact!I13*1.5,"")))))) | F22: =IF(E22="","",MIN(10,MAX(1,2*LN(E22+1)))) | G22: =IF(D22="","",D22*E22) | H22: =IF('Top 10 Risks'!D25="","",IF('Top 10 Risks'!K25=1,7,IF('Top 10 Risks'!K25=2,5,IF('Top 10 Risks'!K25=3,3,IF('Top 10 Risks'!K25=4,9,5))))) | I22: =IF(H22="","",H22/Calibration!$C$21) | J22: =IF(I22="","",1/SQRT(1-MIN(I22,0.95)^2)) | K22: =IF(H22="","",(10-H22)*3) | L22: =IF(D22="","",MIN(0.95,D22*1.2)) | M22: =IF('Top 10 Risks'!D25="","",MIN(1,SUM('Risk Interaction Map'!E24:AI24)/MAX(1,COUNTA('Top 10 Risks'!D$9:D$39)-1))) | N22: =IF(K22="","",K22*L22*M22) | O22: =IF(N22="","",N22/J22) | P22: =IF(O22="","",MIN(1,MAX(0,(10-O22)/10))) | Q22: =IF(P22="","",1-P22) | R22: =Coherence_Density!$D$16 -> 1.0199813 | S22: =Coherence_Density!$D$18 -> 0.63375 | T22: =IF(P22="","",P22*J22*(2-S22)) | U22: =IF(Q22="","",Calibration!$C$20+0.3*(1-Q22)) | V22: =IF(O22="","",O22*(1-1.645*U22)) | W22: =IF(O22="","",O22) | X22: =IF(O22="","",O22*(1+1.645*U22)) | Y22: =IF(T22="","",IF(T22>=1.5,"CRITICAL",IF(T22>=1,"HIGH",IF(T22>=0.5,"MEDIUM","LOW")))) | AB22: =IF('Top 10 Risks'!E25="","",'Top 10 Risks'!E25)
A23: =IF('Top 10 Risks'!D26="","",'Top 10 Risks'!C26) | B23: =IF('Top 10 Risks'!D26="","",'Top 10 Risks'!D26) | D23: =IF('Top 10 Risks'!D26="","",IF('Top 10 Risks'!J26=1,0.05,IF('Top 10 Risks'!J26=2,0.2,IF('Top 10 Risks'!J26=3,0.4,IF('Top 10 Risks'!J26=4,0.7,IF('Top 10 Risks'!J26=5,0.95,"")))))) | E23: =IF('Top 10 Risks'!D26="","",IF('Top 10 Risks'!H26=1,MatrixImpact!I10/2,IF('Top 10 Risks'!H26=2,SQRT(MatrixImpact!I10*MatrixImpact!I11),IF('Top 10 Risks'!H26=3,SQRT(MatrixImpact!I11*MatrixImpact!I12),IF('Top 10 Risks'!H26=4,SQRT(MatrixImpact!I12*MatrixImpact!I13),IF('Top 10 Risks'!H26=5,MatrixImpact!I13*1.5,"")))))) | F23: =IF(E23="","",MIN(10,MAX(1,2*LN(E23+1)))) | G23: =IF(D23="","",D23*E23) | H23: =IF('Top 10 Risks'!D26="","",IF('Top 10 Risks'!K26=1,7,IF('Top 10 Risks'!K26=2,5,IF('Top 10 Risks'!K26=3,3,IF('Top 10 Risks'!K26=4,9,5))))) | I23: =IF(H23="","",H23/Calibration!$C$21) | J23: =IF(I23="","",1/SQRT(1-MIN(I23,0.95)^2)) | K23: =IF(H23="","",(10-H23)*3) | L23: =IF(D23="","",MIN(0.95,D23*1.2)) | M23: =IF('Top 10 Risks'!D26="","",MIN(1,SUM('Risk Interaction Map'!E25:AI25)/MAX(1,COUNTA('Top 10 Risks'!D$9:D$39)-1))) | N23: =IF(K23="","",K23*L23*M23) | O23: =IF(N23="","",N23/J23) | P23: =IF(O23="","",MIN(1,MAX(0,(10-O23)/10))) | Q23: =IF(P23="","",1-P23) | R23: =Coherence_Density!$D$16 -> 1.0199813 | S23: =Coherence_Density!$D$18 -> 0.63375 | T23: =IF(P23="","",P23*J23*(2-S23)) | U23: =IF(Q23="","",Calibration!$C$20+0.3*(1-Q23)) | V23: =IF(O23="","",O23*(1-1.645*U23)) | W23: =IF(O23="","",O23) | X23: =IF(O23="","",O23*(1+1.645*U23)) | Y23: =IF(T23="","",IF(T23>=1.5,"CRITICAL",IF(T23>=1,"HIGH",IF(T23>=0.5,"MEDIUM","LOW")))) | AB23: =IF('Top 10 Risks'!E26="","",'Top 10 Risks'!E26)
A24: =IF('Top 10 Risks'!D27="","",'Top 10 Risks'!C27) | B24: =IF('Top 10 Risks'!D27="","",'Top 10 Risks'!D27) | D24: =IF('Top 10 Risks'!D27="","",IF('Top 10 Risks'!J27=1,0.05,IF('Top 10 Risks'!J27=2,0.2,IF('Top 10 Risks'!J27=3,0.4,IF('Top 10 Risks'!J27=4,0.7,IF('Top 10 Risks'!J27=5,0.95,"")))))) | E24: =IF('Top 10 Risks'!D27="","",IF('Top 10 Risks'!H27=1,MatrixImpact!I10/2,IF('Top 10 Risks'!H27=2,SQRT(MatrixImpact!I10*MatrixImpact!I11),IF('Top 10 Risks'!H27=3,SQRT(MatrixImpact!I11*MatrixImpact!I12),IF('Top 10 Risks'!H27=4,SQRT(MatrixImpact!I12*MatrixImpact!I13),IF('Top 10 Risks'!H27=5,MatrixImpact!I13*1.5,"")))))) | F24: =IF(E24="","",MIN(10,MAX(1,2*LN(E24+1)))) | G24: =IF(D24="","",D24*E24) | H24: =IF('Top 10 Risks'!D27="","",IF('Top 10 Risks'!K27=1,7,IF('Top 10 Risks'!K27=2,5,IF('Top 10 Risks'!K27=3,3,IF('Top 10 Risks'!K27=4,9,5))))) | I24: =IF(H24="","",H24/Calibration!$C$21) | J24: =IF(I24="","",1/SQRT(1-MIN(I24,0.95)^2)) | K24: =IF(H24="","",(10-H24)*3) | L24: =IF(D24="","",MIN(0.95,D24*1.2)) | M24: =IF('Top 10 Risks'!D27="","",MIN(1,SUM('Risk Interaction Map'!E26:AI26)/MAX(1,COUNTA('Top 10 Risks'!D$9:D$39)-1))) | N24: =IF(K24="","",K24*L24*M24) | O24: =IF(N24="","",N24/J24) | P24: =IF(O24="","",MIN(1,MAX(0,(10-O24)/10))) | Q24: =IF(P24="","",1-P24) | R24: =Coherence_Density!$D$16 -> 1.0199813 | S24: =Coherence_Density!$D$18 -> 0.63375 | T24: =IF(P24="","",P24*J24*(2-S24)) | U24: =IF(Q24="","",Calibration!$C$20+0.3*(1-Q24)) | V24: =IF(O24="","",O24*(1-1.645*U24)) | W24: =IF(O24="","",O24) | X24: =IF(O24="","",O24*(1+1.645*U24)) | Y24: =IF(T24="","",IF(T24>=1.5,"CRITICAL",IF(T24>=1,"HIGH",IF(T24>=0.5,"MEDIUM","LOW")))) | AB24: =IF('Top 10 Risks'!E27="","",'Top 10 Risks'!E27)
A25: =IF('Top 10 Risks'!D28="","",'Top 10 Risks'!C28) | B25: =IF('Top 10 Risks'!D28="","",'Top 10 Risks'!D28) | D25: =IF('Top 10 Risks'!D28="","",IF('Top 10 Risks'!J28=1,0.05,IF('Top 10 Risks'!J28=2,0.2,IF('Top 10 Risks'!J28=3,0.4,IF('Top 10 Risks'!J28=4,0.7,IF('Top 10 Risks'!J28=5,0.95,"")))))) | E25: =IF('Top 10 Risks'!D28="","",IF('Top 10 Risks'!H28=1,MatrixImpact!I10/2,IF('Top 10 Risks'!H28=2,SQRT(MatrixImpact!I10*MatrixImpact!I11),IF('Top 10 Risks'!H28=3,SQRT(MatrixImpact!I11*MatrixImpact!I12),IF('Top 10 Risks'!H28=4,SQRT(MatrixImpact!I12*MatrixImpact!I13),IF('Top 10 Risks'!H28=5,MatrixImpact!I13*1.5,"")))))) | F25: =IF(E25="","",MIN(10,MAX(1,2*LN(E25+1)))) | G25: =IF(D25="","",D25*E25) | H25: =IF('Top 10 Risks'!D28="","",IF('Top 10 Risks'!K28=1,7,IF('Top 10 Risks'!K28=2,5,IF('Top 10 Risks'!K28=3,3,IF('Top 10 Risks'!K28=4,9,5))))) | I25: =IF(H25="","",H25/Calibration!$C$21) | J25: =IF(I25="","",1/SQRT(1-MIN(I25,0.95)^2)) | K25: =IF(H25="","",(10-H25)*3) | L25: =IF(D25="","",MIN(0.95,D25*1.2)) | M25: =IF('Top 10 Risks'!D28="","",MIN(1,SUM('Risk Interaction Map'!E27:AI27)/MAX(1,COUNTA('Top 10 Risks'!D$9:D$39)-1))) | N25: =IF(K25="","",K25*L25*M25) | O25: =IF(N25="","",N25/J25) | P25: =IF(O25="","",MIN(1,MAX(0,(10-O25)/10))) | Q25: =IF(P25="","",1-P25) | R25: =Coherence_Density!$D$16 -> 1.0199813 | S25: =Coherence_Density!$D$18 -> 0.63375 | T25: =IF(P25="","",P25*J25*(2-S25)) | U25: =IF(Q25="","",Calibration!$C$20+0.3*(1-Q25)) | V25: =IF(O25="","",O25*(1-1.645*U25)) | W25: =IF(O25="","",O25) | X25: =IF(O25="","",O25*(1+1.645*U25)) | Y25: =IF(T25="","",IF(T25>=1.5,"CRITICAL",IF(T25>=1,"HIGH",IF(T25>=0.5,"MEDIUM","LOW")))) | AB25: =IF('Top 10 Risks'!E28="","",'Top 10 Risks'!E28)
A26: =IF('Top 10 Risks'!D29="","",'Top 10 Risks'!C29) | B26: =IF('Top 10 Risks'!D29="","",'Top 10 Risks'!D29) | D26: =IF('Top 10 Risks'!D29="","",IF('Top 10 Risks'!J29=1,0.05,IF('Top 10 Risks'!J29=2,0.2,IF('Top 10 Risks'!J29=3,0.4,IF('Top 10 Risks'!J29=4,0.7,IF('Top 10 Risks'!J29=5,0.95,"")))))) | E26: =IF('Top 10 Risks'!D29="","",IF('Top 10 Risks'!H29=1,MatrixImpact!I10/2,IF('Top 10 Risks'!H29=2,SQRT(MatrixImpact!I10*MatrixImpact!I11),IF('Top 10 Risks'!H29=3,SQRT(MatrixImpact!I11*MatrixImpact!I12),IF('Top 10 Risks'!H29=4,SQRT(MatrixImpact!I12*MatrixImpact!I13),IF('Top 10 Risks'!H29=5,MatrixImpact!I13*1.5,"")))))) | F26: =IF(E26="","",MIN(10,MAX(1,2*LN(E26+1)))) | G26: =IF(D26="","",D26*E26) | H26: =IF('Top 10 Risks'!D29="","",IF('Top 10 Risks'!K29=1,7,IF('Top 10 Risks'!K29=2,5,IF('Top 10 Risks'!K29=3,3,IF('Top 10 Risks'!K29=4,9,5))))) | I26: =IF(H26="","",H26/Calibration!$C$21) | J26: =IF(I26="","",1/SQRT(1-MIN(I26,0.95)^2)) | K26: =IF(H26="","",(10-H26)*3) | L26: =IF(D26="","",MIN(0.95,D26*1.2)) | M26: =IF('Top 10 Risks'!D29="","",MIN(1,SUM('Risk Interaction Map'!E28:AI28)/MAX(1,COUNTA('Top 10 Risks'!D$9:D$39)-1))) | N26: =IF(K26="","",K26*L26*M26) | O26: =IF(N26="","",N26/J26) | P26: =IF(O26="","",MIN(1,MAX(0,(10-O26)/10))) | Q26: =IF(P26="","",1-P26) | R26: =Coherence_Density!$D$16 -> 1.0199813 | S26: =Coherence_Density!$D$18 -> 0.63375 | T26: =IF(P26="","",P26*J26*(2-S26)) | U26: =IF(Q26="","",Calibration!$C$20+0.3*(1-Q26)) | V26: =IF(O26="","",O26*(1-1.645*U26)) | W26: =IF(O26="","",O26) | X26: =IF(O26="","",O26*(1+1.645*U26)) | Y26: =IF(T26="","",IF(T26>=1.5,"CRITICAL",IF(T26>=1,"HIGH",IF(T26>=0.5,"MEDIUM","LOW")))) | AB26: =IF('Top 10 Risks'!E29="","",'Top 10 Risks'!E29)
A27: =IF('Top 10 Risks'!D30="","",'Top 10 Risks'!C30) | B27: =IF('Top 10 Risks'!D30="","",'Top 10 Risks'!D30) | D27: =IF('Top 10 Risks'!D30="","",IF('Top 10 Risks'!J30=1,0.05,IF('Top 10 Risks'!J30=2,0.2,IF('Top 10 Risks'!J30=3,0.4,IF('Top 10 Risks'!J30=4,0.7,IF('Top 10 Risks'!J30=5,0.95,"")))))) | E27: =IF('Top 10 Risks'!D30="","",IF('Top 10 Risks'!H30=1,MatrixImpact!I10/2,IF('Top 10 Risks'!H30=2,SQRT(MatrixImpact!I10*MatrixImpact!I11),IF('Top 10 Risks'!H30=3,SQRT(MatrixImpact!I11*MatrixImpact!I12),IF('Top 10 Risks'!H30=4,SQRT(MatrixImpact!I12*MatrixImpact!I13),IF('Top 10 Risks'!H30=5,MatrixImpact!I13*1.5,"")))))) | F27: =IF(E27="","",MIN(10,MAX(1,2*LN(E27+1)))) | G27: =IF(D27="","",D27*E27) | H27: =IF('Top 10 Risks'!D30="","",IF('Top 10 Risks'!K30=1,7,IF('Top 10 Risks'!K30=2,5,IF('Top 10 Risks'!K30=3,3,IF('Top 10 Risks'!K30=4,9,5))))) | I27: =IF(H27="","",H27/Calibration!$C$21) | J27: =IF(I27="","",1/SQRT(1-MIN(I27,0.95)^2)) | K27: =IF(H27="","",(10-H27)*3) | L27: =IF(D27="","",MIN(0.95,D27*1.2)) | M27: =IF('Top 10 Risks'!D30="","",MIN(1,SUM('Risk Interaction Map'!E29:AI29)/MAX(1,COUNTA('Top 10 Risks'!D$9:D$39)-1))) | N27: =IF(K27="","",K27*L27*M27) | O27: =IF(N27="","",N27/J27) | P27: =IF(O27="","",MIN(1,MAX(0,(10-O27)/10))) | Q27: =IF(P27="","",1-P27) | R27: =Coherence_Density!$D$16 -> 1.0199813 | S27: =Coherence_Density!$D$18 -> 0.63375 | T27: =IF(P27="","",P27*J27*(2-S27)) | U27: =IF(Q27="","",Calibration!$C$20+0.3*(1-Q27)) | V27: =IF(O27="","",O27*(1-1.645*U27)) | W27: =IF(O27="","",O27) | X27: =IF(O27="","",O27*(1+1.645*U27)) | Y27: =IF(T27="","",IF(T27>=1.5,"CRITICAL",IF(T27>=1,"HIGH",IF(T27>=0.5,"MEDIUM","LOW")))) | AB27: =IF('Top 10 Risks'!E30="","",'Top 10 Risks'!E30)
A28: =IF('Top 10 Risks'!D31="","",'Top 10 Risks'!C31) | B28: =IF('Top 10 Risks'!D31="","",'Top 10 Risks'!D31) | D28: =IF('Top 10 Risks'!D31="","",IF('Top 10 Risks'!J31=1,0.05,IF('Top 10 Risks'!J31=2,0.2,IF('Top 10 Risks'!J31=3,0.4,IF('Top 10 Risks'!J31=4,0.7,IF('Top 10 Risks'!J31=5,0.95,"")))))) | E28: =IF('Top 10 Risks'!D31="","",IF('Top 10 Risks'!H31=1,MatrixImpact!I10/2,IF('Top 10 Risks'!H31=2,SQRT(MatrixImpact!I10*MatrixImpact!I11),IF('Top 10 Risks'!H31=3,SQRT(MatrixImpact!I11*MatrixImpact!I12),IF('Top 10 Risks'!H31=4,SQRT(MatrixImpact!I12*MatrixImpact!I13),IF('Top 10 Risks'!H31=5,MatrixImpact!I13*1.5,"")))))) | F28: =IF(E28="","",MIN(10,MAX(1,2*LN(E28+1)))) | G28: =IF(D28="","",D28*E28) | H28: =IF('Top 10 Risks'!D31="","",IF('Top 10 Risks'!K31=1,7,IF('Top 10 Risks'!K31=2,5,IF('Top 10 Risks'!K31=3,3,IF('Top 10 Risks'!K31=4,9,5))))) | I28: =IF(H28="","",H28/Calibration!$C$21) | J28: =IF(I28="","",1/SQRT(1-MIN(I28,0.95)^2)) | K28: =IF(H28="","",(10-H28)*3) | L28: =IF(D28="","",MIN(0.95,D28*1.2)) | M28: =IF('Top 10 Risks'!D31="","",MIN(1,SUM('Risk Interaction Map'!E30:AI30)/MAX(1,COUNTA('Top 10 Risks'!D$9:D$39)-1))) | N28: =IF(K28="","",K28*L28*M28) | O28: =IF(N28="","",N28/J28) | P28: =IF(O28="","",MIN(1,MAX(0,(10-O28)/10))) | Q28: =IF(P28="","",1-P28) | R28: =Coherence_Density!$D$16 -> 1.0199813 | S28: =Coherence_Density!$D$18 -> 0.63375 | T28: =IF(P28="","",P28*J28*(2-S28)) | U28: =IF(Q28="","",Calibration!$C$20+0.3*(1-Q28)) | V28: =IF(O28="","",O28*(1-1.645*U28)) | W28: =IF(O28="","",O28) | X28: =IF(O28="","",O28*(1+1.645*U28)) | Y28: =IF(T28="","",IF(T28>=1.5,"CRITICAL",IF(T28>=1,"HIGH",IF(T28>=0.5,"MEDIUM","LOW")))) | AB28: =IF('Top 10 Risks'!E31="","",'Top 10 Risks'!E31)
A29: =IF('Top 10 Risks'!D32="","",'Top 10 Risks'!C32) | B29: =IF('Top 10 Risks'!D32="","",'Top 10 Risks'!D32) | D29: =IF('Top 10 Risks'!D32="","",IF('Top 10 Risks'!J32=1,0.05,IF('Top 10 Risks'!J32=2,0.2,IF('Top 10 Risks'!J32=3,0.4,IF('Top 10 Risks'!J32=4,0.7,IF('Top 10 Risks'!J32=5,0.95,"")))))) | E29: =IF('Top 10 Risks'!D32="","",IF('Top 10 Risks'!H32=1,MatrixImpact!I10/2,IF('Top 10 Risks'!H32=2,SQRT(MatrixImpact!I10*MatrixImpact!I11),IF('Top 10 Risks'!H32=3,SQRT(MatrixImpact!I11*MatrixImpact!I12),IF('Top 10 Risks'!H32=4,SQRT(MatrixImpact!I12*MatrixImpact!I13),IF('Top 10 Risks'!H32=5,MatrixImpact!I13*1.5,"")))))) | F29: =IF(E29="","",MIN(10,MAX(1,2*LN(E29+1)))) | G29: =IF(D29="","",D29*E29) | H29: =IF('Top 10 Risks'!D32="","",IF('Top 10 Risks'!K32=1,7,IF('Top 10 Risks'!K32=2,5,IF('Top 10 Risks'!K32=3,3,IF('Top 10 Risks'!K32=4,9,5))))) | I29: =IF(H29="","",H29/Calibration!$C$21) | J29: =IF(I29="","",1/SQRT(1-MIN(I29,0.95)^2)) | K29: =IF(H29="","",(10-H29)*3) | L29: =IF(D29="","",MIN(0.95,D29*1.2)) | M29: =IF('Top 10 Risks'!D32="","",MIN(1,SUM('Risk Interaction Map'!E31:AI31)/MAX(1,COUNTA('Top 10 Risks'!D$9:D$39)-1))) | N29: =IF(K29="","",K29*L29*M29) | O29: =IF(N29="","",N29/J29) | P29: =IF(O29="","",MIN(1,MAX(0,(10-O29)/10))) | Q29: =IF(P29="","",1-P29) | R29: =Coherence_Density!$D$16 -> 1.0199813 | S29: =Coherence_Density!$D$18 -> 0.63375 | T29: =IF(P29="","",P29*J29*(2-S29)) | U29: =IF(Q29="","",Calibration!$C$20+0.3*(1-Q29)) | V29: =IF(O29="","",O29*(1-1.645*U29)) | W29: =IF(O29="","",O29) | X29: =IF(O29="","",O29*(1+1.645*U29)) | Y29: =IF(T29="","",IF(T29>=1.5,"CRITICAL",IF(T29>=1,"HIGH",IF(T29>=0.5,"MEDIUM","LOW")))) | AB29: =IF('Top 10 Risks'!E32="","",'Top 10 Risks'!E32)
A30: =IF('Top 10 Risks'!D33="","",'Top 10 Risks'!C33) | B30: =IF('Top 10 Risks'!D33="","",'Top 10 Risks'!D33) | D30: =IF('Top 10 Risks'!D33="","",IF('Top 10 Risks'!J33=1,0.05,IF('Top 10 Risks'!J33=2,0.2,IF('Top 10 Risks'!J33=3,0.4,IF('Top 10 Risks'!J33=4,0.7,IF('Top 10 Risks'!J33=5,0.95,"")))))) | E30: =IF('Top 10 Risks'!D33="","",IF('Top 10 Risks'!H33=1,MatrixImpact!I10/2,IF('Top 10 Risks'!H33=2,SQRT(MatrixImpact!I10*MatrixImpact!I11),IF('Top 10 Risks'!H33=3,SQRT(MatrixImpact!I11*MatrixImpact!I12),IF('Top 10 Risks'!H33=4,SQRT(MatrixImpact!I12*MatrixImpact!I13),IF('Top 10 Risks'!H33=5,MatrixImpact!I13*1.5,"")))))) | F30: =IF(E30="","",MIN(10,MAX(1,2*LN(E30+1)))) | G30: =IF(D30="","",D30*E30) | H30: =IF('Top 10 Risks'!D33="","",IF('Top 10 Risks'!K33=1,7,IF('Top 10 Risks'!K33=2,5,IF('Top 10 Risks'!K33=3,3,IF('Top 10 Risks'!K33=4,9,5))))) | I30: =IF(H30="","",H30/Calibration!$C$21) | J30: =IF(I30="","",1/SQRT(1-MIN(I30,0.95)^2)) | K30: =IF(H30="","",(10-H30)*3) | L30: =IF(D30="","",MIN(0.95,D30*1.2)) | M30: =IF('Top 10 Risks'!D33="","",MIN(1,SUM('Risk Interaction Map'!E32:AI32)/MAX(1,COUNTA('Top 10 Risks'!D$9:D$39)-1))) | N30: =IF(K30="","",K30*L30*M30) | O30: =IF(N30="","",N30/J30) | P30: =IF(O30="","",MIN(1,MAX(0,(10-O30)/10))) | Q30: =IF(P30="","",1-P30) | R30: =Coherence_Density!$D$16 -> 1.0199813 | S30: =Coherence_Density!$D$18 -> 0.63375 | T30: =IF(P30="","",P30*J30*(2-S30)) | U30: =IF(Q30="","",Calibration!$C$20+0.3*(1-Q30)) | V30: =IF(O30="","",O30*(1-1.645*U30)) | W30: =IF(O30="","",O30) | X30: =IF(O30="","",O30*(1+1.645*U30)) | Y30: =IF(T30="","",IF(T30>=1.5,"CRITICAL",IF(T30>=1,"HIGH",IF(T30>=0.5,"MEDIUM","LOW")))) | AB30: =IF('Top 10 Risks'!E33="","",'Top 10 Risks'!E33)
A31: =IF('Top 10 Risks'!D34="","",'Top 10 Risks'!C34) | B31: =IF('Top 10 Risks'!D34="","",'Top 10 Risks'!D34) | D31: =IF('Top 10 Risks'!D34="","",IF('Top 10 Risks'!J34=1,0.05,IF('Top 10 Risks'!J34=2,0.2,IF('Top 10 Risks'!J34=3,0.4,IF('Top 10 Risks'!J34=4,0.7,IF('Top 10 Risks'!J34=5,0.95,"")))))) | E31: =IF('Top 10 Risks'!D34="","",IF('Top 10 Risks'!H34=1,MatrixImpact!I10/2,IF('Top 10 Risks'!H34=2,SQRT(MatrixImpact!I10*MatrixImpact!I11),IF('Top 10 Risks'!H34=3,SQRT(MatrixImpact!I11*MatrixImpact!I12),IF('Top 10 Risks'!H34=4,SQRT(MatrixImpact!I12*MatrixImpact!I13),IF('Top 10 Risks'!H34=5,MatrixImpact!I13*1.5,"")))))) | F31: =IF(E31="","",MIN(10,MAX(1,2*LN(E31+1)))) | G31: =IF(D31="","",D31*E31) | H31: =IF('Top 10 Risks'!D34="","",IF('Top 10 Risks'!K34=1,7,IF('Top 10 Risks'!K34=2,5,IF('Top 10 Risks'!K34=3,3,IF('Top 10 Risks'!K34=4,9,5))))) | I31: =IF(H31="","",H31/Calibration!$C$21) | J31: =IF(I31="","",1/SQRT(1-MIN(I31,0.95)^2)) | K31: =IF(H31="","",(10-H31)*3) | L31: =IF(D31="","",MIN(0.95,D31*1.2)) | M31: =IF('Top 10 Risks'!D34="","",MIN(1,SUM('Risk Interaction Map'!E33:AI33)/MAX(1,COUNTA('Top 10 Risks'!D$9:D$39)-1))) | N31: =IF(K31="","",K31*L31*M31) | O31: =IF(N31="","",N31/J31) | P31: =IF(O31="","",MIN(1,MAX(0,(10-O31)/10))) | Q31: =IF(P31="","",1-P31) | R31: =Coherence_Density!$D$16 -> 1.0199813 | S31: =Coherence_Density!$D$18 -> 0.63375 | T31: =IF(P31="","",P31*J31*(2-S31)) | U31: =IF(Q31="","",Calibration!$C$20+0.3*(1-Q31)) | V31: =IF(O31="","",O31*(1-1.645*U31)) | W31: =IF(O31="","",O31) | X31: =IF(O31="","",O31*(1+1.645*U31)) | Y31: =IF(T31="","",IF(T31>=1.5,"CRITICAL",IF(T31>=1,"HIGH",IF(T31>=0.5,"MEDIUM","LOW")))) | AB31: =IF('Top 10 Risks'!E34="","",'Top 10 Risks'!E34)
A32: =IF('Top 10 Risks'!D35="","",'Top 10 Risks'!C35) | B32: =IF('Top 10 Risks'!D35="","",'Top 10 Risks'!D35) | D32: =IF('Top 10 Risks'!D35="","",IF('Top 10 Risks'!J35=1,0.05,IF('Top 10 Risks'!J35=2,0.2,IF('Top 10 Risks'!J35=3,0.4,IF('Top 10 Risks'!J35=4,0.7,IF('Top 10 Risks'!J35=5,0.95,"")))))) | E32: =IF('Top 10 Risks'!D35="","",IF('Top 10 Risks'!H35=1,MatrixImpact!I10/2,IF('Top 10 Risks'!H35=2,SQRT(MatrixImpact!I10*MatrixImpact!I11),IF('Top 10 Risks'!H35=3,SQRT(MatrixImpact!I11*MatrixImpact!I12),IF('Top 10 Risks'!H35=4,SQRT(MatrixImpact!I12*MatrixImpact!I13),IF('Top 10 Risks'!H35=5,MatrixImpact!I13*1.5,"")))))) | F32: =IF(E32="","",MIN(10,MAX(1,2*LN(E32+1)))) | G32: =IF(D32="","",D32*E32) | H32: =IF('Top 10 Risks'!D35="","",IF('Top 10 Risks'!K35=1,7,IF('Top 10 Risks'!K35=2,5,IF('Top 10 Risks'!K35=3,3,IF('Top 10 Risks'!K35=4,9,5))))) | I32: =IF(H32="","",H32/Calibration!$C$21) | J32: =IF(I32="","",1/SQRT(1-MIN(I32,0.95)^2)) | K32: =IF(H32="","",(10-H32)*3) | L32: =IF(D32="","",MIN(0.95,D32*1.2)) | M32: =IF('Top 10 Risks'!D35="","",MIN(1,SUM('Risk Interaction Map'!E34:AI34)/MAX(1,COUNTA('Top 10 Risks'!D$9:D$39)-1))) | N32: =IF(K32="","",K32*L32*M32) | O32: =IF(N32="","",N32/J32) | P32: =IF(O32="","",MIN(1,MAX(0,(10-O32)/10))) | Q32: =IF(P32="","",1-P32) | R32: =Coherence_Density!$D$16 -> 1.0199813 | S32: =Coherence_Density!$D$18 -> 0.63375 | T32: =IF(P32="","",P32*J32*(2-S32)) | U32: =IF(Q32="","",Calibration!$C$20+0.3*(1-Q32)) | V32: =IF(O32="","",O32*(1-1.645*U32)) | W32: =IF(O32="","",O32) | X32: =IF(O32="","",O32*(1+1.645*U32)) | Y32: =IF(T32="","",IF(T32>=1.5,"CRITICAL",IF(T32>=1,"HIGH",IF(T32>=0.5,"MEDIUM","LOW")))) | AB32: =IF('Top 10 Risks'!E35="","",'Top 10 Risks'!E35)
A33: =IF('Top 10 Risks'!D36="","",'Top 10 Risks'!C36) | B33: =IF('Top 10 Risks'!D36="","",'Top 10 Risks'!D36) | D33: =IF('Top 10 Risks'!D36="","",IF('Top 10 Risks'!J36=1,0.05,IF('Top 10 Risks'!J36=2,0.2,IF('Top 10 Risks'!J36=3,0.4,IF('Top 10 Risks'!J36=4,0.7,IF('Top 10 Risks'!J36=5,0.95,"")))))) | E33: =IF('Top 10 Risks'!D36="","",IF('Top 10 Risks'!H36=1,MatrixImpact!I10/2,IF('Top 10 Risks'!H36=2,SQRT(MatrixImpact!I10*MatrixImpact!I11),IF('Top 10 Risks'!H36=3,SQRT(MatrixImpact!I11*MatrixImpact!I12),IF('Top 10 Risks'!H36=4,SQRT(MatrixImpact!I12*MatrixImpact!I13),IF('Top 10 Risks'!H36=5,MatrixImpact!I13*1.5,"")))))) | F33: =IF(E33="","",MIN(10,MAX(1,2*LN(E33+1)))) | G33: =IF(D33="","",D33*E33) | H33: =IF('Top 10 Risks'!D36="","",IF('Top 10 Risks'!K36=1,7,IF('Top 10 Risks'!K36=2,5,IF('Top 10 Risks'!K36=3,3,IF('Top 10 Risks'!K36=4,9,5))))) | I33: =IF(H33="","",H33/Calibration!$C$21) | J33: =IF(I33="","",1/SQRT(1-MIN(I33,0.95)^2)) | K33: =IF(H33="","",(10-H33)*3) | L33: =IF(D33="","",MIN(0.95,D33*1.2)) | M33: =IF('Top 10 Risks'!D36="","",MIN(1,SUM('Risk Interaction Map'!E35:AI35)/MAX(1,COUNTA('Top 10 Risks'!D$9:D$39)-1))) | N33: =IF(K33="","",K33*L33*M33) | O33: =IF(N33="","",N33/J33) | P33: =IF(O33="","",MIN(1,MAX(0,(10-O33)/10))) | Q33: =IF(P33="","",1-P33) | R33: =Coherence_Density!$D$16 -> 1.0199813 | S33: =Coherence_Density!$D$18 -> 0.63375 | T33: =IF(P33="","",P33*J33*(2-S33)) | U33: =IF(Q33="","",Calibration!$C$20+0.3*(1-Q33)) | V33: =IF(O33="","",O33*(1-1.645*U33)) | W33: =IF(O33="","",O33) | X33: =IF(O33="","",O33*(1+1.645*U33)) | Y33: =IF(T33="","",IF(T33>=1.5,"CRITICAL",IF(T33>=1,"HIGH",IF(T33>=0.5,"MEDIUM","LOW")))) | AB33: =IF('Top 10 Risks'!E36="","",'Top 10 Risks'!E36)
A34: =IF('Top 10 Risks'!D37="","",'Top 10 Risks'!C37) | B34: =IF('Top 10 Risks'!D37="","",'Top 10 Risks'!D37) | D34: =IF('Top 10 Risks'!D37="","",IF('Top 10 Risks'!J37=1,0.05,IF('Top 10 Risks'!J37=2,0.2,IF('Top 10 Risks'!J37=3,0.4,IF('Top 10 Risks'!J37=4,0.7,IF('Top 10 Risks'!J37=5,0.95,"")))))) | E34: =IF('Top 10 Risks'!D37="","",IF('Top 10 Risks'!H37=1,MatrixImpact!I10/2,IF('Top 10 Risks'!H37=2,SQRT(MatrixImpact!I10*MatrixImpact!I11),IF('Top 10 Risks'!H37=3,SQRT(MatrixImpact!I11*MatrixImpact!I12),IF('Top 10 Risks'!H37=4,SQRT(MatrixImpact!I12*MatrixImpact!I13),IF('Top 10 Risks'!H37=5,MatrixImpact!I13*1.5,"")))))) | F34: =IF(E34="","",MIN(10,MAX(1,2*LN(E34+1)))) | G34: =IF(D34="","",D34*E34) | H34: =IF('Top 10 Risks'!D37="","",IF('Top 10 Risks'!K37=1,7,IF('Top 10 Risks'!K37=2,5,IF('Top 10 Risks'!K37=3,3,IF('Top 10 Risks'!K37=4,9,5))))) | I34: =IF(H34="","",H34/Calibration!$C$21) | J34: =IF(I34="","",1/SQRT(1-MIN(I34,0.95)^2)) | K34: =IF(H34="","",(10-H34)*3) | L34: =IF(D34="","",MIN(0.95,D34*1.2)) | M34: =IF('Top 10 Risks'!D37="","",MIN(1,SUM('Risk Interaction Map'!E36:AI36)/MAX(1,COUNTA('Top 10 Risks'!D$9:D$39)-1))) | N34: =IF(K34="","",K34*L34*M34) | O34: =IF(N34="","",N34/J34) | P34: =IF(O34="","",MIN(1,MAX(0,(10-O34)/10))) | Q34: =IF(P34="","",1-P34) | R34: =Coherence_Density!$D$16 -> 1.0199813 | S34: =Coherence_Density!$D$18 -> 0.63375 | T34: =IF(P34="","",P34*J34*(2-S34)) | U34: =IF(Q34="","",Calibration!$C$20+0.3*(1-Q34)) | V34: =IF(O34="","",O34*(1-1.645*U34)) | W34: =IF(O34="","",O34) | X34: =IF(O34="","",O34*(1+1.645*U34)) | Y34: =IF(T34="","",IF(T34>=1.5,"CRITICAL",IF(T34>=1,"HIGH",IF(T34>=0.5,"MEDIUM","LOW")))) | AB34: =IF('Top 10 Risks'!E37="","",'Top 10 Risks'!E37)
A35: =IF('Top 10 Risks'!D38="","",'Top 10 Risks'!C38) | B35: =IF('Top 10 Risks'!D38="","",'Top 10 Risks'!D38) | D35: =IF('Top 10 Risks'!D38="","",IF('Top 10 Risks'!J38=1,0.05,IF('Top 10 Risks'!J38=2,0.2,IF('Top 10 Risks'!J38=3,0.4,IF('Top 10 Risks'!J38=4,0.7,IF('Top 10 Risks'!J38=5,0.95,"")))))) | E35: =IF('Top 10 Risks'!D38="","",IF('Top 10 Risks'!H38=1,MatrixImpact!I10/2,IF('Top 10 Risks'!H38=2,SQRT(MatrixImpact!I10*MatrixImpact!I11),IF('Top 10 Risks'!H38=3,SQRT(MatrixImpact!I11*MatrixImpact!I12),IF('Top 10 Risks'!H38=4,SQRT(MatrixImpact!I12*MatrixImpact!I13),IF('Top 10 Risks'!H38=5,MatrixImpact!I13*1.5,"")))))) | F35: =IF(E35="","",MIN(10,MAX(1,2*LN(E35+1)))) | G35: =IF(D35="","",D35*E35) | H35: =IF('Top 10 Risks'!D38="","",IF('Top 10 Risks'!K38=1,7,IF('Top 10 Risks'!K38=2,5,IF('Top 10 Risks'!K38=3,3,IF('Top 10 Risks'!K38=4,9,5))))) | I35: =IF(H35="","",H35/Calibration!$C$21) | J35: =IF(I35="","",1/SQRT(1-MIN(I35,0.95)^2)) | K35: =IF(H35="","",(10-H35)*3) | L35: =IF(D35="","",MIN(0.95,D35*1.2)) | M35: =IF('Top 10 Risks'!D38="","",MIN(1,SUM('Risk Interaction Map'!E37:AI37)/MAX(1,COUNTA('Top 10 Risks'!D$9:D$39)-1))) | N35: =IF(K35="","",K35*L35*M35) | O35: =IF(N35="","",N35/J35) | P35: =IF(O35="","",MIN(1,MAX(0,(10-O35)/10))) | Q35: =IF(P35="","",1-P35) | R35: =Coherence_Density!$D$16 -> 1.0199813 | S35: =Coherence_Density!$D$18 -> 0.63375 | T35: =IF(P35="","",P35*J35*(2-S35)) | U35: =IF(Q35="","",Calibration!$C$20+0.3*(1-Q35)) | V35: =IF(O35="","",O35*(1-1.645*U35)) | W35: =IF(O35="","",O35) | X35: =IF(O35="","",O35*(1+1.645*U35)) | Y35: =IF(T35="","",IF(T35>=1.5,"CRITICAL",IF(T35>=1,"HIGH",IF(T35>=0.5,"MEDIUM","LOW")))) | AB35: =IF('Top 10 Risks'!E38="","",'Top 10 Risks'!E38)
A36: =IF('Top 10 Risks'!D39="","",'Top 10 Risks'!C39) | B36: =IF('Top 10 Risks'!D39="","",'Top 10 Risks'!D39) | D36: =IF('Top 10 Risks'!D39="","",IF('Top 10 Risks'!J39=1,0.05,IF('Top 10 Risks'!J39=2,0.2,IF('Top 10 Risks'!J39=3,0.4,IF('Top 10 Risks'!J39=4,0.7,IF('Top 10 Risks'!J39=5,0.95,"")))))) | E36: =IF('Top 10 Risks'!D39="","",IF('Top 10 Risks'!H39=1,MatrixImpact!I10/2,IF('Top 10 Risks'!H39=2,SQRT(MatrixImpact!I10*MatrixImpact!I11),IF('Top 10 Risks'!H39=3,SQRT(MatrixImpact!I11*MatrixImpact!I12),IF('Top 10 Risks'!H39=4,SQRT(MatrixImpact!I12*MatrixImpact!I13),IF('Top 10 Risks'!H39=5,MatrixImpact!I13*1.5,"")))))) | F36: =IF(E36="","",MIN(10,MAX(1,2*LN(E36+1)))) | G36: =IF(D36="","",D36*E36) | H36: =IF('Top 10 Risks'!D39="","",IF('Top 10 Risks'!K39=1,7,IF('Top 10 Risks'!K39=2,5,IF('Top 10 Risks'!K39=3,3,IF('Top 10 Risks'!K39=4,9,5))))) | I36: =IF(H36="","",H36/Calibration!$C$21) | J36: =IF(I36="","",1/SQRT(1-MIN(I36,0.95)^2)) | K36: =IF(H36="","",(10-H36)*3) | L36: =IF(D36="","",MIN(0.95,D36*1.2)) | M36: =IF('Top 10 Risks'!D39="","",MIN(1,SUM('Risk Interaction Map'!E38:AI38)/MAX(1,COUNTA('Top 10 Risks'!D$9:D$39)-1))) | N36: =IF(K36="","",K36*L36*M36) | O36: =IF(N36="","",N36/J36) | P36: =IF(O36="","",MIN(1,MAX(0,(10-O36)/10))) | Q36: =IF(P36="","",1-P36) | R36: =Coherence_Density!$D$16 -> 1.0199813 | S36: =Coherence_Density!$D$18 -> 0.63375 | T36: =IF(P36="","",P36*J36*(2-S36)) | U36: =IF(Q36="","",Calibration!$C$20+0.3*(1-Q36)) | V36: =IF(O36="","",O36*(1-1.645*U36)) | W36: =IF(O36="","",O36) | X36: =IF(O36="","",O36*(1+1.645*U36)) | Y36: =IF(T36="","",IF(T36>=1.5,"CRITICAL",IF(T36>=1,"HIGH",IF(T36>=0.5,"MEDIUM","LOW")))) | AB36: =IF('Top 10 Risks'!E39="","",'Top 10 Risks'!E39)

Sheet FORGE
A1: FORGE — Focused Organizational Response & Governance Engine (v6.1 Full Calculation Chain)
A2: Each column = one verifiable calculation step | Blue = Input | Black = Formula | Green = Cross-sheet reference
A3: IDENTIFICATION | D3: CRISIS QUANTIFICATION | H3: SEVERITY | I3: RI / SMI / RESPONSE CALCULATION | O3: R-TTS & RESIDUAL | T3: URGENCY | V3: PALMER NOISE & MC | Z3: ROI | AA3: BACKCASTING & STATUS
D4: Input (0-1) | E4: Input | F4: MIN(10,MAX(1, 2×LN(€M+1))) | G4: Prob × Impact | H4: Input (1-10) | I4: CORE!D36 | J4: CORE!D44 | K4: Input (0-10) | L4: (RI/10)× (DQ/10) | M4: RI_RA/10 | N4: RE × RF | O4: ((10-Sev)×3)× (1-RE×RF) | P4: Impact× (1-RE) | Q4: MIN(10,MAX(1, 2×LN(Res+1))) | R4: R-TTS × R_mod | S4: Recovery × 30.44 | T4: (Sev/10)× (1-CI)/R-TTS | U4: Based on UI | V4: Co_RI!D30 | W4: Resid× (1-1.645×η) | X4: Residual | Y4: Resid× (1+1.645×η) | Z4: (Imp-Res) /Res | AA4: days | AB4: days | AC4: days | AD4: days
A5: ID | B5: Crisis | C5: Category | D5: Prob | E5: Impact (€M) | F5: Impact Score | G5: Exp Loss (€M) | H5: Severity | I5: RI | J5: SMI | K5: Decision Quality | L5: Response Effectiveness | M5: Resource Factor | N5: Containment Index | O5: R-TTS (months) | P5: Residual (€M) | Q5: Resid Score | R5: Recovery (months) | S5: Recovery (days) | T5: Urgency Index | U5: Urgency Class | V5: Palmer η_B | W5: MC R-Low | X5: MC R-Mid | Y5: MC R-High | Z5: Mitig ROI | AA5: Backcast 25% | AB5: Backcast 50% | AC5: Backcast 75% | AD5: Backcast 95% | AE5: Status | AF5: Notes
A6: =IF('Top 10 Risks'!D9="","",'Top 10 Risks'!C9) | B6: =IF('Top 10 Risks'!D9="","",'Top 10 Risks'!D9) | C6: =IF(RADAR!C6="","",RADAR!C6) -> OPS | D6: =IF(RADAR!D6="","",RADAR!D6) | E6: =IF(RADAR!E6="","",RADAR!E6) | F6: =IF(E6="","",MIN(10,MAX(1,2*LN(E6+1)))) | G6: =IF(D6="","",D6*E6) | H6: 9 | I6: =CORE!$D$36 -> 6.885 | J6: =CORE!$D$44 -> 6.475 | K6: =IF('Top 10 Risks'!D9="","",10*(IF(OR('Risk Control'!E8=FALSE(),'Risk Control'!E8=""),0,'Risk Control'!E8/4)*0.2+IF(OR('Risk Control'!L8=FALSE(),'Risk Control'!L8=""),0,'Risk Control'!L8/4)*0.15+IF(OR('Risk Control'!S8=FALSE(),'Risk Control'!S8=""),0,'Risk Control'!S8/5)*0.25+IF(OR('Risk Control'!AA8=FALSE(),'Risk Control'!AA8=""),0,'Risk Control'!AA8/5)*0.25+IF(OR('Risk Control'!AI8=FALSE(),'Risk Control'!AI8=""),0,'Risk Control'!AI8/5)*0.15)) | L6: =IF(OR(I6="",K6=""),0,(I6/10)*MAX(0,K6/10)) -> 0 | M6: =Company_RI!$F$22/10 -> 0.78 | N6: =IF(OR(L6="",M6=""),0,L6*M6) -> 0 | O6: =IF(OR(H6="",H6=0),"",((10-H6)*3)*(1-IFERROR(L6*M6,0))) -> 3 | P6: =IF(OR(E6="",E6=0),"",E6*(1-IFERROR(L6,0))) | Q6: =IF(P6="","",MIN(10,MAX(1,2*LN(P6+1)))) | R6: =IF(OR(O6="",O6=0),"",O6*Company_RI!$D$32) -> 3.9345 | S6: =IF(R6="","",R6*30.44) -> 119.76618 | T6: =IF(OR(H6="",O6="",O6=0),"",(H6/10)*(1-IFERROR(N6,0))/MAX(O6,0.1)) -> 0.3 | U6: =IF(T6="","",IF(T6>=2,"IMMEDIATE",IF(T6>=1,"URGENT",IF(T6>=0.5,"ELEVATED","STANDARD")))) -> STANDARD | V6: =Company_RI!$D$30 -> 0.19345 | W6: =IF(P6="","",P6*(1-1.645*V6)) | X6: =IF(P6="","",P6) | Y6: =IF(P6="","",P6*(1+1.645*V6)) | Z6: =IF(OR(P6="",P6=0),"",(E6-P6)/P6) | AA6: =IF(OR(O6="",O6=0),"",ROUND(-LN(0.75)/Company_RI!$D$31,0)) -> 8 | AB6: =IF(OR(O6="",O6=0),"",ROUND(-LN(0.5)/Company_RI!$D$31,0)) -> 18 | AC6: =IF(OR(O6="",O6=0),"",ROUND(-LN(0.25)/Company_RI!$D$31,0)) -> 36 | AD6: =IF(OR(O6="",O6=0),"",ROUND(-LN(0.05)/Company_RI!$D$31,0)) -> 78 | AE6: ACTIVE | AF6: =IF('Top 10 Risks'!E9="","",'Top 10 Risks'!E9)
A7: =IF('Top 10 Risks'!D10="","",'Top 10 Risks'!C10) | B7: =IF('Top 10 Risks'!D10="","",'Top 10 Risks'!D10) | C7: =IF(RADAR!C7="","",RADAR!C7) -> REG | D7: =IF(RADAR!D7="","",RADAR!D7) | E7: =IF(RADAR!E7="","",RADAR!E7) | F7: =IF(E7="","",MIN(10,MAX(1,2*LN(E7+1)))) | G7: =IF(D7="","",D7*E7) | H7: 6 | I7: =CORE!$D$36 -> 6.885 | J7: =CORE!$D$44 -> 6.475 | K7: =IF('Top 10 Risks'!D10="","",10*(IF(OR('Risk Control'!E9=FALSE(),'Risk Control'!E9=""),0,'Risk Control'!E9/4)*0.2+IF(OR('Risk Control'!L9=FALSE(),'Risk Control'!L9=""),0,'Risk Control'!L9/4)*0.15+IF(OR('Risk Control'!S9=FALSE(),'Risk Control'!S9=""),0,'Risk Control'!S9/5)*0.25+IF(OR('Risk Control'!AA9=FALSE(),'Risk Control'!AA9=""),0,'Risk Control'!AA9/5)*0.25+IF(OR('Risk Control'!AI9=FALSE(),'Risk Control'!AI9=""),0,'Risk Control'!AI9/5)*0.15)) | L7: =IF(OR(I7="",K7=""),0,(I7/10)*MAX(0,K7/10)) -> 0 | M7: =Company_RI!$F$22/10 -> 0.78 | N7: =IF(OR(L7="",M7=""),0,L7*M7) -> 0 | O7: =IF(OR(H7="",H7=0),"",((10-H7)*3)*(1-IFERROR(L7*M7,0))) -> 12 | P7: =IF(OR(E7="",E7=0),"",E7*(1-IFERROR(L7,0))) | Q7: =IF(P7="","",MIN(10,MAX(1,2*LN(P7+1)))) | R7: =IF(OR(O7="",O7=0),"",O7*Company_RI!$D$32) -> 15.738 | S7: =IF(R7="","",R7*30.44) -> 479.06472 | T7: =IF(OR(H7="",O7="",O7=0),"",(H7/10)*(1-IFERROR(N7,0))/MAX(O7,0.1)) -> 0.05 | U7: =IF(T7="","",IF(T7>=2,"IMMEDIATE",IF(T7>=1,"URGENT",IF(T7>=0.5,"ELEVATED","STANDARD")))) -> STANDARD | V7: =Company_RI!$D$30 -> 0.19345 | W7: =IF(P7="","",P7*(1-1.645*V7)) | X7: =IF(P7="","",P7) | Y7: =IF(P7="","",P7*(1+1.645*V7)) | Z7: =IF(OR(P7="",P7=0),"",(E7-P7)/P7) | AA7: =IF(OR(O7="",O7=0),"",ROUND(-LN(0.75)/Company_RI!$D$31,0)) -> 8 | AB7: =IF(OR(O7="",O7=0),"",ROUND(-LN(0.5)/Company_RI!$D$31,0)) -> 18 | AC7: =IF(OR(O7="",O7=0),"",ROUND(-LN(0.25)/Company_RI!$D$31,0)) -> 36 | AD7: =IF(OR(O7="",O7=0),"",ROUND(-LN(0.05)/Company_RI!$D$31,0)) -> 78 | AE7: ACTIVE | AF7: =IF('Top 10 Risks'!E10="","",'Top 10 Risks'!E10)
A8: =IF('Top 10 Risks'!D11="","",'Top 10 Risks'!C11) | B8: =IF('Top 10 Risks'!D11="","",'Top 10 Risks'!D11) | C8: =IF(RADAR!C8="","",RADAR!C8) -> TECH | D8: =IF(RADAR!D8="","",RADAR!D8) | E8: =IF(RADAR!E8="","",RADAR!E8) | F8: =IF(E8="","",MIN(10,MAX(1,2*LN(E8+1)))) | G8: =IF(D8="","",D8*E8) | H8: 7 | I8: =CORE!$D$36 -> 6.885 | J8: =CORE!$D$44 -> 6.475 | K8: =IF('Top 10 Risks'!D11="","",10*(IF(OR('Risk Control'!E10=FALSE(),'Risk Control'!E10=""),0,'Risk Control'!E10/4)*0.2+IF(OR('Risk Control'!L10=FALSE(),'Risk Control'!L10=""),0,'Risk Control'!L10/4)*0.15+IF(OR('Risk Control'!S10=FALSE(),'Risk Control'!S10=""),0,'Risk Control'!S10/5)*0.25+IF(OR('Risk Control'!AA10=FALSE(),'Risk Control'!AA10=""),0,'Risk Control'!AA10/5)*0.25+IF(OR('Risk Control'!AI10=FALSE(),'Risk Control'!AI10=""),0,'Risk Control'!AI10/5)*0.15)) | L8: =IF(OR(I8="",K8=""),0,(I8/10)*MAX(0,K8/10)) -> 0 | M8: =Company_RI!$F$22/10 -> 0.78 | N8: =IF(OR(L8="",M8=""),0,L8*M8) -> 0 | O8: =IF(OR(H8="",H8=0),"",((10-H8)*3)*(1-IFERROR(L8*M8,0))) -> 9 | P8: =IF(OR(E8="",E8=0),"",E8*(1-IFERROR(L8,0))) | Q8: =IF(P8="","",MIN(10,MAX(1,2*LN(P8+1)))) | R8: =IF(OR(O8="",O8=0),"",O8*Company_RI!$D$32) -> 11.8035 | S8: =IF(R8="","",R8*30.44) -> 359.29854 | T8: =IF(OR(H8="",O8="",O8=0),"",(H8/10)*(1-IFERROR(N8,0))/MAX(O8,0.1)) -> 0.077777778 | U8: =IF(T8="","",IF(T8>=2,"IMMEDIATE",IF(T8>=1,"URGENT",IF(T8>=0.5,"ELEVATED","STANDARD")))) -> STANDARD | V8: =Company_RI!$D$30 -> 0.19345 | W8: =IF(P8="","",P8*(1-1.645*V8)) | X8: =IF(P8="","",P8) | Y8: =IF(P8="","",P8*(1+1.645*V8)) | Z8: =IF(OR(P8="",P8=0),"",(E8-P8)/P8) | AA8: =IF(OR(O8="",O8=0),"",ROUND(-LN(0.75)/Company_RI!$D$31,0)) -> 8 | AB8: =IF(OR(O8="",O8=0),"",ROUND(-LN(0.5)/Company_RI!$D$31,0)) -> 18 | AC8: =IF(OR(O8="",O8=0),"",ROUND(-LN(0.25)/Company_RI!$D$31,0)) -> 36 | AD8: =IF(OR(O8="",O8=0),"",ROUND(-LN(0.05)/Company_RI!$D$31,0)) -> 78 | AE8: MONITORING | AF8: =IF('Top 10 Risks'!E11="","",'Top 10 Risks'!E11)
A9: =IF('Top 10 Risks'!D12="","",'Top 10 Risks'!C12) | B9: =IF('Top 10 Risks'!D12="","",'Top 10 Risks'!D12) | C9: =IF(RADAR!C9="","",RADAR!C9) | D9: =IF(RADAR!D9="","",RADAR!D9) | E9: =IF(RADAR!E9="","",RADAR!E9) | F9: =IF(E9="","",MIN(10,MAX(1,2*LN(E9+1)))) | G9: =IF(D9="","",D9*E9) | I9: =CORE!$D$36 -> 6.885 | J9: =CORE!$D$44 -> 6.475 | K9: =IF('Top 10 Risks'!D12="","",10*(IF(OR('Risk Control'!E11=FALSE(),'Risk Control'!E11=""),0,'Risk Control'!E11/4)*0.2+IF(OR('Risk Control'!L11=FALSE(),'Risk Control'!L11=""),0,'Risk Control'!L11/4)*0.15+IF(OR('Risk Control'!S11=FALSE(),'Risk Control'!S11=""),0,'Risk Control'!S11/5)*0.25+IF(OR('Risk Control'!AA11=FALSE(),'Risk Control'!AA11=""),0,'Risk Control'!AA11/5)*0.25+IF(OR('Risk Control'!AI11=FALSE(),'Risk Control'!AI11=""),0,'Risk Control'!AI11/5)*0.15)) | L9: =IF(OR(I9="",K9=""),0,(I9/10)*MAX(0,K9/10)) -> 0 | M9: =Company_RI!$F$22/10 -> 0.78 | N9: =IF(OR(L9="",M9=""),0,L9*M9) -> 0 | O9: =IF(OR(H9="",H9=0),"",((10-H9)*3)*(1-IFERROR(L9*M9,0))) | P9: =IF(OR(E9="",E9=0),"",E9*(1-IFERROR(L9,0))) | Q9: =IF(P9="","",MIN(10,MAX(1,2*LN(P9+1)))) | R9: =IF(OR(O9="",O9=0),"",O9*Company_RI!$D$32) | S9: =IF(R9="","",R9*30.44) | T9: =IF(OR(H9="",O9="",O9=0),"",(H9/10)*(1-IFERROR(N9,0))/MAX(O9,0.1)) | U9: =IF(T9="","",IF(T9>=2,"IMMEDIATE",IF(T9>=1,"URGENT",IF(T9>=0.5,"ELEVATED","STANDARD")))) | V9: =Company_RI!$D$30 -> 0.19345 | W9: =IF(P9="","",P9*(1-1.645*V9)) | X9: =IF(P9="","",P9) | Y9: =IF(P9="","",P9*(1+1.645*V9)) | Z9: =IF(OR(P9="",P9=0),"",(E9-P9)/P9) | AA9: =IF(OR(O9="",O9=0),"",ROUND(-LN(0.75)/Company_RI!$D$31,0)) | AB9: =IF(OR(O9="",O9=0),"",ROUND(-LN(0.5)/Company_RI!$D$31,0)) | AC9: =IF(OR(O9="",O9=0),"",ROUND(-LN(0.25)/Company_RI!$D$31,0)) | AD9: =IF(OR(O9="",O9=0),"",ROUND(-LN(0.05)/Company_RI!$D$31,0)) | AF9: =IF('Top 10 Risks'!E12="","",'Top 10 Risks'!E12)
A10: =IF('Top 10 Risks'!D13="","",'Top 10 Risks'!C13) | B10: =IF('Top 10 Risks'!D13="","",'Top 10 Risks'!D13) | C10: =IF(RADAR!C10="","",RADAR!C10) | D10: =IF(RADAR!D10="","",RADAR!D10) | E10: =IF(RADAR!E10="","",RADAR!E10) | F10: =IF(E10="","",MIN(10,MAX(1,2*LN(E10+1)))) | G10: =IF(D10="","",D10*E10) | I10: =CORE!$D$36 -> 6.885 | J10: =CORE!$D$44 -> 6.475 | K10: =IF('Top 10 Risks'!D13="","",10*(IF(OR('Risk Control'!E12=FALSE(),'Risk Control'!E12=""),0,'Risk Control'!E12/4)*0.2+IF(OR('Risk Control'!L12=FALSE(),'Risk Control'!L12=""),0,'Risk Control'!L12/4)*0.15+IF(OR('Risk Control'!S12=FALSE(),'Risk Control'!S12=""),0,'Risk Control'!S12/5)*0.25+IF(OR('Risk Control'!AA12=FALSE(),'Risk Control'!AA12=""),0,'Risk Control'!AA12/5)*0.25+IF(OR('Risk Control'!AI12=FALSE(),'Risk Control'!AI12=""),0,'Risk Control'!AI12/5)*0.15)) | L10: =IF(OR(I10="",K10=""),0,(I10/10)*MAX(0,K10/10)) -> 0 | M10: =Company_RI!$F$22/10 -> 0.78 | N10: =IF(OR(L10="",M10=""),0,L10*M10) -> 0 | O10: =IF(OR(H10="",H10=0),"",((10-H10)*3)*(1-IFERROR(L10*M10,0))) | P10: =IF(OR(E10="",E10=0),"",E10*(1-IFERROR(L10,0))) | Q10: =IF(P10="","",MIN(10,MAX(1,2*LN(P10+1)))) | R10: =IF(OR(O10="",O10=0),"",O10*Company_RI!$D$32) | S10: =IF(R10="","",R10*30.44) | T10: =IF(OR(H10="",O10="",O10=0),"",(H10/10)*(1-IFERROR(N10,0))/MAX(O10,0.1)) | U10: =IF(T10="","",IF(T10>=2,"IMMEDIATE",IF(T10>=1,"URGENT",IF(T10>=0.5,"ELEVATED","STANDARD")))) | V10: =Company_RI!$D$30 -> 0.19345 | W10: =IF(P10="","",P10*(1-1.645*V10)) | X10: =IF(P10="","",P10) | Y10: =IF(P10="","",P10*(1+1.645*V10)) | Z10: =IF(OR(P10="",P10=0),"",(E10-P10)/P10) | AA10: =IF(OR(O10="",O10=0),"",ROUND(-LN(0.75)/Company_RI!$D$31,0)) | AB10: =IF(OR(O10="",O10=0),"",ROUND(-LN(0.5)/Company_RI!$D$31,0)) | AC10: =IF(OR(O10="",O10=0),"",ROUND(-LN(0.25)/Company_RI!$D$31,0)) | AD10: =IF(OR(O10="",O10=0),"",ROUND(-LN(0.05)/Company_RI!$D$31,0)) | AF10: =IF('Top 10 Risks'!E13="","",'Top 10 Risks'!E13)
A11: =IF('Top 10 Risks'!D14="","",'Top 10 Risks'!C14) | B11: =IF('Top 10 Risks'!D14="","",'Top 10 Risks'!D14) | C11: =IF(RADAR!C11="","",RADAR!C11) | D11: =IF(RADAR!D11="","",RADAR!D11) | E11: =IF(RADAR!E11="","",RADAR!E11) | F11: =IF(E11="","",MIN(10,MAX(1,2*LN(E11+1)))) | G11: =IF(D11="","",D11*E11) | I11: =CORE!$D$36 -> 6.885 | J11: =CORE!$D$44 -> 6.475 | K11: =IF('Top 10 Risks'!D14="","",10*(IF(OR('Risk Control'!E13=FALSE(),'Risk Control'!E13=""),0,'Risk Control'!E13/4)*0.2+IF(OR('Risk Control'!L13=FALSE(),'Risk Control'!L13=""),0,'Risk Control'!L13/4)*0.15+IF(OR('Risk Control'!S13=FALSE(),'Risk Control'!S13=""),0,'Risk Control'!S13/5)*0.25+IF(OR('Risk Control'!AA13=FALSE(),'Risk Control'!AA13=""),0,'Risk Control'!AA13/5)*0.25+IF(OR('Risk Control'!AI13=FALSE(),'Risk Control'!AI13=""),0,'Risk Control'!AI13/5)*0.15)) | L11: =IF(OR(I11="",K11=""),0,(I11/10)*MAX(0,K11/10)) -> 0 | M11: =Company_RI!$F$22/10 -> 0.78 | N11: =IF(OR(L11="",M11=""),0,L11*M11) -> 0 | O11: =IF(OR(H11="",H11=0),"",((10-H11)*3)*(1-IFERROR(L11*M11,0))) | P11: =IF(OR(E11="",E11=0),"",E11*(1-IFERROR(L11,0))) | Q11: =IF(P11="","",MIN(10,MAX(1,2*LN(P11+1)))) | R11: =IF(OR(O11="",O11=0),"",O11*Company_RI!$D$32) | S11: =IF(R11="","",R11*30.44) | T11: =IF(OR(H11="",O11="",O11=0),"",(H11/10)*(1-IFERROR(N11,0))/MAX(O11,0.1)) | U11: =IF(T11="","",IF(T11>=2,"IMMEDIATE",IF(T11>=1,"URGENT",IF(T11>=0.5,"ELEVATED","STANDARD")))) | V11: =Company_RI!$D$30 -> 0.19345 | W11: =IF(P11="","",P11*(1-1.645*V11)) | X11: =IF(P11="","",P11) | Y11: =IF(P11="","",P11*(1+1.645*V11)) | Z11: =IF(OR(P11="",P11=0),"",(E11-P11)/P11) | AA11: =IF(OR(O11="",O11=0),"",ROUND(-LN(0.75)/Company_RI!$D$31,0)) | AB11: =IF(OR(O11="",O11=0),"",ROUND(-LN(0.5)/Company_RI!$D$31,0)) | AC11: =IF(OR(O11="",O11=0),"",ROUND(-LN(0.25)/Company_RI!$D$31,0)) | AD11: =IF(OR(O11="",O11=0),"",ROUND(-LN(0.05)/Company_RI!$D$31,0)) | AF11: =IF('Top 10 Risks'!E14="","",'Top 10 Risks'!E14)
A12: =IF('Top 10 Risks'!D15="","",'Top 10 Risks'!C15) | B12: =IF('Top 10 Risks'!D15="","",'Top 10 Risks'!D15) | C12: =IF(RADAR!C12="","",RADAR!C12) | D12: =IF(RADAR!D12="","",RADAR!D12) | E12: =IF(RADAR!E12="","",RADAR!E12) | F12: =IF(E12="","",MIN(10,MAX(1,2*LN(E12+1)))) | G12: =IF(D12="","",D12*E12) | I12: =CORE!$D$36 -> 6.885 | J12: =CORE!$D$44 -> 6.475 | K12: =IF('Top 10 Risks'!D15="","",10*(IF(OR('Risk Control'!E14=FALSE(),'Risk Control'!E14=""),0,'Risk Control'!E14/4)*0.2+IF(OR('Risk Control'!L14=FALSE(),'Risk Control'!L14=""),0,'Risk Control'!L14/4)*0.15+IF(OR('Risk Control'!S14=FALSE(),'Risk Control'!S14=""),0,'Risk Control'!S14/5)*0.25+IF(OR('Risk Control'!AA14=FALSE(),'Risk Control'!AA14=""),0,'Risk Control'!AA14/5)*0.25+IF(OR('Risk Control'!AI14=FALSE(),'Risk Control'!AI14=""),0,'Risk Control'!AI14/5)*0.15)) | L12: =IF(OR(I12="",K12=""),0,(I12/10)*MAX(0,K12/10)) -> 0 | M12: =Company_RI!$F$22/10 -> 0.78 | N12: =IF(OR(L12="",M12=""),0,L12*M12) -> 0 | O12: =IF(OR(H12="",H12=0),"",((10-H12)*3)*(1-IFERROR(L12*M12,0))) | P12: =IF(OR(E12="",E12=0),"",E12*(1-IFERROR(L12,0))) | Q12: =IF(P12="","",MIN(10,MAX(1,2*LN(P12+1)))) | R12: =IF(OR(O12="",O12=0),"",O12*Company_RI!$D$32) | S12: =IF(R12="","",R12*30.44) | T12: =IF(OR(H12="",O12="",O12=0),"",(H12/10)*(1-IFERROR(N12,0))/MAX(O12,0.1)) | U12: =IF(T12="","",IF(T12>=2,"IMMEDIATE",IF(T12>=1,"URGENT",IF(T12>=0.5,"ELEVATED","STANDARD")))) | V12: =Company_RI!$D$30 -> 0.19345 | W12: =IF(P12="","",P12*(1-1.645*V12)) | X12: =IF(P12="","",P12) | Y12: =IF(P12="","",P12*(1+1.645*V12)) | Z12: =IF(OR(P12="",P12=0),"",(E12-P12)/P12) | AA12: =IF(OR(O12="",O12=0),"",ROUND(-LN(0.75)/Company_RI!$D$31,0)) | AB12: =IF(OR(O12="",O12=0),"",ROUND(-LN(0.5)/Company_RI!$D$31,0)) | AC12: =IF(OR(O12="",O12=0),"",ROUND(-LN(0.25)/Company_RI!$D$31,0)) | AD12: =IF(OR(O12="",O12=0),"",ROUND(-LN(0.05)/Company_RI!$D$31,0)) | AF12: =IF('Top 10 Risks'!E15="","",'Top 10 Risks'!E15)
A13: =IF('Top 10 Risks'!D16="","",'Top 10 Risks'!C16) | B13: =IF('Top 10 Risks'!D16="","",'Top 10 Risks'!D16) | C13: =IF(RADAR!C13="","",RADAR!C13) | D13: =IF(RADAR!D13="","",RADAR!D13) | E13: =IF(RADAR!E13="","",RADAR!E13) | F13: =IF(E13="","",MIN(10,MAX(1,2*LN(E13+1)))) | G13: =IF(D13="","",D13*E13) | I13: =CORE!$D$36 -> 6.885 | J13: =CORE!$D$44 -> 6.475 | K13: =IF('Top 10 Risks'!D16="","",10*(IF(OR('Risk Control'!E15=FALSE(),'Risk Control'!E15=""),0,'Risk Control'!E15/4)*0.2+IF(OR('Risk Control'!L15=FALSE(),'Risk Control'!L15=""),0,'Risk Control'!L15/4)*0.15+IF(OR('Risk Control'!S15=FALSE(),'Risk Control'!S15=""),0,'Risk Control'!S15/5)*0.25+IF(OR('Risk Control'!AA15=FALSE(),'Risk Control'!AA15=""),0,'Risk Control'!AA15/5)*0.25+IF(OR('Risk Control'!AI15=FALSE(),'Risk Control'!AI15=""),0,'Risk Control'!AI15/5)*0.15)) | L13: =IF(OR(I13="",K13=""),0,(I13/10)*MAX(0,K13/10)) -> 0 | M13: =Company_RI!$F$22/10 -> 0.78 | N13: =IF(OR(L13="",M13=""),0,L13*M13) -> 0 | O13: =IF(OR(H13="",H13=0),"",((10-H13)*3)*(1-IFERROR(L13*M13,0))) | P13: =IF(OR(E13="",E13=0),"",E13*(1-IFERROR(L13,0))) | Q13: =IF(P13="","",MIN(10,MAX(1,2*LN(P13+1)))) | R13: =IF(OR(O13="",O13=0),"",O13*Company_RI!$D$32) | S13: =IF(R13="","",R13*30.44) | T13: =IF(OR(H13="",O13="",O13=0),"",(H13/10)*(1-IFERROR(N13,0))/MAX(O13,0.1)) | U13: =IF(T13="","",IF(T13>=2,"IMMEDIATE",IF(T13>=1,"URGENT",IF(T13>=0.5,"ELEVATED","STANDARD")))) | V13: =Company_RI!$D$30 -> 0.19345 | W13: =IF(P13="","",P13*(1-1.645*V13)) | X13: =IF(P13="","",P13) | Y13: =IF(P13="","",P13*(1+1.645*V13)) | Z13: =IF(OR(P13="",P13=0),"",(E13-P13)/P13) | AA13: =IF(OR(O13="",O13=0),"",ROUND(-LN(0.75)/Company_RI!$D$31,0)) | AB13: =IF(OR(O13="",O13=0),"",ROUND(-LN(0.5)/Company_RI!$D$31,0)) | AC13: =IF(OR(O13="",O13=0),"",ROUND(-LN(0.25)/Company_RI!$D$31,0)) | AD13: =IF(OR(O13="",O13=0),"",ROUND(-LN(0.05)/Company_RI!$D$31,0)) | AF13: =IF('Top 10 Risks'!E16="","",'Top 10 Risks'!E16)
A14: =IF('Top 10 Risks'!D17="","",'Top 10 Risks'!C17) | B14: =IF('Top 10 Risks'!D17="","",'Top 10 Risks'!D17) | C14: =IF(RADAR!C14="","",RADAR!C14) | D14: =IF(RADAR!D14="","",RADAR!D14) | E14: =IF(RADAR!E14="","",RADAR!E14) | F14: =IF(E14="","",MIN(10,MAX(1,2*LN(E14+1)))) | G14: =IF(D14="","",D14*E14) | I14: =CORE!$D$36 -> 6.885 | J14: =CORE!$D$44 -> 6.475 | K14: =IF('Top 10 Risks'!D17="","",10*(IF(OR('Risk Control'!E16=FALSE(),'Risk Control'!E16=""),0,'Risk Control'!E16/4)*0.2+IF(OR('Risk Control'!L16=FALSE(),'Risk Control'!L16=""),0,'Risk Control'!L16/4)*0.15+IF(OR('Risk Control'!S16=FALSE(),'Risk Control'!S16=""),0,'Risk Control'!S16/5)*0.25+IF(OR('Risk Control'!AA16=FALSE(),'Risk Control'!AA16=""),0,'Risk Control'!AA16/5)*0.25+IF(OR('Risk Control'!AI16=FALSE(),'Risk Control'!AI16=""),0,'Risk Control'!AI16/5)*0.15)) | L14: =IF(OR(I14="",K14=""),0,(I14/10)*MAX(0,K14/10)) -> 0 | M14: =Company_RI!$F$22/10 -> 0.78 | N14: =IF(OR(L14="",M14=""),0,L14*M14) -> 0 | O14: =IF(OR(H14="",H14=0),"",((10-H14)*3)*(1-IFERROR(L14*M14,0))) | P14: =IF(OR(E14="",E14=0),"",E14*(1-IFERROR(L14,0))) | Q14: =IF(P14="","",MIN(10,MAX(1,2*LN(P14+1)))) | R14: =IF(OR(O14="",O14=0),"",O14*Company_RI!$D$32) | S14: =IF(R14="","",R14*30.44) | T14: =IF(OR(H14="",O14="",O14=0),"",(H14/10)*(1-IFERROR(N14,0))/MAX(O14,0.1)) | U14: =IF(T14="","",IF(T14>=2,"IMMEDIATE",IF(T14>=1,"URGENT",IF(T14>=0.5,"ELEVATED","STANDARD")))) | V14: =Company_RI!$D$30 -> 0.19345 | W14: =IF(P14="","",P14*(1-1.645*V14)) | X14: =IF(P14="","",P14) | Y14: =IF(P14="","",P14*(1+1.645*V14)) | Z14: =IF(OR(P14="",P14=0),"",(E14-P14)/P14) | AA14: =IF(OR(O14="",O14=0),"",ROUND(-LN(0.75)/Company_RI!$D$31,0)) | AB14: =IF(OR(O14="",O14=0),"",ROUND(-LN(0.5)/Company_RI!$D$31,0)) | AC14: =IF(OR(O14="",O14=0),"",ROUND(-LN(0.25)/Company_RI!$D$31,0)) | AD14: =IF(OR(O14="",O14=0),"",ROUND(-LN(0.05)/Company_RI!$D$31,0)) | AF14: =IF('Top 10 Risks'!E17="","",'Top 10 Risks'!E17)
A15: =IF('Top 10 Risks'!D18="","",'Top 10 Risks'!C18) | B15: =IF('Top 10 Risks'!D18="","",'Top 10 Risks'!D18) | C15: =IF(RADAR!C15="","",RADAR!C15) | D15: =IF(RADAR!D15="","",RADAR!D15) | E15: =IF(RADAR!E15="","",RADAR!E15) | F15: =IF(E15="","",MIN(10,MAX(1,2*LN(E15+1)))) | G15: =IF(D15="","",D15*E15) | I15: =CORE!$D$36 -> 6.885 | J15: =CORE!$D$44 -> 6.475 | K15: =IF('Top 10 Risks'!D18="","",10*(IF(OR('Risk Control'!E17=FALSE(),'Risk Control'!E17=""),0,'Risk Control'!E17/4)*0.2+IF(OR('Risk Control'!L17=FALSE(),'Risk Control'!L17=""),0,'Risk Control'!L17/4)*0.15+IF(OR('Risk Control'!S17=FALSE(),'Risk Control'!S17=""),0,'Risk Control'!S17/5)*0.25+IF(OR('Risk Control'!AA17=FALSE(),'Risk Control'!AA17=""),0,'Risk Control'!AA17/5)*0.25+IF(OR('Risk Control'!AI17=FALSE(),'Risk Control'!AI17=""),0,'Risk Control'!AI17/5)*0.15)) | L15: =IF(OR(I15="",K15=""),0,(I15/10)*MAX(0,K15/10)) -> 0 | M15: =Company_RI!$F$22/10 -> 0.78 | N15: =IF(OR(L15="",M15=""),0,L15*M15) -> 0 | O15: =IF(OR(H15="",H15=0),"",((10-H15)*3)*(1-IFERROR(L15*M15,0))) | P15: =IF(OR(E15="",E15=0),"",E15*(1-IFERROR(L15,0))) | Q15: =IF(P15="","",MIN(10,MAX(1,2*LN(P15+1)))) | R15: =IF(OR(O15="",O15=0),"",O15*Company_RI!$D$32) | S15: =IF(R15="","",R15*30.44) | T15: =IF(OR(H15="",O15="",O15=0),"",(H15/10)*(1-IFERROR(N15,0))/MAX(O15,0.1)) | U15: =IF(T15="","",IF(T15>=2,"IMMEDIATE",IF(T15>=1,"URGENT",IF(T15>=0.5,"ELEVATED","STANDARD")))) | V15: =Company_RI!$D$30 -> 0.19345 | W15: =IF(P15="","",P15*(1-1.645*V15)) | X15: =IF(P15="","",P15) | Y15: =IF(P15="","",P15*(1+1.645*V15)) | Z15: =IF(OR(P15="",P15=0),"",(E15-P15)/P15) | AA15: =IF(OR(O15="",O15=0),"",ROUND(-LN(0.75)/Company_RI!$D$31,0)) | AB15: =IF(OR(O15="",O15=0),"",ROUND(-LN(0.5)/Company_RI!$D$31,0)) | AC15: =IF(OR(O15="",O15=0),"",ROUND(-LN(0.25)/Company_RI!$D$31,0)) | AD15: =IF(OR(O15="",O15=0),"",ROUND(-LN(0.05)/Company_RI!$D$31,0)) | AF15: =IF('Top 10 Risks'!E18="","",'Top 10 Risks'!E18)
A16: =IF('Top 10 Risks'!D19="","",'Top 10 Risks'!C19) | B16: =IF('Top 10 Risks'!D19="","",'Top 10 Risks'!D19) | C16: =IF(RADAR!C16="","",RADAR!C16) | D16: =IF(RADAR!D16="","",RADAR!D16) | E16: =IF(RADAR!E16="","",RADAR!E16) | F16: =IF(E16="","",MIN(10,MAX(1,2*LN(E16+1)))) | G16: =IF(D16="","",D16*E16) | I16: =CORE!$D$36 -> 6.885 | J16: =CORE!$D$44 -> 6.475 | K16: =IF('Top 10 Risks'!D19="","",10*(IF(OR('Risk Control'!E18=FALSE(),'Risk Control'!E18=""),0,'Risk Control'!E18/4)*0.2+IF(OR('Risk Control'!L18=FALSE(),'Risk Control'!L18=""),0,'Risk Control'!L18/4)*0.15+IF(OR('Risk Control'!S18=FALSE(),'Risk Control'!S18=""),0,'Risk Control'!S18/5)*0.25+IF(OR('Risk Control'!AA18=FALSE(),'Risk Control'!AA18=""),0,'Risk Control'!AA18/5)*0.25+IF(OR('Risk Control'!AI18=FALSE(),'Risk Control'!AI18=""),0,'Risk Control'!AI18/5)*0.15)) | L16: =IF(OR(I16="",K16=""),0,(I16/10)*MAX(0,K16/10)) -> 0 | M16: =Company_RI!$F$22/10 -> 0.78 | N16: =IF(OR(L16="",M16=""),0,L16*M16) -> 0 | O16: =IF(OR(H16="",H16=0),"",((10-H16)*3)*(1-IFERROR(L16*M16,0))) | P16: =IF(OR(E16="",E16=0),"",E16*(1-IFERROR(L16,0))) | Q16: =IF(P16="","",MIN(10,MAX(1,2*LN(P16+1)))) | R16: =IF(OR(O16="",O16=0),"",O16*Company_RI!$D$32) | S16: =IF(R16="","",R16*30.44) | T16: =IF(OR(H16="",O16="",O16=0),"",(H16/10)*(1-IFERROR(N16,0))/MAX(O16,0.1)) | U16: =IF(T16="","",IF(T16>=2,"IMMEDIATE",IF(T16>=1,"URGENT",IF(T16>=0.5,"ELEVATED","STANDARD")))) | V16: =Company_RI!$D$30 -> 0.19345 | W16: =IF(P16="","",P16*(1-1.645*V16)) | X16: =IF(P16="","",P16) | Y16: =IF(P16="","",P16*(1+1.645*V16)) | Z16: =IF(OR(P16="",P16=0),"",(E16-P16)/P16) | AA16: =IF(OR(O16="",O16=0),"",ROUND(-LN(0.75)/Company_RI!$D$31,0)) | AB16: =IF(OR(O16="",O16=0),"",ROUND(-LN(0.5)/Company_RI!$D$31,0)) | AC16: =IF(OR(O16="",O16=0),"",ROUND(-LN(0.25)/Company_RI!$D$31,0)) | AD16: =IF(OR(O16="",O16=0),"",ROUND(-LN(0.05)/Company_RI!$D$31,0)) | AF16: =IF('Top 10 Risks'!E19="","",'Top 10 Risks'!E19)
A17: =IF('Top 10 Risks'!D20="","",'Top 10 Risks'!C20) | B17: =IF('Top 10 Risks'!D20="","",'Top 10 Risks'!D20) | C17: =IF(RADAR!C17="","",RADAR!C17) | D17: =IF(RADAR!D17="","",RADAR!D17) | E17: =IF(RADAR!E17="","",RADAR!E17) | F17: =IF(E17="","",MIN(10,MAX(1,2*LN(E17+1)))) | G17: =IF(D17="","",D17*E17) | I17: =CORE!$D$36 -> 6.885 | J17: =CORE!$D$44 -> 6.475 | K17: =IF('Top 10 Risks'!D20="","",10*(IF(OR('Risk Control'!E19=FALSE(),'Risk Control'!E19=""),0,'Risk Control'!E19/4)*0.2+IF(OR('Risk Control'!L19=FALSE(),'Risk Control'!L19=""),0,'Risk Control'!L19/4)*0.15+IF(OR('Risk Control'!S19=FALSE(),'Risk Control'!S19=""),0,'Risk Control'!S19/5)*0.25+IF(OR('Risk Control'!AA19=FALSE(),'Risk Control'!AA19=""),0,'Risk Control'!AA19/5)*0.25+IF(OR('Risk Control'!AI19=FALSE(),'Risk Control'!AI19=""),0,'Risk Control'!AI19/5)*0.15)) | L17: =IF(OR(I17="",K17=""),0,(I17/10)*MAX(0,K17/10)) -> 0 | M17: =Company_RI!$F$22/10 -> 0.78 | N17: =IF(OR(L17="",M17=""),0,L17*M17) -> 0 | O17: =IF(OR(H17="",H17=0),"",((10-H17)*3)*(1-IFERROR(L17*M17,0))) | P17: =IF(OR(E17="",E17=0),"",E17*(1-IFERROR(L17,0))) | Q17: =IF(P17="","",MIN(10,MAX(1,2*LN(P17+1)))) | R17: =IF(OR(O17="",O17=0),"",O17*Company_RI!$D$32) | S17: =IF(R17="","",R17*30.44) | T17: =IF(OR(H17="",O17="",O17=0),"",(H17/10)*(1-IFERROR(N17,0))/MAX(O17,0.1)) | U17: =IF(T17="","",IF(T17>=2,"IMMEDIATE",IF(T17>=1,"URGENT",IF(T17>=0.5,"ELEVATED","STANDARD")))) | V17: =Company_RI!$D$30 -> 0.19345 | W17: =IF(P17="","",P17*(1-1.645*V17)) | X17: =IF(P17="","",P17) | Y17: =IF(P17="","",P17*(1+1.645*V17)) | Z17: =IF(OR(P17="",P17=0),"",(E17-P17)/P17) | AA17: =IF(OR(O17="",O17=0),"",ROUND(-LN(0.75)/Company_RI!$D$31,0)) | AB17: =IF(OR(O17="",O17=0),"",ROUND(-LN(0.5)/Company_RI!$D$31,0)) | AC17: =IF(OR(O17="",O17=0),"",ROUND(-LN(0.25)/Company_RI!$D$31,0)) | AD17: =IF(OR(O17="",O17=0),"",ROUND(-LN(0.05)/Company_RI!$D$31,0)) | AF17: =IF('Top 10 Risks'!E20="","",'Top 10 Risks'!E20)
A18: =IF('Top 10 Risks'!D21="","",'Top 10 Risks'!C21) | B18: =IF('Top 10 Risks'!D21="","",'Top 10 Risks'!D21) | C18: =IF(RADAR!C18="","",RADAR!C18) | D18: =IF(RADAR!D18="","",RADAR!D18) | E18: =IF(RADAR!E18="","",RADAR!E18) | F18: =IF(E18="","",MIN(10,MAX(1,2*LN(E18+1)))) | G18: =IF(D18="","",D18*E18) | I18: =CORE!$D$36 -> 6.885 | J18: =CORE!$D$44 -> 6.475 | K18: =IF('Top 10 Risks'!D21="","",10*(IF(OR('Risk Control'!E20=FALSE(),'Risk Control'!E20=""),0,'Risk Control'!E20/4)*0.2+IF(OR('Risk Control'!L20=FALSE(),'Risk Control'!L20=""),0,'Risk Control'!L20/4)*0.15+IF(OR('Risk Control'!S20=FALSE(),'Risk Control'!S20=""),0,'Risk Control'!S20/5)*0.25+IF(OR('Risk Control'!AA20=FALSE(),'Risk Control'!AA20=""),0,'Risk Control'!AA20/5)*0.25+IF(OR('Risk Control'!AI20=FALSE(),'Risk Control'!AI20=""),0,'Risk Control'!AI20/5)*0.15)) | L18: =IF(OR(I18="",K18=""),0,(I18/10)*MAX(0,K18/10)) -> 0 | M18: =Company_RI!$F$22/10 -> 0.78 | N18: =IF(OR(L18="",M18=""),0,L18*M18) -> 0 | O18: =IF(OR(H18="",H18=0),"",((10-H18)*3)*(1-IFERROR(L18*M18,0))) | P18: =IF(OR(E18="",E18=0),"",E18*(1-IFERROR(L18,0))) | Q18: =IF(P18="","",MIN(10,MAX(1,2*LN(P18+1)))) | R18: =IF(OR(O18="",O18=0),"",O18*Company_RI!$D$32) | S18: =IF(R18="","",R18*30.44) | T18: =IF(OR(H18="",O18="",O18=0),"",(H18/10)*(1-IFERROR(N18,0))/MAX(O18,0.1)) | U18: =IF(T18="","",IF(T18>=2,"IMMEDIATE",IF(T18>=1,"URGENT",IF(T18>=0.5,"ELEVATED","STANDARD")))) | V18: =Company_RI!$D$30 -> 0.19345 | W18: =IF(P18="","",P18*(1-1.645*V18)) | X18: =IF(P18="","",P18) | Y18: =IF(P18="","",P18*(1+1.645*V18)) | Z18: =IF(OR(P18="",P18=0),"",(E18-P18)/P18) | AA18: =IF(OR(O18="",O18=0),"",ROUND(-LN(0.75)/Company_RI!$D$31,0)) | AB18: =IF(OR(O18="",O18=0),"",ROUND(-LN(0.5)/Company_RI!$D$31,0)) | AC18: =IF(OR(O18="",O18=0),"",ROUND(-LN(0.25)/Company_RI!$D$31,0)) | AD18: =IF(OR(O18="",O18=0),"",ROUND(-LN(0.05)/Company_RI!$D$31,0)) | AF18: =IF('Top 10 Risks'!E21="","",'Top 10 Risks'!E21)
A19: =IF('Top 10 Risks'!D22="","",'Top 10 Risks'!C22) | B19: =IF('Top 10 Risks'!D22="","",'Top 10 Risks'!D22) | C19: =IF(RADAR!C19="","",RADAR!C19) | D19: =IF(RADAR!D19="","",RADAR!D19) | E19: =IF(RADAR!E19="","",RADAR!E19) | F19: =IF(E19="","",MIN(10,MAX(1,2*LN(E19+1)))) | G19: =IF(D19="","",D19*E19) | I19: =CORE!$D$36 -> 6.885 | J19: =CORE!$D$44 -> 6.475 | K19: =IF('Top 10 Risks'!D22="","",10*(IF(OR('Risk Control'!E21=FALSE(),'Risk Control'!E21=""),0,'Risk Control'!E21/4)*0.2+IF(OR('Risk Control'!L21=FALSE(),'Risk Control'!L21=""),0,'Risk Control'!L21/4)*0.15+IF(OR('Risk Control'!S21=FALSE(),'Risk Control'!S21=""),0,'Risk Control'!S21/5)*0.25+IF(OR('Risk Control'!AA21=FALSE(),'Risk Control'!AA21=""),0,'Risk Control'!AA21/5)*0.25+IF(OR('Risk Control'!AI21=FALSE(),'Risk Control'!AI21=""),0,'Risk Control'!AI21/5)*0.15)) | L19: =IF(OR(I19="",K19=""),0,(I19/10)*MAX(0,K19/10)) -> 0 | M19: =Company_RI!$F$22/10 -> 0.78 | N19: =IF(OR(L19="",M19=""),0,L19*M19) -> 0 | O19: =IF(OR(H19="",H19=0),"",((10-H19)*3)*(1-IFERROR(L19*M19,0))) | P19: =IF(OR(E19="",E19=0),"",E19*(1-IFERROR(L19,0))) | Q19: =IF(P19="","",MIN(10,MAX(1,2*LN(P19+1)))) | R19: =IF(OR(O19="",O19=0),"",O19*Company_RI!$D$32) | S19: =IF(R19="","",R19*30.44) | T19: =IF(OR(H19="",O19="",O19=0),"",(H19/10)*(1-IFERROR(N19,0))/MAX(O19,0.1)) | U19: =IF(T19="","",IF(T19>=2,"IMMEDIATE",IF(T19>=1,"URGENT",IF(T19>=0.5,"ELEVATED","STANDARD")))) | V19: =Company_RI!$D$30 -> 0.19345 | W19: =IF(P19="","",P19*(1-1.645*V19)) | X19: =IF(P19="","",P19) | Y19: =IF(P19="","",P19*(1+1.645*V19)) | Z19: =IF(OR(P19="",P19=0),"",(E19-P19)/P19) | AA19: =IF(OR(O19="",O19=0),"",ROUND(-LN(0.75)/Company_RI!$D$31,0)) | AB19: =IF(OR(O19="",O19=0),"",ROUND(-LN(0.5)/Company_RI!$D$31,0)) | AC19: =IF(OR(O19="",O19=0),"",ROUND(-LN(0.25)/Company_RI!$D$31,0)) | AD19: =IF(OR(O19="",O19=0),"",ROUND(-LN(0.05)/Company_RI!$D$31,0)) | AF19: =IF('Top 10 Risks'!E22="","",'Top 10 Risks'!E22)
A20: =IF('Top 10 Risks'!D23="","",'Top 10 Risks'!C23) | B20: =IF('Top 10 Risks'!D23="","",'Top 10 Risks'!D23) | C20: =IF(RADAR!C20="","",RADAR!C20) | D20: =IF(RADAR!D20="","",RADAR!D20) | E20: =IF(RADAR!E20="","",RADAR!E20) | F20: =IF(E20="","",MIN(10,MAX(1,2*LN(E20+1)))) | G20: =IF(D20="","",D20*E20) | I20: =CORE!$D$36 -> 6.885 | J20: =CORE!$D$44 -> 6.475 | K20: =IF('Top 10 Risks'!D23="","",10*(IF(OR('Risk Control'!E22=FALSE(),'Risk Control'!E22=""),0,'Risk Control'!E22/4)*0.2+IF(OR('Risk Control'!L22=FALSE(),'Risk Control'!L22=""),0,'Risk Control'!L22/4)*0.15+IF(OR('Risk Control'!S22=FALSE(),'Risk Control'!S22=""),0,'Risk Control'!S22/5)*0.25+IF(OR('Risk Control'!AA22=FALSE(),'Risk Control'!AA22=""),0,'Risk Control'!AA22/5)*0.25+IF(OR('Risk Control'!AI22=FALSE(),'Risk Control'!AI22=""),0,'Risk Control'!AI22/5)*0.15)) | L20: =IF(OR(I20="",K20=""),0,(I20/10)*MAX(0,K20/10)) -> 0 | M20: =Company_RI!$F$22/10 -> 0.78 | N20: =IF(OR(L20="",M20=""),0,L20*M20) -> 0 | O20: =IF(OR(H20="",H20=0),"",((10-H20)*3)*(1-IFERROR(L20*M20,0))) | P20: =IF(OR(E20="",E20=0),"",E20*(1-IFERROR(L20,0))) | Q20: =IF(P20="","",MIN(10,MAX(1,2*LN(P20+1)))) | R20: =IF(OR(O20="",O20=0),"",O20*Company_RI!$D$32) | S20: =IF(R20="","",R20*30.44) | T20: =IF(OR(H20="",O20="",O20=0),"",(H20/10)*(1-IFERROR(N20,0))/MAX(O20,0.1)) | U20: =IF(T20="","",IF(T20>=2,"IMMEDIATE",IF(T20>=1,"URGENT",IF(T20>=0.5,"ELEVATED","STANDARD")))) | V20: =Company_RI!$D$30 -> 0.19345 | W20: =IF(P20="","",P20*(1-1.645*V20)) | X20: =IF(P20="","",P20) | Y20: =IF(P20="","",P20*(1+1.645*V20)) | Z20: =IF(OR(P20="",P20=0),"",(E20-P20)/P20) | AA20: =IF(OR(O20="",O20=0),"",ROUND(-LN(0.75)/Company_RI!$D$31,0)) | AB20: =IF(OR(O20="",O20=0),"",ROUND(-LN(0.5)/Company_RI!$D$31,0)) | AC20: =IF(OR(O20="",O20=0),"",ROUND(-LN(0.25)/Company_RI!$D$31,0)) | AD20: =IF(OR(O20="",O20=0),"",ROUND(-LN(0.05)/Company_RI!$D$31,0)) | AF20: =IF('Top 10 Risks'!E23="","",'Top 10 Risks'!E23)
... A36: =IF('Top 10 Risks'!D39="","",'Top 10 Risks'!C39) | B36: =IF('Top 10 Risks'!D39="","",'Top 10 Risks'!D39) | C36: =IF(RADAR!C36="","",RADAR!C36) | D36: =IF(RADAR!D36="","",RADAR!D36) | E36: =IF(RADAR!E36="","",RADAR!E36) | F36: =IF(E36="","",MIN(10,MAX(1,2*LN(E36+1)))) | G36: =IF(D36="","",D36*E36) | I36: =CORE!$D$36 -> 6.885 | J36: =CORE!$D$44 -> 6.475 | K36: =IF('Top 10 Risks'!D39="","",10*(IF(OR('Risk Control'!E38=FALSE(),'Risk Control'!E38=""),0,'Risk Control'!E38/4)*0.2+IF(OR('Risk Control'!L38=FALSE(),'Risk Control'!L38=""),0,'Risk Control'!L38/4)*0.15+IF(OR('Risk Control'!S38=FALSE(),'Risk Control'!S38=""),0,'Risk Control'!S38/5)*0.25+IF(OR('Risk Control'!AA38=FALSE(),'Risk Control'!AA38=""),0,'Risk Control'!AA38/5)*0.25+IF(OR('Risk Control'!AI38=FALSE(),'Risk Control'!AI38=""),0,'Risk Control'!AI38/5)*0.15)) | L36: =IF(OR(I36="",K36=""),0,(I36/10)*MAX(0,K36/10)) -> 0 | M36: =Company_RI!$F$22/10 -> 0.78 | N36: =IF(OR(L36="",M36=""),0,L36*M36) -> 0 | O36: =IF(OR(H36="",H36=0),"",((10-H36)*3)*(1-IFERROR(L36*M36,0))) | P36: =IF(OR(E36="",E36=0),"",E36*(1-IFERROR(L36,0))) | Q36: =IF(P36="","",MIN(10,MAX(1,2*LN(P36+1)))) | R36: =IF(OR(O36="",O36=0),"",O36*Company_RI!$D$32) | S36: =IF(R36="","",R36*30.44) | T36: =IF(OR(H36="",O36="",O36=0),"",(H36/10)*(1-IFERROR(N36,0))/MAX(O36,0.1)) | U36: =IF(T36="","",IF(T36>=2,"IMMEDIATE",IF(T36>=1,"URGENT",IF(T36>=0.5,"ELEVATED","STANDARD")))) | V36: =Company_RI!$D$30 -> 0.19345 | W36: =IF(P36="","",P36*(1-1.645*V36)) | X36: =IF(P36="","",P36) | Y36: =IF(P36="","",P36*(1+1.645*V36)) | Z36: =IF(OR(P36="",P36=0),"",(E36-P36)/P36) | AA36: =IF(OR(O36="",O36=0),"",ROUND(-LN(0.75)/Company_RI!$D$31,0)) | AB36: =IF(OR(O36="",O36=0),"",ROUND(-LN(0.5)/Company_RI!$D$31,0)) | AC36: =IF(OR(O36="",O36=0),"",ROUND(-LN(0.25)/Company_RI!$D$31,0)) | AD36: =IF(OR(O36="",O36=0),"",ROUND(-LN(0.05)/Company_RI!$D$31,0)) | AF36: =IF('Top 10 Risks'!E39="","",'Top 10 Risks'!E39)

Sheet Opportunities
A1: Opportunity Register — Risk-Opportunity Duality
A2: SMI-amplified capture | High Phase Index = Max Risk for Incumbents = Max Opportunity for Challengers
A3: Company SMI: | B3: =CORE!D44 -> 6.475 | D3: OTS Amplifier: | E3: =Company_SMI!D26 -> 1.32375
A5: ID | B5: Opportunity | C5: Category | D5: Prob | E5: Upside(€M) | F5: Upside Score | G5: EV(€M) | H5: Window(mo) | I5: Strat Fit | J5: SMI Align | K5: Capture Idx | L5: OTS Amplified | M5: Invest(€M) | N5: ROI | O5: Priority | P5: Readiness | Q5: Notes
A6: O-001 | B6: Market Consolidation | C6: STR | D6: 0.6 | E6: 250 | F6: =IF(E6="","",MIN(10,MAX(1,2*LN(E6+1)))) -> 10 | G6: =IF(D6="","",D6*E6) -> 150 | H6: 12 | I6: 8 | J6: =IF(I6="","",(I6/10)*(CORE!$D$44/10)) -> 0.518 | K6: =IF(OR(J6="",H6="",H6=0),"",MIN(1,J6*D6*(10/H6))) -> 0.259 | L6: =IF(K6="","",K6*Company_SMI!$D$26) -> 0.34285125 | M6: 40 | N6: =IF(OR(G6="",M6="",M6=0),"",G6/M6) -> 3.75 | O6: =IF(L6="","",IF(L6>=0.7,"CAPTURE NOW",IF(L6>=0.4,"PREPARE",IF(L6>=0.2,"MONITOR","WATCH")))) -> MONITOR
A7: O-002 | B7: Tech Disruption Advantage | C7: TECH | D7: 0.45 | E7: 400 | F7: =IF(E7="","",MIN(10,MAX(1,2*LN(E7+1)))) -> 10 | G7: =IF(D7="","",D7*E7) -> 180 | H7: 18 | I7: 7 | J7: =IF(I7="","",(I7/10)*(CORE!$D$44/10)) -> 0.45325 | K7: =IF(OR(J7="",H7="",H7=0),"",MIN(1,J7*D7*(10/H7))) -> 0.1133125 | L7: =IF(K7="","",K7*Company_SMI!$D$26) -> 0.14999742 | M7: 80 | N7: =IF(OR(G7="",M7="",M7=0),"",G7/M7) -> 2.25 | O7: =IF(L7="","",IF(L7>=0.7,"CAPTURE NOW",IF(L7>=0.4,"PREPARE",IF(L7>=0.2,"MONITOR","WATCH")))) -> WATCH
A8: O-003 | B8: Regulatory Arbitrage Entry | C8: REG | D8: 0.7 | E8: 120 | F8: =IF(E8="","",MIN(10,MAX(1,2*LN(E8+1)))) -> 9.5915811 | G8: =IF(D8="","",D8*E8) -> 84 | H8: 9 | I8: 9 | J8: =IF(I8="","",(I8/10)*(CORE!$D$44/10)) -> 0.58275 | K8: =IF(OR(J8="",H8="",H8=0),"",MIN(1,J8*D8*(10/H8))) -> 0.45325 | L8: =IF(K8="","",K8*Company_SMI!$D$26) -> 0.59998969 | M8: 15 | N8: =IF(OR(G8="",M8="",M8=0),"",G8/M8) -> 5.6 | O8: =IF(L8="","",IF(L8>=0.7,"CAPTURE NOW",IF(L8>=0.4,"PREPARE",IF(L8>=0.2,"MONITOR","WATCH")))) -> PREPARE
A9: O-004 | F9: =IF(E9="","",MIN(10,MAX(1,2*LN(E9+1)))) | G9: =IF(D9="","",D9*E9) | J9: =IF(AND(I9<>"",CORE!$D$44<>""),I9/10*CORE!$D$44/10,"") | K9: =IF(AND(D9<>"",H9<>""),MIN(1,J9*D9*(10/H9)),"") | L9: =IF(K9="","",K9*Company_SMI!$D$26) | N9: =IF(OR(G9="",M9="",M9=0),"",G9/M9) | O9: =IF(K9="","",IF(K9>=0.7,"CAPTURE NOW",IF(K9>=0.4,"PREPARE",IF(K9>=0.2,"MONITOR","WATCH"))))
A10: O-005 | F10: =IF(E10="","",MIN(10,MAX(1,2*LN(E10+1)))) | G10: =IF(D10="","",D10*E10) | J10: =IF(AND(I10<>"",CORE!$D$44<>""),I10/10*CORE!$D$44/10,"") | K10: =IF(AND(D10<>"",H10<>""),MIN(1,J10*D10*(10/H10)),"") | L10: =IF(K10="","",K10*Company_SMI!$D$26) | N10: =IF(OR(G10="",M10="",M10=0),"",G10/M10) | O10: =IF(K10="","",IF(K10>=0.7,"CAPTURE NOW",IF(K10>=0.4,"PREPARE",IF(K10>=0.2,"MONITOR","WATCH"))))
A11: O-006 | F11: =IF(E11="","",MIN(10,MAX(1,2*LN(E11+1)))) | G11: =IF(D11="","",D11*E11) | J11: =IF(AND(I11<>"",CORE!$D$44<>""),I11/10*CORE!$D$44/10,"") | K11: =IF(AND(D11<>"",H11<>""),MIN(1,J11*D11*(10/H11)),"") | L11: =IF(K11="","",K11*Company_SMI!$D$26) | N11: =IF(OR(G11="",M11="",M11=0),"",G11/M11) | O11: =IF(K11="","",IF(K11>=0.7,"CAPTURE NOW",IF(K11>=0.4,"PREPARE",IF(K11>=0.2,"MONITOR","WATCH"))))
A12: O-007 | F12: =IF(E12="","",MIN(10,MAX(1,2*LN(E12+1)))) | G12: =IF(D12="","",D12*E12) | J12: =IF(AND(I12<>"",CORE!$D$44<>""),I12/10*CORE!$D$44/10,"") | K12: =IF(AND(D12<>"",H12<>""),MIN(1,J12*D12*(10/H12)),"") | L12: =IF(K12="","",K12*Company_SMI!$D$26) | N12: =IF(OR(G12="",M12="",M12=0),"",G12/M12) | O12: =IF(K12="","",IF(K12>=0.7,"CAPTURE NOW",IF(K12>=0.4,"PREPARE",IF(K12>=0.2,"MONITOR","WATCH"))))
A13: O-008 | F13: =IF(E13="","",MIN(10,MAX(1,2*LN(E13+1)))) | G13: =IF(D13="","",D13*E13) | J13: =IF(AND(I13<>"",CORE!$D$44<>""),I13/10*CORE!$D$44/10,"") | K13: =IF(AND(D13<>"",H13<>""),MIN(1,J13*D13*(10/H13)),"") | L13: =IF(K13="","",K13*Company_SMI!$D$26) | N13: =IF(OR(G13="",M13="",M13=0),"",G13/M13) | O13: =IF(K13="","",IF(K13>=0.7,"CAPTURE NOW",IF(K13>=0.4,"PREPARE",IF(K13>=0.2,"MONITOR","WATCH"))))
A14: O-009 | F14: =IF(E14="","",MIN(10,MAX(1,2*LN(E14+1)))) | G14: =IF(D14="","",D14*E14) | J14: =IF(AND(I14<>"",CORE!$D$44<>""),I14/10*CORE!$D$44/10,"") | K14: =IF(AND(D14<>"",H14<>""),MIN(1,J14*D14*(10/H14)),"") | L14: =IF(K14="","",K14*Company_SMI!$D$26) | N14: =IF(OR(G14="",M14="",M14=0),"",G14/M14) | O14: =IF(K14="","",IF(K14>=0.7,"CAPTURE NOW",IF(K14>=0.4,"PREPARE",IF(K14>=0.2,"MONITOR","WATCH"))))
A15: O-010 | F15: =IF(E15="","",MIN(10,MAX(1,2*LN(E15+1)))) | G15: =IF(D15="","",D15*E15) | J15: =IF(AND(I15<>"",CORE!$D$44<>""),I15/10*CORE!$D$44/10,"") | K15: =IF(AND(D15<>"",H15<>""),MIN(1,J15*D15*(10/H15)),"") | L15: =IF(K15="","",K15*Company_SMI!$D$26) | N15: =IF(OR(G15="",M15="",M15=0),"",G15/M15) | O15: =IF(K15="","",IF(K15>=0.7,"CAPTURE NOW",IF(K15>=0.4,"PREPARE",IF(K15>=0.2,"MONITOR","WATCH"))))
A16: O-011 | F16: =IF(E16="","",MIN(10,MAX(1,2*LN(E16+1)))) | G16: =IF(D16="","",D16*E16) | J16: =IF(AND(I16<>"",CORE!$D$44<>""),I16/10*CORE!$D$44/10,"") | K16: =IF(AND(D16<>"",H16<>""),MIN(1,J16*D16*(10/H16)),"") | L16: =IF(K16="","",K16*Company_SMI!$D$26) | N16: =IF(OR(G16="",M16="",M16=0),"",G16/M16) | O16: =IF(K16="","",IF(K16>=0.7,"CAPTURE NOW",IF(K16>=0.4,"PREPARE",IF(K16>=0.2,"MONITOR","WATCH"))))
A17: O-012 | F17: =IF(E17="","",MIN(10,MAX(1,2*LN(E17+1)))) | G17: =IF(D17="","",D17*E17) | J17: =IF(AND(I17<>"",CORE!$D$44<>""),I17/10*CORE!$D$44/10,"") | K17: =IF(AND(D17<>"",H17<>""),MIN(1,J17*D17*(10/H17)),"") | L17: =IF(K17="","",K17*Company_SMI!$D$26) | N17: =IF(OR(G17="",M17="",M17=0),"",G17/M17) | O17: =IF(K17="","",IF(K17>=0.7,"CAPTURE NOW",IF(K17>=0.4,"PREPARE",IF(K17>=0.2,"MONITOR","WATCH"))))
A18: O-013 | F18: =IF(E18="","",MIN(10,MAX(1,2*LN(E18+1)))) | G18: =IF(D18="","",D18*E18) | J18: =IF(AND(I18<>"",CORE!$D$44<>""),I18/10*CORE!$D$44/10,"") | K18: =IF(AND(D18<>"",H18<>""),MIN(1,J18*D18*(10/H18)),"") | L18: =IF(K18="","",K18*Company_SMI!$D$26) | N18: =IF(OR(G18="",M18="",M18=0),"",G18/M18) | O18: =IF(K18="","",IF(K18>=0.7,"CAPTURE NOW",IF(K18>=0.4,"PREPARE",IF(K18>=0.2,"MONITOR","WATCH"))))
A19: O-014 | F19: =IF(E19="","",MIN(10,MAX(1,2*LN(E19+1)))) | G19: =IF(D19="","",D19*E19) | J19: =IF(AND(I19<>"",CORE!$D$44<>""),I19/10*CORE!$D$44/10,"") | K19: =IF(AND(D19<>"",H19<>""),MIN(1,J19*D19*(10/H19)),"") | L19: =IF(K19="","",K19*Company_SMI!$D$26) | N19: =IF(OR(G19="",M19="",M19=0),"",G19/M19) | O19: =IF(K19="","",IF(K19>=0.7,"CAPTURE NOW",IF(K19>=0.4,"PREPARE",IF(K19>=0.2,"MONITOR","WATCH"))))
A20: O-015 | F20: =IF(E20="","",MIN(10,MAX(1,2*LN(E20+1)))) | G20: =IF(D20="","",D20*E20) | J20: =IF(AND(I20<>"",CORE!$D$44<>""),I20/10*CORE!$D$44/10,"") | K20: =IF(AND(D20<>"",H20<>""),MIN(1,J20*D20*(10/H20)),"") | L20: =IF(K20="","",K20*Company_SMI!$D$26) | N20: =IF(OR(G20="",M20="",M20=0),"",G20/M20) | O20: =IF(K20="","",IF(K20>=0.7,"CAPTURE NOW",IF(K20>=0.4,"PREPARE",IF(K20>=0.2,"MONITOR","WATCH"))))
A21: O-016 | F21: =IF(E21="","",MIN(10,MAX(1,2*LN(E21+1)))) | G21: =IF(D21="","",D21*E21) | J21: =IF(AND(I21<>"",CORE!$D$44<>""),I21/10*CORE!$D$44/10,"") | K21: =IF(AND(D21<>"",H21<>""),MIN(1,J21*D21*(10/H21)),"") | L21: =IF(K21="","",K21*Company_SMI!$D$26) | O21: =IF(K21="","",IF(K21>=0.7,"CAPTURE NOW",IF(K21>=0.4,"PREPARE",IF(K21>=0.2,"MONITOR","WATCH"))))
A22: O-017 | F22: =IF(E22="","",MIN(10,MAX(1,2*LN(E22+1)))) | G22: =IF(D22="","",D22*E22) | J22: =IF(AND(I22<>"",CORE!$D$44<>""),I22/10*CORE!$D$44/10,"") | K22: =IF(AND(D22<>"",H22<>""),MIN(1,J22*D22*(10/H22)),"") | L22: =IF(K22="","",K22*Company_SMI!$D$26) | O22: =IF(K22="","",IF(K22>=0.7,"CAPTURE NOW",IF(K22>=0.4,"PREPARE",IF(K22>=0.2,"MONITOR","WATCH"))))
A23: O-018 | F23: =IF(E23="","",MIN(10,MAX(1,2*LN(E23+1)))) | G23: =IF(D23="","",D23*E23) | J23: =IF(AND(I23<>"",CORE!$D$44<>""),I23/10*CORE!$D$44/10,"") | K23: =IF(AND(D23<>"",H23<>""),MIN(1,J23*D23*(10/H23)),"") | L23: =IF(K23="","",K23*Company_SMI!$D$26) | O23: =IF(K23="","",IF(K23>=0.7,"CAPTURE NOW",IF(K23>=0.4,"PREPARE",IF(K23>=0.2,"MONITOR","WATCH"))))
A24: O-019 | F24: =IF(E24="","",MIN(10,MAX(1,2*LN(E24+1)))) | G24: =IF(D24="","",D24*E24) | J24: =IF(AND(I24<>"",CORE!$D$44<>""),I24/10*CORE!$D$44/10,"") | K24: =IF(AND(D24<>"",H24<>""),MIN(1,J24*D24*(10/H24)),"") | L24: =IF(K24="","",K24*Company_SMI!$D$26) | O24: =IF(K24="","",IF(K24>=0.7,"CAPTURE NOW",IF(K24>=0.4,"PREPARE",IF(K24>=0.2,"MONITOR","WATCH"))))
A25: O-020 | F25: =IF(E25="","",MIN(10,MAX(1,2*LN(E25+1)))) | G25: =IF(D25="","",D25*E25) | J25: =IF(AND(I25<>"",CORE!$D$44<>""),I25/10*CORE!$D$44/10,"") | K25: =IF(AND(D25<>"",H25<>""),MIN(1,J25*D25*(10/H25)),"") | L25: =IF(K25="","",K25*Company_SMI!$D$26) | O25: =IF(K25="","",IF(K25>=0.7,"CAPTURE NOW",IF(K25>=0.4,"PREPARE",IF(K25>=0.2,"MONITOR","WATCH"))))
A26: O-021 | F26: =IF(E26="","",MIN(10,MAX(1,2*LN(E26+1)))) | G26: =IF(D26="","",D26*E26) | J26: =IF(AND(I26<>"",CORE!$D$44<>""),I26/10*CORE!$D$44/10,"") | K26: =IF(AND(D26<>"",H26<>""),MIN(1,J26*D26*(10/H26)),"") | L26: =IF(K26="","",K26*Company_SMI!$D$26) | O26: =IF(K26="","",IF(K26>=0.7,"CAPTURE NOW",IF(K26>=0.4,"PREPARE",IF(K26>=0.2,"MONITOR","WATCH"))))
A27: O-022 | F27: =IF(E27="","",MIN(10,MAX(1,2*LN(E27+1)))) | G27: =IF(D27="","",D27*E27) | J27: =IF(AND(I27<>"",CORE!$D$44<>""),I27/10*CORE!$D$44/10,"") | K27: =IF(AND(D27<>"",H27<>""),MIN(1,J27*D27*(10/H27)),"") | L27: =IF(K27="","",K27*Company_SMI!$D$26) | O27: =IF(K27="","",IF(K27>=0.7,"CAPTURE NOW",IF(K27>=0.4,"PREPARE",IF(K27>=0.2,"MONITOR","WATCH"))))
A28: O-023 | F28: =IF(E28="","",MIN(10,MAX(1,2*LN(E28+1)))) | G28: =IF(D28="","",D28*E28) | J28: =IF(AND(I28<>"",CORE!$D$44<>""),I28/10*CORE!$D$44/10,"") | K28: =IF(AND(D28<>"",H28<>""),MIN(1,J28*D28*(10/H28)),"") | L28: =IF(K28="","",K28*Company_SMI!$D$26) | O28: =IF(K28="","",IF(K28>=0.7,"CAPTURE NOW",IF(K28>=0.4,"PREPARE",IF(K28>=0.2,"MONITOR","WATCH"))))
A29: O-024 | F29: =IF(E29="","",MIN(10,MAX(1,2*LN(E29+1)))) | G29: =IF(D29="","",D29*E29) | J29: =IF(AND(I29<>"",CORE!$D$44<>""),I29/10*CORE!$D$44/10,"") | K29: =IF(AND(D29<>"",H29<>""),MIN(1,J29*D29*(10/H29)),"") | L29: =IF(K29="","",K29*Company_SMI!$D$26) | O29: =IF(K29="","",IF(K29>=0.7,"CAPTURE NOW",IF(K29>=0.4,"PREPARE",IF(K29>=0.2,"MONITOR","WATCH"))))
A30: O-025 | F30: =IF(E30="","",MIN(10,MAX(1,2*LN(E30+1)))) | G30: =IF(D30="","",D30*E30) | J30: =IF(AND(I30<>"",CORE!$D$44<>""),I30/10*CORE!$D$44/10,"") | K30: =IF(AND(D30<>"",H30<>""),MIN(1,J30*D30*(10/H30)),"") | L30: =IF(K30="","",K30*Company_SMI!$D$26) | O30: =IF(K30="","",IF(K30>=0.7,"CAPTURE NOW",IF(K30>=0.4,"PREPARE",IF(K30>=0.2,"MONITOR","WATCH"))))
A31: O-026 | F31: =IF(E31="","",MIN(10,MAX(1,2*LN(E31+1)))) | G31: =IF(D31="","",D31*E31) | J31: =IF(AND(I31<>"",CORE!$D$44<>""),I31/10*CORE!$D$44/10,"") | K31: =IF(AND(D31<>"",H31<>""),MIN(1,J31*D31*(10/H31)),"") | L31: =IF(K31="","",K31*Company_SMI!$D$26) | O31: =IF(K31="","",IF(K31>=0.7,"CAPTURE NOW",IF(K31>=0.4,"PREPARE",IF(K31>=0.2,"MONITOR","WATCH"))))
A32: O-027 | F32: =IF(E32="","",MIN(10,MAX(1,2*LN(E32+1)))) | G32: =IF(D32="","",D32*E32) | J32: =IF(AND(I32<>"",CORE!$D$44<>""),I32/10*CORE!$D$44/10,"") | K32: =IF(AND(D32<>"",H32<>""),MIN(1,J32*D32*(10/H32)),"") | L32: =IF(K32="","",K32*Company_SMI!$D$26) | O32: =IF(K32="","",IF(K32>=0.7,"CAPTURE NOW",IF(K32>=0.4,"PREPARE",IF(K32>=0.2,"MONITOR","WATCH"))))
... A36: O-031 | F36: =IF(E36="","",MIN(10,MAX(1,2*LN(E36+1)))) | G36: =IF(D36="","",D36*E36) | J36: =IF(AND(I36<>"",CORE!$D$44<>""),I36/10*CORE!$D$44/10,"") | K36: =IF(AND(D36<>"",H36<>""),MIN(1,J36*D36*(10/H36)),"") | L36: =IF(K36="","",K36*Company_SMI!$D$26) | O36: =IF(K36="","",IF(K36>=0.7,"CAPTURE NOW",IF(K36>=0.4,"PREPARE",IF(K36>=0.2,"MONITOR","WATCH"))))

Sheet Risk Control
C3: =IF(SelectedBU="","",INDEX(ReportingUnits,SelectedBU,1)) -> Company 3 | Z3: ="Top 10 Risks that could occur within the "&Parameters!E17&". Risk 'In Control' Sheet" -> Top 10 Risks that could occur within the next 3 - 5 years. Risk 'In Control' Sheet
C6: RiskId | D6: Risk Title (with a light description) | E6: Clear Ownership | L6: Risk Limits | S6: Risk Assessment | AA6: Strength of the Controls | AI6: Risk Assurance - Monitoring | AR6: Feedback on risk information provided by Internal Assurance?
F7: Applicable? | H7: Risk Owner | I7: Risk Actionees (responsible persons of mitigation actions) | J7: Well functioning decision Forum in place | K7: Roles and responsibilities are well defined | M7: Applicable? | O7: Informal Risk Limits applied by the business | P7: Self-limits fixed the risk owner | Q7: Limits included in Group Policy or Strategy | R7: Group Risk Limits clearly defined and applied | T7: Applicable? | V7: Vague estimates | W7: Qualitative (management judgement) | X7: Quantitative or Qualitative using Group guidelines | Y7: Uses Loss History | Z7: Quantitative, distributions and correlations | AB7: Applicable? | AD7: Unreliable | AE7: Informal | AF7: Adequate | AG7: Reliable | AH7: Effective | AJ7: Applicable? | AL7: Self Assessment | AM7: Early warning: Exceptions – Issues – Whistle Blowing | AN7: Systematic occured risks and Incident reporting | AO7: Internal Audit | AP7: External Audit or certification
C8: =RiskList!A2 -> Company 101 | D8: =RiskList!B2 | E8: =IF(F8<1,FALSE(),COUNTIF(H8:K8,1)) -> FALSE | L8: =IF(M8<1,FALSE(),MAX(O8*1,P8*2,Q8*3,R8*4)) -> FALSE | S8: =IF(T8<1,FALSE(),MAX(V8*1,W8*2,X8*3,Y8*4,Z8*5)) -> FALSE | AA8: =IF(AB8<1,FALSE(),MAX(AD8*1,AE8*2,AF8*3,AG8*4,AH8*5)) -> FALSE | AI8: =IF(AJ8<1,FALSE(),COUNTIF(AL8:AP8,1)) -> FALSE
C9: =RiskList!A3 -> Company 102 | D9: =RiskList!B3 | E9: =IF(F9<1,FALSE(),COUNTIF(H9:K9,1)) -> FALSE | L9: =IF(M9<1,FALSE(),MAX(O9*1,P9*2,Q9*3,R9*4)) -> FALSE | S9: =IF(T9<1,FALSE(),MAX(V9*1,W9*2,X9*3,Y9*4,Z9*5)) -> FALSE | AA9: =IF(AB9<1,FALSE(),MAX(AD9*1,AE9*2,AF9*3,AG9*4,AH9*5)) -> FALSE | AI9: =IF(AJ9<1,FALSE(),COUNTIF(AL9:AP9,1)) -> FALSE
C10: =RiskList!A4 -> Company 103 | D10: =RiskList!B4 | E10: =IF(F10<1,FALSE(),COUNTIF(H10:K10,1)) -> FALSE | L10: =IF(M10<1,FALSE(),MAX(O10*1,P10*2,Q10*3,R10*4)) -> FALSE | S10: =IF(T10<1,FALSE(),MAX(V10*1,W10*2,X10*3,Y10*4,Z10*5)) -> FALSE | AA10: =IF(AB10<1,FALSE(),MAX(AD10*1,AE10*2,AF10*3,AG10*4,AH10*5)) -> FALSE | AI10: =IF(AJ10<1,FALSE(),COUNTIF(AL10:AP10,1)) -> FALSE
C11: =RiskList!A5 -> Company 104 | D11: =RiskList!B5 | E11: =IF(F11<1,FALSE(),COUNTIF(H11:K11,1)) -> FALSE | L11: =IF(M11<1,FALSE(),MAX(O11*1,P11*2,Q11*3,R11*4)) -> FALSE | S11: =IF(T11<1,FALSE(),MAX(V11*1,W11*2,X11*3,Y11*4,Z11*5)) -> FALSE | AA11: =IF(AB11<1,FALSE(),MAX(AD11*1,AE11*2,AF11*3,AG11*4,AH11*5)) -> FALSE | AI11: =IF(AJ11<1,FALSE(),COUNTIF(AL11:AP11,1)) -> FALSE
C12: =RiskList!A6 -> Company 105 | D12: =RiskList!B6 | E12: =IF(F12<1,FALSE(),COUNTIF(H12:K12,1)) -> FALSE | L12: =IF(M12<1,FALSE(),MAX(O12*1,P12*2,Q12*3,R12*4)) -> FALSE | S12: =IF(T12<1,FALSE(),MAX(V12*1,W12*2,X12*3,Y12*4,Z12*5)) -> FALSE | AA12: =IF(AB12<1,FALSE(),MAX(AD12*1,AE12*2,AF12*3,AG12*4,AH12*5)) -> FALSE | AI12: =IF(AJ12<1,FALSE(),COUNTIF(AL12:AP12,1)) -> FALSE
C13: =RiskList!A7 -> Company 106 | D13: =RiskList!B7 | E13: =IF(F13<1,FALSE(),COUNTIF(H13:K13,1)) -> FALSE | L13: =IF(M13<1,FALSE(),MAX(O13*1,P13*2,Q13*3,R13*4)) -> FALSE | S13: =IF(T13<1,FALSE(),MAX(V13*1,W13*2,X13*3,Y13*4,Z13*5)) -> FALSE | AA13: =IF(AB13<1,FALSE(),MAX(AD13*1,AE13*2,AF13*3,AG13*4,AH13*5)) -> FALSE | AI13: =IF(AJ13<1,FALSE(),COUNTIF(AL13:AP13,1)) -> FALSE
C14: =RiskList!A8 -> Company 107 | D14: =RiskList!B8 | E14: =IF(F14<1,FALSE(),COUNTIF(H14:K14,1)) -> FALSE | L14: =IF(M14<1,FALSE(),MAX(O14*1,P14*2,Q14*3,R14*4)) -> FALSE | S14: =IF(T14<1,FALSE(),MAX(V14*1,W14*2,X14*3,Y14*4,Z14*5)) -> FALSE | AA14: =IF(AB14<1,FALSE(),MAX(AD14*1,AE14*2,AF14*3,AG14*4,AH14*5)) -> FALSE | AI14: =IF(AJ14<1,FALSE(),COUNTIF(AL14:AP14,1)) -> FALSE
C15: =RiskList!A9 -> Company 108 | D15: =RiskList!B9 | E15: =IF(F15<1,FALSE(),COUNTIF(H15:K15,1)) -> FALSE | L15: =IF(M15<1,FALSE(),MAX(O15*1,P15*2,Q15*3,R15*4)) -> FALSE | S15: =IF(T15<1,FALSE(),MAX(V15*1,W15*2,X15*3,Y15*4,Z15*5)) -> FALSE | AA15: =IF(AB15<1,FALSE(),MAX(AD15*1,AE15*2,AF15*3,AG15*4,AH15*5)) -> FALSE | AI15: =IF(AJ15<1,FALSE(),COUNTIF(AL15:AP15,1)) -> FALSE
A16: 0 | C16: =RiskList!A10 -> Company 109 | D16: =RiskList!B10 | E16: =IF(F16<1,FALSE(),COUNTIF(H16:K16,1)) -> FALSE | L16: =IF(M16<1,FALSE(),MAX(O16*1,P16*2,Q16*3,R16*4)) -> FALSE | S16: =IF(T16<1,FALSE(),MAX(V16*1,W16*2,X16*3,Y16*4,Z16*5)) -> FALSE | AA16: =IF(AB16<1,FALSE(),MAX(AD16*1,AE16*2,AF16*3,AG16*4,AH16*5)) -> FALSE | AI16: =IF(AJ16<1,FALSE(),COUNTIF(AL16:AP16,1)) -> FALSE
C17: =RiskList!A11 -> Company 110 | D17: =RiskList!B11 | E17: =IF(F17<1,FALSE(),COUNTIF(H17:K17,1)) -> FALSE | L17: =IF(M17<1,FALSE(),MAX(O17*1,P17*2,Q17*3,R17*4)) -> FALSE | S17: =IF(T17<1,FALSE(),MAX(V17*1,W17*2,X17*3,Y17*4,Z17*5)) -> FALSE | AA17: =IF(AB17<1,FALSE(),MAX(AD17*1,AE17*2,AF17*3,AG17*4,AH17*5)) -> FALSE | AI17: =IF(AJ17<1,FALSE(),COUNTIF(AL17:AP17,1)) -> FALSE
C18: =RiskList!A12 -> Company 111 | D18: =RiskList!B12 | E18: =IF(F18<1,FALSE(),COUNTIF(H18:K18,1)) -> FALSE | L18: =IF(M18<1,FALSE(),MAX(O18*1,P18*2,Q18*3,R18*4)) -> FALSE | S18: =IF(T18<1,FALSE(),MAX(V18*1,W18*2,X18*3,Y18*4,Z18*5)) -> FALSE | AA18: =IF(AB18<1,FALSE(),MAX(AD18*1,AE18*2,AF18*3,AG18*4,AH18*5)) -> FALSE | AI18: =IF(AJ18<1,FALSE(),COUNTIF(AL18:AP18,1)) -> FALSE
C19: =RiskList!A13 -> Company 112 | D19: =RiskList!B13 | E19: =IF(F19<1,FALSE(),COUNTIF(H19:K19,1)) -> FALSE | L19: =IF(M19<1,FALSE(),MAX(O19*1,P19*2,Q19*3,R19*4)) -> FALSE | S19: =IF(T19<1,FALSE(),MAX(V19*1,W19*2,X19*3,Y19*4,Z19*5)) -> FALSE | AA19: =IF(AB19<1,FALSE(),MAX(AD19*1,AE19*2,AF19*3,AG19*4,AH19*5)) -> FALSE | AI19: =IF(AJ19<1,FALSE(),COUNTIF(AL19:AP19,1)) -> FALSE
C20: =RiskList!A14 -> Company 113 | D20: =RiskList!B14 | E20: =IF(F20<1,FALSE(),COUNTIF(H20:K20,1)) -> FALSE | L20: =IF(M20<1,FALSE(),MAX(O20*1,P20*2,Q20*3,R20*4)) -> FALSE | S20: =IF(T20<1,FALSE(),MAX(V20*1,W20*2,X20*3,Y20*4,Z20*5)) -> FALSE | AA20: =IF(AB20<1,FALSE(),MAX(AD20*1,AE20*2,AF20*3,AG20*4,AH20*5)) -> FALSE | AI20: =IF(AJ20<1,FALSE(),COUNTIF(AL20:AP20,1)) -> FALSE
C21: =RiskList!A15 -> Company 114 | D21: =RiskList!B15 | E21: =IF(F21<1,FALSE(),COUNTIF(H21:K21,1)) -> FALSE | L21: =IF(M21<1,FALSE(),MAX(O21*1,P21*2,Q21*3,R21*4)) -> FALSE | S21: =IF(T21<1,FALSE(),MAX(V21*1,W21*2,X21*3,Y21*4,Z21*5)) -> FALSE | AA21: =IF(AB21<1,FALSE(),MAX(AD21*1,AE21*2,AF21*3,AG21*4,AH21*5)) -> FALSE | AI21: =IF(AJ21<1,FALSE(),COUNTIF(AL21:AP21,1)) -> FALSE
C22: =RiskList!A16 -> Company 115 | D22: =RiskList!B16 | E22: =IF(F22<1,FALSE(),COUNTIF(H22:K22,1)) -> FALSE | L22: =IF(M22<1,FALSE(),MAX(O22*1,P22*2,Q22*3,R22*4)) -> FALSE | S22: =IF(T22<1,FALSE(),MAX(V22*1,W22*2,X22*3,Y22*4,Z22*5)) -> FALSE | AA22: =IF(AB22<1,FALSE(),MAX(AD22*1,AE22*2,AF22*3,AG22*4,AH22*5)) -> FALSE | AI22: =IF(AJ22<1,FALSE(),COUNTIF(AL22:AP22,1)) -> FALSE
C23: =RiskList!A17 -> Company 116 | D23: =RiskList!B17 | E23: =IF(F23<1,FALSE(),COUNTIF(H23:K23,1)) -> FALSE | L23: =IF(M23<1,FALSE(),MAX(O23*1,P23*2,Q23*3,R23*4)) -> FALSE | S23: =IF(T23<1,FALSE(),MAX(V23*1,W23*2,X23*3,Y23*4,Z23*5)) -> FALSE | AA23: =IF(AB23<1,FALSE(),MAX(AD23*1,AE23*2,AF23*3,AG23*4,AH23*5)) -> FALSE | AI23: =IF(AJ23<1,FALSE(),COUNTIF(AL23:AP23,1)) -> FALSE
C24: =RiskList!A18 -> Company 117 | D24: =RiskList!B18 | E24: =IF(F24<1,FALSE(),COUNTIF(H24:K24,1)) -> FALSE | L24: =IF(M24<1,FALSE(),MAX(O24*1,P24*2,Q24*3,R24*4)) -> FALSE | S24: =IF(T24<1,FALSE(),MAX(V24*1,W24*2,X24*3,Y24*4,Z24*5)) -> FALSE | AA24: =IF(AB24<1,FALSE(),MAX(AD24*1,AE24*2,AF24*3,AG24*4,AH24*5)) -> FALSE | AI24: =IF(AJ24<1,FALSE(),COUNTIF(AL24:AP24,1)) -> FALSE
C25: =RiskList!A19 -> Company 118 | D25: =RiskList!B19 | E25: =IF(F25<1,FALSE(),COUNTIF(H25:K25,1)) -> FALSE | L25: =IF(M25<1,FALSE(),MAX(O25*1,P25*2,Q25*3,R25*4)) -> FALSE | S25: =IF(T25<1,FALSE(),MAX(V25*1,W25*2,X25*3,Y25*4,Z25*5)) -> FALSE | AA25: =IF(AB25<1,FALSE(),MAX(AD25*1,AE25*2,AF25*3,AG25*4,AH25*5)) -> FALSE | AI25: =IF(AJ25<1,FALSE(),COUNTIF(AL25:AP25,1)) -> FALSE
C26: =RiskList!A20 -> Company 119 | D26: =RiskList!B20 | E26: =IF(F26<1,FALSE(),COUNTIF(H26:K26,1)) -> FALSE | L26: =IF(M26<1,FALSE(),MAX(O26*1,P26*2,Q26*3,R26*4)) -> FALSE | S26: =IF(T26<1,FALSE(),MAX(V26*1,W26*2,X26*3,Y26*4,Z26*5)) -> FALSE | AA26: =IF(AB26<1,FALSE(),MAX(AD26*1,AE26*2,AF26*3,AG26*4,AH26*5)) -> FALSE | AI26: =IF(AJ26<1,FALSE(),COUNTIF(AL26:AP26,1)) -> FALSE
C27: =RiskList!A21 -> Company 120 | D27: =RiskList!B21 | E27: =IF(F27<1,FALSE(),COUNTIF(H27:K27,1)) -> FALSE | L27: =IF(M27<1,FALSE(),MAX(O27*1,P27*2,Q27*3,R27*4)) -> FALSE | S27: =IF(T27<1,FALSE(),MAX(V27*1,W27*2,X27*3,Y27*4,Z27*5)) -> FALSE | AA27: =IF(AB27<1,FALSE(),MAX(AD27*1,AE27*2,AF27*3,AG27*4,AH27*5)) -> FALSE | AI27: =IF(AJ27<1,FALSE(),COUNTIF(AL27:AP27,1)) -> FALSE
C28: =RiskList!A22 -> Company 121 | D28: =RiskList!B22 | E28: =IF(F28<1,FALSE(),COUNTIF(H28:K28,1)) -> FALSE | L28: =IF(M28<1,FALSE(),MAX(O28*1,P28*2,Q28*3,R28*4)) -> FALSE | S28: =IF(T28<1,FALSE(),MAX(V28*1,W28*2,X28*3,Y28*4,Z28*5)) -> FALSE | AA28: =IF(AB28<1,FALSE(),MAX(AD28*1,AE28*2,AF28*3,AG28*4,AH28*5)) -> FALSE | AI28: =IF(AJ28<1,FALSE(),COUNTIF(AL28:AP28,1)) -> FALSE
... C57: =RiskList!A51 -> 0 | D57: =RiskList!B51 -> 0 | E57: =IF(F57<1,FALSE(),COUNTIF(H57:K57,1)) -> FALSE | L57: =IF(M57<1,FALSE(),MAX(O57*1,P57*2,Q57*3,R57*4)) -> FALSE | S57: =IF(T57<1,FALSE(),MAX(V57*1,W57*2,X57*3,Y57*4,Z57*5)) -> FALSE | AA57: =IF(AB57<1,FALSE(),MAX(AD57*1,AE57*2,AF57*3,AG57*4,AH57*5)) -> FALSE | AI57: =IF(AJ57<1,FALSE(),COUNTIF(AL57:AP57,1)) -> FALSE
C58: =RiskList!A52 -> 0 | D58: =COUNTIF(D8:D57,"<>0") -> 34

Sheet Risk Interaction Map
C3: =IF(MAX(BC:BC)>MAX(E58:BB58),INDEX(C:C,MATCH(MAX(BC:BC),BC:BC,0)),INDEX(E7:BB7,1,MATCH(MAX(E58:BB58),E58:BB58,0))) -> Company 101 | E3: Risk Interaction Map
C6: Risk in rows directly influences Risk in columns | E6: =INDIRECT("d"&COLUMN()+3) | F6: =INDIRECT("d"&COLUMN()+3) | G6: =INDIRECT("d"&COLUMN()+3) | H6: =INDIRECT("d"&COLUMN()+3) | I6: =INDIRECT("d"&COLUMN()+3) | J6: =INDIRECT("d"&COLUMN()+3) | K6: =INDIRECT("d"&COLUMN()+3) | L6: =INDIRECT("d"&COLUMN()+3) | ... BB6: =INDIRECT("d"&COLUMN()+3)
E7: =INDIRECT("C"&COLUMN()+3) -> Company 101 | F7: =INDIRECT("C"&COLUMN()+3) -> Company 102 | G7: =INDIRECT("C"&COLUMN()+3) -> Company 103 | H7: =INDIRECT("C"&COLUMN()+3) -> Company 104 | I7: =INDIRECT("C"&COLUMN()+3) -> Company 105 | J7: =INDIRECT("C"&COLUMN()+3) -> Company 106 | K7: =INDIRECT("C"&COLUMN()+3) -> Company 107 | L7: =INDIRECT("C"&COLUMN()+3) -> Company 108 | ... BB7: =INDIRECT("C"&COLUMN()+3) -> 0
C8: =RiskList!A2 -> Company 101 | D8: =IF(RiskList!B2=0,"",RiskList!B2) | BC8: =COUNTA(E8:BB8) -> 0
C9: =RiskList!A3 -> Company 102 | D9: =IF(RiskList!B3=0,"",RiskList!B3) | BC9: =COUNTA(E9:BB9) -> 0
C10: =RiskList!A4 -> Company 103 | D10: =IF(RiskList!B4=0,"",RiskList!B4) | BC10: =COUNTA(E10:BB10) -> 0
C11: =RiskList!A5 -> Company 104 | D11: =IF(RiskList!B5=0,"",RiskList!B5) | BC11: =COUNTA(E11:BB11) -> 0
C12: =RiskList!A6 -> Company 105 | D12: =IF(RiskList!B6=0,"",RiskList!B6) | BC12: =COUNTA(E12:BB12) -> 0
C13: =RiskList!A7 -> Company 106 | D13: =IF(RiskList!B7=0,"",RiskList!B7) | BC13: =COUNTA(E13:BB13) -> 0
C14: =RiskList!A8 -> Company 107 | D14: =IF(RiskList!B8=0,"",RiskList!B8) | BC14: =COUNTA(E14:BB14) -> 0
C15: =RiskList!A9 -> Company 108 | D15: =IF(RiskList!B9=0,"",RiskList!B9) | BC15: =COUNTA(E15:BB15) -> 0
C16: =RiskList!A10 -> Company 109 | D16: =IF(RiskList!B10=0,"",RiskList!B10) | BC16: =COUNTA(E16:BB16) -> 0
C17: =RiskList!A11 -> Company 110 | D17: =IF(RiskList!B11=0,"",RiskList!B11) | BC17: =COUNTA(E17:BB17) -> 0
C18: =RiskList!A12 -> Company 111 | D18: =IF(RiskList!B12=0,"",RiskList!B12) | BC18: =COUNTA(E18:BB18) -> 0
C19: =RiskList!A13 -> Company 112 | D19: =IF(RiskList!B13=0,"",RiskList!B13) | BC19: =COUNTA(E19:BB19) -> 0
... C57: =RiskList!A51 -> 0 | D57: =IF(RiskList!B51=0,"",RiskList!B51) | BC57: =COUNTA(E57:BB57) -> 0
C58: =COUNTA(C8:C57) -> 50 | D58: =COUNTA(D8:D57)-COUNTIF(D8:D57,"") -> 0 | E58: =COUNTA(E8:E57) -> 0 | F58: =COUNTA(F8:F57) -> 0 | G58: =COUNTA(G8:G57) -> 0 | H58: =COUNTA(H8:H57) -> 0 | I58: =COUNTA(I8:I57) -> 0 | J58: =COUNTA(J8:J57) -> 0 | K58: =COUNTA(K8:K57) -> 0 | L58: =COUNTA(L8:L57) -> 0 | ... BB58: =COUNTA(BB8:BB57) -> 0

Sheet Coherence_Density
A1: Coherence Density Matrix — Von Neumann Entropy
A2: 5×5 density matrix | S = −Tr(ρ ln ρ) | Coherence Factor C = avg off-diagonal
A4: SECTION A: RISK CORRELATION MATRIX ρ (0-1 scale)
B5: R-001: Supply Chain | C5: R-002: Regulatory | D5: R-003: Cyber | E5: R-004 (user) | F5: R-005 (user)
A6: R-001: Supply Chain | B6: 1 | C6: 0.35 | D6: 0.25 | E6: 0.15 | F6: 0.1
A7: R-002: Regulatory | B7: 0.35 | C7: 1 | D7: 0.2 | E7: 0.3 | F7: 0.25
A8: R-003: Cyber | B8: 0.25 | C8: 0.2 | D8: 1 | E8: 0.4 | F8: 0.35
A9: R-004 (user) | B9: 0.15 | C9: 0.3 | D9: 0.4 | E9: 1 | F9: 0.2
A10: R-005 (user) | B10: 0.1 | C10: 0.25 | D10: 0.35 | E10: 0.2 | F10: 1
A13: SECTION B: DERIVED METRICS
A14: Metric | B14: Symbol | C14: Formula | D14: Value | E14: Interpretation
A15: Frobenius Norm² | B15: ‖ρ‖²_F | C15: Σ(ρᵢⱼ²) | D15: =B6^2+C6^2+D6^2+E6^2+F6^2+B7^2+C7^2+D7^2+E7^2+F7^2+B8^2+C8^2+D8^2+E8^2+F8^2+B9^2+C9^2+D9^2+E9^2+F9^2+B10^2+C10^2+D10^2+E10^2+F10^2 -> 6.465
A16: Von Neumann Entropy | B16: S | C16: ln(5)×[1-(‖ρ/n‖²-1/n)/(1/n-1/n²)] | D16: =LN(5)*(1-(D15/25-1/5)/(1/5-1/25)) -> 1.0199813
A17: Max Entropy | B17: S_max | C17: LN(5) | D17: =LN(5) -> 1.6094379
A18: Entropy Ratio | B18: S/S_max | D18: =D16/D17 -> 0.63375
A19: Off-Diagonal Sum | D19: =C6+D6+E6+F6+B7+D7+E7+F7+B8+C8+E8+F8+B9+C9+D9+F9+B10+C10+D10+E10 -> 5.1
A20: Coherence Factor | B20: C | C20: σρᵢⱼ(i≠j) / n(n-1)) | D20: =D19/20 -> 0.255
A21: Cascade Risk Flag | D21: =IF(D20>0.35,"HIGH CASCADE RISK",IF(D20>0.2,"MODERATE","LOW")) -> MODERATE
A22: Palmer Noise Adj | B22: η_adj | C22: η_base × (1+0.5×C) | D22: =Calibration!C20*(1+0.5*D20) -> 0.1048575

Sheet Risks & Objectives
C3: =Header!$A$1 -> 0 | E3: Mapping Risks by Objective
C6: Linkages between risks (in rows) and objectives (in columns) | E6: =IF((COLUMN()-4<=NbObjectives),INDIRECT(ADDRESS(COLUMN()+9,3,1,1,"Objectives")),"") -> 0 | F6: =IF((COLUMN()-4<=NbObjectives),INDIRECT(ADDRESS(COLUMN()+9,3,1,1,"Objectives")),"") -> 0 | G6: =IF((COLUMN()-4<=NbObjectives),INDIRECT(ADDRESS(COLUMN()+9,3,1,1,"Objectives")),"") -> 0 | H6: =IF((COLUMN()-4<=NbObjectives),INDIRECT(ADDRESS(COLUMN()+9,3,1,1,"Objectives")),"") | I6: =IF((COLUMN()-4<=NbObjectives),INDIRECT(ADDRESS(COLUMN()+9,3,1,1,"Objectives")),"") | J6: =IF((COLUMN()-4<=NbObjectives),INDIRECT(ADDRESS(COLUMN()+9,3,1,1,"Objectives")),"") | K6: =IF((COLUMN()-4<=NbObjectives),INDIRECT(ADDRESS(COLUMN()+9,3,1,1,"Objectives")),"") | L6: =IF((COLUMN()-4<=NbObjectives),INDIRECT(ADDRESS(COLUMN()+9,3,1,1,"Objectives")),"") | ... BB6: =IF((COLUMN()-4<=NbObjectives),INDIRECT(ADDRESS(COLUMN()+9,3,1,1,"Objectives")),"")
C7: =RiskList!A2 -> Company 101 | D7: =IF(RiskList!B2=0,"",RiskList!B2) | BC7: =COUNTA(E7:BB7) -> 0
C8: =RiskList!A3 -> Company 102 | D8: =IF(RiskList!B3=0,"",RiskList!B3) | BC8: =COUNTA(E8:BB8) -> 0
C9: =RiskList!A4 -> Company 103 | D9: =IF(RiskList!B4=0,"",RiskList!B4) | BC9: =COUNTA(E9:BB9) -> 0
C10: =RiskList!A5 -> Company 104 | D10: =IF(RiskList!B5=0,"",RiskList!B5) | BC10: =COUNTA(E10:BB10) -> 0
C11: =RiskList!A6 -> Company 105 | D11: =IF(RiskList!B6=0,"",RiskList!B6) | BC11: =COUNTA(E11:BB11) -> 0
C12: =RiskList!A7 -> Company 106 | D12: =IF(RiskList!B7=0,"",RiskList!B7) | BC12: =COUNTA(E12:BB12) -> 0
C13: =RiskList!A8 -> Company 107 | D13: =IF(RiskList!B8=0,"",RiskList!B8) | BC13: =COUNTA(E13:BB13) -> 0
C14: =RiskList!A9 -> Company 108 | D14: =IF(RiskList!B9=0,"",RiskList!B9) | BC14: =COUNTA(E14:BB14) -> 0
C15: =RiskList!A10 -> Company 109 | D15: =IF(RiskList!B10=0,"",RiskList!B10) | BC15: =COUNTA(E15:BB15) -> 0
C16: =RiskList!A11 -> Company 110 | D16: =IF(RiskList!B11=0,"",RiskList!B11) | BC16: =COUNTA(E16:BB16) -> 0
C17: =RiskList!A12 -> Company 111 | D17: =IF(RiskList!B12=0,"",RiskList!B12) | BC17: =COUNTA(E17:BB17) -> 0
C18: =RiskList!A13 -> Company 112 | D18: =IF(RiskList!B13=0,"",RiskList!B13) | BC18: =COUNTA(E18:BB18) -> 0
... C56: =RiskList!A51 -> 0 | D56: =IF(RiskList!B51=0,"",RiskList!B51) | BC56: =COUNTA(E56:BB56) -> 0
C57: =COUNTA(C7:C56) -> 50 | D57: =COUNTA(D7:D56)-COUNTIF(D7:D56,"") -> 0 | E57: =COUNTA(E7:E56) -> 0 | F57: =COUNTA(F7:F56) -> 0 | G57: =COUNTA(G7:G56) -> 0 | H57: =COUNTA(H7:H56) -> 0 | I57: =COUNTA(I7:I56) -> 0 | J57: =COUNTA(J7:J56) -> 0 | K57: =COUNTA(K7:K56) -> 0 | L57: =COUNTA(L7:L56) -> 0 | ... BB57: =COUNTA(BB7:BB56) -> 0
D61: Strategic Priorities | E61: =IF(COUNTA(E$7:E$56)>0,INDEX(Objectives!$D:$D,MATCH(E$6,Objectives!$C:$C,0))) -> FALSE | F61: =IF(COUNTA(F$7:F$56)>0,INDEX(Objectives!$D:$D,MATCH(F$6,Objectives!$C:$C,0))) -> FALSE | G61: =IF(COUNTA(G$7:G$56)>0,INDEX(Objectives!$D:$D,MATCH(G$6,Objectives!$C:$C,0))) -> FALSE | H61: =IF(COUNTA(H$7:H$56)>0,INDEX(Objectives!$D:$D,MATCH(H$6,Objectives!$C:$C,0))) -> FALSE | I61: =IF(COUNTA(I$7:I$56)>0,INDEX(Objectives!$D:$D,MATCH(I$6,Objectives!$C:$C,0))) -> FALSE | J61: =IF(COUNTA(J$7:J$56)>0,INDEX(Objectives!$D:$D,MATCH(J$6,Objectives!$C:$C,0))) -> FALSE | K61: =IF(COUNTA(K$7:K$56)>0,INDEX(Objectives!$D:$D,MATCH(K$6,Objectives!$C:$C,0))) -> FALSE | L61: =IF(COUNTA(L$7:L$56)>0,INDEX(Objectives!$D:$D,MATCH(L$6,Objectives!$C:$C,0))) -> FALSE | ... BB61: =IF(COUNTA(BB$7:BB$56)>0,INDEX(Objectives!$D:$D,MATCH(BB$6,Objectives!$C:$C,0))) -> FALSE | BC61: =SUM(E61:BB61) -> 0
D62: Operational Performance | E62: =IF(COUNTA(E$7:E$56)>0,INDEX(Objectives!$E:$E,MATCH(E$6,Objectives!$C:$C,0))) -> FALSE | F62: =IF(COUNTA(F$7:F$56)>0,INDEX(Objectives!$E:$E,MATCH(F$6,Objectives!$C:$C,0))) -> FALSE | G62: =IF(COUNTA(G$7:G$56)>0,INDEX(Objectives!$E:$E,MATCH(G$6,Objectives!$C:$C,0))) -> FALSE | H62: =IF(COUNTA(H$7:H$56)>0,INDEX(Objectives!$E:$E,MATCH(H$6,Objectives!$C:$C,0))) -> FALSE | I62: =IF(COUNTA(I$7:I$56)>0,INDEX(Objectives!$E:$E,MATCH(I$6,Objectives!$C:$C,0))) -> FALSE | J62: =IF(COUNTA(J$7:J$56)>0,INDEX(Objectives!$E:$E,MATCH(J$6,Objectives!$C:$C,0))) -> FALSE | K62: =IF(COUNTA(K$7:K$56)>0,INDEX(Objectives!$E:$E,MATCH(K$6,Objectives!$C:$C,0))) -> FALSE | L62: =IF(COUNTA(L$7:L$56)>0,INDEX(Objectives!$E:$E,MATCH(L$6,Objectives!$C:$C,0))) -> FALSE | ... BB62: =IF(COUNTA(BB$7:BB$56)>0,INDEX(Objectives!$E:$E,MATCH(BB$6,Objectives!$C:$C,0))) -> FALSE | BC62: =SUM(E62:BB62) -> 0
D63: Compliance | E63: =IF(COUNTA(E$7:E$56)>0,INDEX(Objectives!$F:$F,MATCH(E$6,Objectives!$C:$C,0))) -> FALSE | F63: =IF(COUNTA(F$7:F$56)>0,INDEX(Objectives!$F:$F,MATCH(F$6,Objectives!$C:$C,0))) -> FALSE | G63: =IF(COUNTA(G$7:G$56)>0,INDEX(Objectives!$F:$F,MATCH(G$6,Objectives!$C:$C,0))) -> FALSE | H63: =IF(COUNTA(H$7:H$56)>0,INDEX(Objectives!$F:$F,MATCH(H$6,Objectives!$C:$C,0))) -> FALSE | I63: =IF(COUNTA(I$7:I$56)>0,INDEX(Objectives!$F:$F,MATCH(I$6,Objectives!$C:$C,0))) -> FALSE | J63: =IF(COUNTA(J$7:J$56)>0,INDEX(Objectives!$F:$F,MATCH(J$6,Objectives!$C:$C,0))) -> FALSE | K63: =IF(COUNTA(K$7:K$56)>0,INDEX(Objectives!$F:$F,MATCH(K$6,Objectives!$C:$C,0))) -> FALSE | L63: =IF(COUNTA(L$7:L$56)>0,INDEX(Objectives!$F:$F,MATCH(L$6,Objectives!$C:$C,0))) -> FALSE | ... BB63: =IF(COUNTA(BB$7:BB$56)>0,INDEX(Objectives!$F:$F,MATCH(BB$6,Objectives!$C:$C,0))) -> FALSE | BC63: =SUM(E63:BB63) -> 0

Sheet Long Term Risks
C3: =IF(SelectedBU="","",INDEX(ReportingUnits,SelectedBU,1)) -> Company 3 | E3: Priority Risks that could occur in a long term view, within a time horizon of 10 years or even more, but on which it is necessary to work on starting from now
C6: Prio-rity | D6: Risk Title (with a light description) | E6: Causes and Factors (risk main causes and/or factors)
C8: 1
C9: 2
C10: 3
C11: 4
C12: 5
D13: =COUNTA(D8:D12) -> 0 | E13: =COUNTA(E8:E12) -> 0

Sheet Risk Aggregation
B2: Risk | C2: Risk Category | D2: Risk Domain | E2: Short Description | F2: Pr | G2: ImQuanti | H2: ImQuali | J2: Risk | K2: PrMín | L2: PrMostlikelly | M2: PrMáx | N2: PrAggregation | O2: ImMín | P2: ImMostlikelly | Q2: ImMáx | R2: ImAggregation | S2: P x I | U2: PrScale | V2: ImScale | W2: RMin | X2: RMax | Y2: Range | AA2: Cash Flow @ Risk | AB2: Pr | AC2: =E55 -> 0 | AD2: Lower Limit (10%) | AE2: Upper Limit (90%) | AG2: Risk Category | AH2: Risk Domain
B3: 1 | E3: =RiskList!A2&": "&RiskList!B2 -> Company 101: | F3: =IF($L3=0%,"",IF(AND($L3>MatrixImpact!$C$8,$L3<=MatrixImpact!$D$8),5,IF(AND($L3>MatrixImpact!$C$7,$L3<=MatrixImpact!$D$7),4,IF(AND($L3>MatrixImpact!$C$6,$L3<=MatrixImpact!$D$6),3,IF(AND($L3>MatrixImpact!$C$5,$L3<=MatrixImpact!$D$5),2,IF(AND($L3>MatrixImpact!$C$4,$L3<=MatrixImpact!$D$4),1,"")))))) | G3: =IF($P3>MatrixImpact!$C$14,5,IF(AND($P3>MatrixImpact!$C$13,$P3<=MatrixImpact!$D$13),4,IF(AND($P3>MatrixImpact!$C$12,$P3<=MatrixImpact!$D$12),3,IF(AND($P3>MatrixImpact!$C$11,$P3<=MatrixImpact!$D$11),2,IF(AND($P3>MatrixImpact!$C$10,$P3<=MatrixImpact!$D$10),1,""))))) | H3: =INDIRECT(ADDRESS(ROW()+6,9,1,1,"Top 10 Risks")) -> 0 | J3: =B3 -> 1 | K3: =IF(F3=MatrixImpact!$B$4,MatrixImpact!$C$4,IF(F3=MatrixImpact!$B$5,MatrixImpact!$C$5,IF(F3=MatrixImpact!$B$6,MatrixImpact!$C$6,IF(F3=MatrixImpact!$B$7,MatrixImpact!$C$7,IF(F3=MatrixImpact!$B$8,MatrixImpact!$C$8,""))))) | L3: =INDIRECT(ADDRESS(ROW()+6,10,1,1,"Top 10 Risks")) -> 0 | M3: =IF(F3=MatrixImpact!$B$4,MatrixImpact!$D$4,IF(F3=MatrixImpact!$B$5,MatrixImpact!$D$5,IF(F3=MatrixImpact!$B$6,MatrixImpact!$D$6,IF(F3=MatrixImpact!$B$7,MatrixImpact!$D$7,IF(F3=MatrixImpact!$B$8,MatrixImpact!$D$8,""))))) | O3: =IF(G3=MatrixImpact!$B$10,MatrixImpact!$C$10,IF(G3=MatrixImpact!$B$11,MatrixImpact!$C$11,IF(G3=MatrixImpact!$B$12,MatrixImpact!$C$12,IF(G3=MatrixImpact!$B$13,MatrixImpact!$C$13,IF(G3=MatrixImpact!$B$14,MatrixImpact!$C$14,""))))) | P3: =INDIRECT(ADDRESS(ROW()+6,8,1,1,"Top 10 Risks")) -> 0 | Q3: =IF(IF(G3=MatrixImpact!$B$10,MatrixImpact!$D$10,IF(G3=MatrixImpact!$B$11,MatrixImpact!$D$11,IF(G3=MatrixImpact!$B$12,MatrixImpact!$D$12,IF(G3=MatrixImpact!$B$13,MatrixImpact!$D$13,IF(G3=MatrixImpact!$B$14,MatrixImpact!$D$14,"")))))<P3,P3,IF(G3=MatrixImpact!$B$10,MatrixImpact!$D$10,IF(G3=MatrixImpact!$B$11,MatrixImpact!$D$11,IF(G3=MatrixImpact!$B$12,MatrixImpact!$D$12,IF(G3=MatrixImpact!$B$13,MatrixImpact!$D$13,IF(G3=MatrixImpact!$B$14,MatrixImpact!$D$14,"")))))) | S3: =N3*R3 -> 0 | U3: 1 | V3: 1 | W3: =INDEX(MatrixImpact!C$4:C$8,MATCH($U3,MatrixImpact!$B$4:$B$8,0),1)*INDEX(MatrixImpact!C$10:C$14,MATCH($V3,MatrixImpact!$B$10:$B$14,0),1) -> 0 | X3: =INDEX(MatrixImpact!D$4:D$8,MATCH($U3,MatrixImpact!$B$4:$B$8,0),1)*INDEX(MatrixImpact!D$10:D$14,MATCH($V3,MatrixImpact!$B$10:$B$14,0),1) -> 0.2 | Y3: =IF(AND($AE$4>=W3,$AD$4<=X3),TRUE(),FALSE()) -> TRUE | AB3: 1 | AC3: =F55 -> 0
B4: 2 | E4: =RiskList!A3&": "&RiskList!B3 -> Company 102: | F4: =IF($L4=0%,"",IF(AND($L4>MatrixImpact!$C$8,$L4<=MatrixImpact!$D$8),5,IF(AND($L4>MatrixImpact!$C$7,$L4<=MatrixImpact!$D$7),4,IF(AND($L4>MatrixImpact!$C$6,$L4<=MatrixImpact!$D$6),3,IF(AND($L4>MatrixImpact!$C$5,$L4<=MatrixImpact!$D$5),2,IF(AND($L4>MatrixImpact!$C$4,$L4<=MatrixImpact!$D$4),1,"")))))) | G4: =IF($P4>MatrixImpact!$C$14,5,IF(AND($P4>MatrixImpact!$C$13,$P4<=MatrixImpact!$D$13),4,IF(AND($P4>MatrixImpact!$C$12,$P4<=MatrixImpact!$D$12),3,IF(AND($P4>MatrixImpact!$C$11,$P4<=MatrixImpact!$D$11),2,IF(AND($P4>MatrixImpact!$C$10,$P4<=MatrixImpact!$D$10),1,""))))) | H4: =INDIRECT(ADDRESS(ROW()+6,9,1,1,"Top 10 Risks")) -> 0 | J4: =B4 -> 2 | K4: =IF(F4=MatrixImpact!$B$4,MatrixImpact!$C$4,IF(F4=MatrixImpact!$B$5,MatrixImpact!$C$5,IF(F4=MatrixImpact!$B$6,MatrixImpact!$C$6,IF(F4=MatrixImpact!$B$7,MatrixImpact!$C$7,IF(F4=MatrixImpact!$B$8,MatrixImpact!$C$8,""))))) | L4: =INDIRECT(ADDRESS(ROW()+6,10,1,1,"Top 10 Risks")) -> 0 | M4: =IF(F4=MatrixImpact!$B$4,MatrixImpact!$D$4,IF(F4=MatrixImpact!$B$5,MatrixImpact!$D$5,IF(F4=MatrixImpact!$B$6,MatrixImpact!$D$6,IF(F4=MatrixImpact!$B$7,MatrixImpact!$D$7,IF(F4=MatrixImpact!$B$8,MatrixImpact!$D$8,""))))) | O4: =IF(G4=MatrixImpact!$B$10,MatrixImpact!$C$10,IF(G4=MatrixImpact!$B$11,MatrixImpact!$C$11,IF(G4=MatrixImpact!$B$12,MatrixImpact!$C$12,IF(G4=MatrixImpact!$B$13,MatrixImpact!$C$13,IF(G4=MatrixImpact!$B$14,MatrixImpact!$C$14,""))))) | P4: =INDIRECT(ADDRESS(ROW()+6,8,1,1,"Top 10 Risks")) -> 0 | Q4: =IF(IF(G4=MatrixImpact!$B$10,MatrixImpact!$D$10,IF(G4=MatrixImpact!$B$11,MatrixImpact!$D$11,IF(G4=MatrixImpact!$B$12,MatrixImpact!$D$12,IF(G4=MatrixImpact!$B$13,MatrixImpact!$D$13,IF(G4=MatrixImpact!$B$14,MatrixImpact!$D$14,"")))))<P4,P4,IF(G4=MatrixImpact!$B$10,MatrixImpact!$D$10,IF(G4=MatrixImpact!$B$11,MatrixImpact!$D$11,IF(G4=MatrixImpact!$B$12,MatrixImpact!$D$12,IF(G4=MatrixImpact!$B$13,MatrixImpact!$D$13,IF(G4=MatrixImpact!$B$14,MatrixImpact!$D$14,"")))))) | S4: =N4*R4 -> 0 | U4: 2 | V4: 1 | W4: =INDEX(MatrixImpact!C$4:C$8,MATCH($U4,MatrixImpact!$B$4:$B$8,0),1)*INDEX(MatrixImpact!C$10:C$14,MATCH($V4,MatrixImpact!$B$10:$B$14,0),1) -> 0 | X4: =INDEX(MatrixImpact!D$4:D$8,MATCH($U4,MatrixImpact!$B$4:$B$8,0),1)*INDEX(MatrixImpact!D$10:D$14,MATCH($V4,MatrixImpact!$B$10:$B$14,0),1) -> 0.6 | Y4: =IF(AND($AE$4>=W4,$AD$4<=X4),TRUE(),FALSE()) -> TRUE | AB4: =AB3-5% -> 0.95 | AC4: =AC3 -> 0 | AG4: Strategic Risk | AH4: Industry Risk
B5: 3 | E5: =RiskList!A4&": "&RiskList!B4 -> Company 103: | F5: =IF($L5=0%,"",IF(AND($L5>MatrixImpact!$C$8,$L5<=MatrixImpact!$D$8),5,IF(AND($L5>MatrixImpact!$C$7,$L5<=MatrixImpact!$D$7),4,IF(AND($L5>MatrixImpact!$C$6,$L5<=MatrixImpact!$D$6),3,IF(AND($L5>MatrixImpact!$C$5,$L5<=MatrixImpact!$D$5),2,IF(AND($L5>MatrixImpact!$C$4,$L5<=MatrixImpact!$D$4),1,"")))))) | G5: =IF($P5>MatrixImpact!$C$14,5,IF(AND($P5>MatrixImpact!$C$13,$P5<=MatrixImpact!$D$13),4,IF(AND($P5>MatrixImpact!$C$12,$P5<=MatrixImpact!$D$12),3,IF(AND($P5>MatrixImpact!$C$11,$P5<=MatrixImpact!$D$11),2,IF(AND($P5>MatrixImpact!$C$10,$P5<=MatrixImpact!$D$10),1,""))))) | H5: =INDIRECT(ADDRESS(ROW()+6,9,1,1,"Top 10 Risks")) -> 0 | J5: =B5 -> 3 | K5: =IF(F5=MatrixImpact!$B$4,MatrixImpact!$C$4,IF(F5=MatrixImpact!$B$5,MatrixImpact!$C$5,IF(F5=MatrixImpact!$B$6,MatrixImpact!$C$6,IF(F5=MatrixImpact!$B$7,MatrixImpact!$C$7,IF(F5=MatrixImpact!$B$8,MatrixImpact!$C$8,""))))) | L5: =INDIRECT(ADDRESS(ROW()+6,10,1,1,"Top 10 Risks")) -> 0 | M5: =IF(F5=MatrixImpact!$B$4,MatrixImpact!$D$4,IF(F5=MatrixImpact!$B$5,MatrixImpact!$D$5,IF(F5=MatrixImpact!$B$6,MatrixImpact!$D$6,IF(F5=MatrixImpact!$B$7,MatrixImpact!$D$7,IF(F5=MatrixImpact!$B$8,MatrixImpact!$D$8,""))))) | O5: =IF(G5=MatrixImpact!$B$10,MatrixImpact!$C$10,IF(G5=MatrixImpact!$B$11,MatrixImpact!$C$11,IF(G5=MatrixImpact!$B$12,MatrixImpact!$C$12,IF(G5=MatrixImpact!$B$13,MatrixImpact!$C$13,IF(G5=MatrixImpact!$B$14,MatrixImpact!$C$14,""))))) | P5: =INDIRECT(ADDRESS(ROW()+6,8,1,1,"Top 10 Risks")) -> 0 | Q5: =IF(IF(G5=MatrixImpact!$B$10,MatrixImpact!$D$10,IF(G5=MatrixImpact!$B$11,MatrixImpact!$D$11,IF(G5=MatrixImpact!$B$12,MatrixImpact!$D$12,IF(G5=MatrixImpact!$B$13,MatrixImpact!$D$13,IF(G5=MatrixImpact!$B$14,MatrixImpact!$D$14,"")))))<P5,P5,IF(G5=MatrixImpact!$B$10,MatrixImpact!$D$10,IF(G5=MatrixImpact!$B$11,MatrixImpact!$D$11,IF(G5=MatrixImpact!$B$12,MatrixImpact!$D$12,IF(G5=MatrixImpact!$B$13,MatrixImpact!$D$13,IF(G5=MatrixImpact!$B$14,MatrixImpact!$D$14,"")))))) | S5: =N5*R5 -> 0 | U5: 3 | V5: 1 | W5: =INDEX(MatrixImpact!C$4:C$8,MATCH($U5,MatrixImpact!$B$4:$B$8,0),1)*INDEX(MatrixImpact!C$10:C$14,MATCH($V5,MatrixImpact!$B$10:$B$14,0),1) -> 0 | X5: =INDEX(MatrixImpact!D$4:D$8,MATCH($U5,MatrixImpact!$B$4:$B$8,0),1)*INDEX(MatrixImpact!D$10:D$14,MATCH($V5,MatrixImpact!$B$10:$B$14,0),1) -> 1 | Y5: =IF(AND($AE$4>=W5,$AD$4<=X5),TRUE(),FALSE()) -> TRUE | AB5: =AB4-5% -> 0.9 | AC5: =AC4 -> 0 | AG5: Management Risk | AH5: Market Risk: Competitors
B6: 4 | E6: =RiskList!A5&": "&RiskList!B5 -> Company 104: | F6: =IF($L6=0%,"",IF(AND($L6>MatrixImpact!$C$8,$L6<=MatrixImpact!$D$8),5,IF(AND($L6>MatrixImpact!$C$7,$L6<=MatrixImpact!$D$7),4,IF(AND($L6>MatrixImpact!$C$6,$L6<=MatrixImpact!$D$6),3,IF(AND($L6>MatrixImpact!$C$5,$L6<=MatrixImpact!$D$5),2,IF(AND($L6>MatrixImpact!$C$4,$L6<=MatrixImpact!$D$4),1,"")))))) | G6: =IF($P6>MatrixImpact!$C$14,5,IF(AND($P6>MatrixImpact!$C$13,$P6<=MatrixImpact!$D$13),4,IF(AND($P6>MatrixImpact!$C$12,$P6<=MatrixImpact!$D$12),3,IF(AND($P6>MatrixImpact!$C$11,$P6<=MatrixImpact!$D$11),2,IF(AND($P6>MatrixImpact!$C$10,$P6<=MatrixImpact!$D$10),1,""))))) | H6: =INDIRECT(ADDRESS(ROW()+6,9,1,1,"Top 10 Risks")) -> 0 | J6: =B6 -> 4 | K6: =IF(F6=MatrixImpact!$B$4,MatrixImpact!$C$4,IF(F6=MatrixImpact!$B$5,MatrixImpact!$C$5,IF(F6=MatrixImpact!$B$6,MatrixImpact!$C$6,IF(F6=MatrixImpact!$B$7,MatrixImpact!$C$7,IF(F6=MatrixImpact!$B$8,MatrixImpact!$C$8,""))))) | L6: =INDIRECT(ADDRESS(ROW()+6,10,1,1,"Top 10 Risks")) -> 0 | M6: =IF(F6=MatrixImpact!$B$4,MatrixImpact!$D$4,IF(F6=MatrixImpact!$B$5,MatrixImpact!$D$5,IF(F6=MatrixImpact!$B$6,MatrixImpact!$D$6,IF(F6=MatrixImpact!$B$7,MatrixImpact!$D$7,IF(F6=MatrixImpact!$B$8,MatrixImpact!$D$8,""))))) | O6: =IF(G6=MatrixImpact!$B$10,MatrixImpact!$C$10,IF(G6=MatrixImpact!$B$11,MatrixImpact!$C$11,IF(G6=MatrixImpact!$B$12,MatrixImpact!$C$12,IF(G6=MatrixImpact!$B$13,MatrixImpact!$C$13,IF(G6=MatrixImpact!$B$14,MatrixImpact!$C$14,""))))) | P6: =INDIRECT(ADDRESS(ROW()+6,8,1,1,"Top 10 Risks")) -> 0 | Q6: =IF(IF(G6=MatrixImpact!$B$10,MatrixImpact!$D$10,IF(G6=MatrixImpact!$B$11,MatrixImpact!$D$11,IF(G6=MatrixImpact!$B$12,MatrixImpact!$D$12,IF(G6=MatrixImpact!$B$13,MatrixImpact!$D$13,IF(G6=MatrixImpact!$B$14,MatrixImpact!$D$14,"")))))<P6,P6,IF(G6=MatrixImpact!$B$10,MatrixImpact!$D$10,IF(G6=MatrixImpact!$B$11,MatrixImpact!$D$11,IF(G6=MatrixImpact!$B$12,MatrixImpact!$D$12,IF(G6=MatrixImpact!$B$13,MatrixImpact!$D$13,IF(G6=MatrixImpact!$B$14,MatrixImpact!$D$14,"")))))) | S6: =N6*R6 -> 0 | U6: 4 | V6: 1 | W6: =INDEX(MatrixImpact!C$4:C$8,MATCH($U6,MatrixImpact!$B$4:$B$8,0),1)*INDEX(MatrixImpact!C$10:C$14,MATCH($V6,MatrixImpact!$B$10:$B$14,0),1) -> 0 | X6: =INDEX(MatrixImpact!D$4:D$8,MATCH($U6,MatrixImpact!$B$4:$B$8,0),1)*INDEX(MatrixImpact!D$10:D$14,MATCH($V6,MatrixImpact!$B$10:$B$14,0),1) -> 1.8 | Y6: =IF(AND($AE$4>=W6,$AD$4<=X6),TRUE(),FALSE()) -> TRUE | AB6: =AB5-5% -> 0.85 | AC6: =AC5 -> 0 | AG6: Operations Risk | AH6: Market Risk: Products
B7: 5 | E7: =RiskList!A6&": "&RiskList!B6 -> Company 105: | F7: =IF($L7=0%,"",IF(AND($L7>MatrixImpact!$C$8,$L7<=MatrixImpact!$D$8),5,IF(AND($L7>MatrixImpact!$C$7,$L7<=MatrixImpact!$D$7),4,IF(AND($L7>MatrixImpact!$C$6,$L7<=MatrixImpact!$D$6),3,IF(AND($L7>MatrixImpact!$C$5,$L7<=MatrixImpact!$D$5),2,IF(AND($L7>MatrixImpact!$C$4,$L7<=MatrixImpact!$D$4),1,"")))))) | G7: =IF($P7>MatrixImpact!$C$14,5,IF(AND($P7>MatrixImpact!$C$13,$P7<=MatrixImpact!$D$13),4,IF(AND($P7>MatrixImpact!$C$12,$P7<=MatrixImpact!$D$12),3,IF(AND($P7>MatrixImpact!$C$11,$P7<=MatrixImpact!$D$11),2,IF(AND($P7>MatrixImpact!$C$10,$P7<=MatrixImpact!$D$10),1,""))))) | H7: =INDIRECT(ADDRESS(ROW()+6,9,1,1,"Top 10 Risks")) -> 0 | J7: =B7 -> 5 | K7: =IF(F7=MatrixImpact!$B$4,MatrixImpact!$C$4,IF(F7=MatrixImpact!$B$5,MatrixImpact!$C$5,IF(F7=MatrixImpact!$B$6,MatrixImpact!$C$6,IF(F7=MatrixImpact!$B$7,MatrixImpact!$C$7,IF(F7=MatrixImpact!$B$8,MatrixImpact!$C$8,""))))) | L7: =INDIRECT(ADDRESS(ROW()+6,10,1,1,"Top 10 Risks")) -> 0 | M7: =IF(F7=MatrixImpact!$B$4,MatrixImpact!$D$4,IF(F7=MatrixImpact!$B$5,MatrixImpact!$D$5,IF(F7=MatrixImpact!$B$6,MatrixImpact!$D$6,IF(F7=MatrixImpact!$B$7,MatrixImpact!$D$7,IF(F7=MatrixImpact!$B$8,MatrixImpact!$D$8,""))))) | O7: =IF(G7=MatrixImpact!$B$10,MatrixImpact!$C$10,IF(G7=MatrixImpact!$B$11,MatrixImpact!$C$11,IF(G7=MatrixImpact!$B$12,MatrixImpact!$C$12,IF(G7=MatrixImpact!$B$13,MatrixImpact!$C$13,IF(G7=MatrixImpact!$B$14,MatrixImpact!$C$14,""))))) | P7: =INDIRECT(ADDRESS(ROW()+6,8,1,1,"Top 10 Risks")) -> 0 | Q7: =IF(IF(G7=MatrixImpact!$B$10,MatrixImpact!$D$10,IF(G7=MatrixImpact!$B$11,MatrixImpact!$D$11,IF(G7=MatrixImpact!$B$12,MatrixImpact!$D$12,IF(G7=MatrixImpact!$B$13,MatrixImpact!$D$13,IF(G7=MatrixImpact!$B$14,MatrixImpact!$D$14,"")))))<P7,P7,IF(G7=MatrixImpact!$B$10,MatrixImpact!$D$10,IF(G7=MatrixImpact!$B$11,MatrixImpact!$D$11,IF(G7=MatrixImpact!$B$12,MatrixImpact!$D$12,IF(G7=MatrixImpact!$B$13,MatrixImpact!$D$13,IF(G7=MatrixImpact!$B$14,MatrixImpact!$D$14,"")))))) | S7: =N7*R7 -> 0 | U7: 5 | V7: 1 | W7: =INDEX(MatrixImpact!C$4:C$8,MATCH($U7,MatrixImpact!$B$4:$B$8,0),1)*INDEX(MatrixImpact!C$10:C$14,MATCH($V7,MatrixImpact!$B$10:$B$14,0),1) -> 0 | X7: =INDEX(MatrixImpact!D$4:D$8,MATCH($U7,MatrixImpact!$B$4:$B$8,0),1)*INDEX(MatrixImpact!D$10:D$14,MATCH($V7,MatrixImpact!$B$10:$B$14,0),1) -> 2 | Y7: =IF(AND($AE$4>=W7,$AD$4<=X7),TRUE(),FALSE()) -> TRUE | AB7: =AB6-5% -> 0.8 | AC7: =AC6 -> 0 | AG7: Legal Risk | AH7: Market Risk: Customers
B8: 6 | E8: =RiskList!A7&": "&RiskList!B7 -> Company 106: | F8: =IF($L8=0%,"",IF(AND($L8>MatrixImpact!$C$8,$L8<=MatrixImpact!$D$8),5,IF(AND($L8>MatrixImpact!$C$7,$L8<=MatrixImpact!$D$7),4,IF(AND($L8>MatrixImpact!$C$6,$L8<=MatrixImpact!$D$6),3,IF(AND($L8>MatrixImpact!$C$5,$L8<=MatrixImpact!$D$5),2,IF(AND($L8>MatrixImpact!$C$4,$L8<=MatrixImpact!$D$4),1,"")))))) | G8: =IF($P8>MatrixImpact!$C$14,5,IF(AND($P8>MatrixImpact!$C$13,$P8<=MatrixImpact!$D$13),4,IF(AND($P8>MatrixImpact!$C$12,$P8<=MatrixImpact!$D$12),3,IF(AND($P8>MatrixImpact!$C$11,$P8<=MatrixImpact!$D$11),2,IF(AND($P8>MatrixImpact!$C$10,$P8<=MatrixImpact!$D$10),1,""))))) | H8: =INDIRECT(ADDRESS(ROW()+6,9,1,1,"Top 10 Risks")) -> 0 | J8: =B8 -> 6 | K8: =IF(F8=MatrixImpact!$B$4,MatrixImpact!$C$4,IF(F8=MatrixImpact!$B$5,MatrixImpact!$C$5,IF(F8=MatrixImpact!$B$6,MatrixImpact!$C$6,IF(F8=MatrixImpact!$B$7,MatrixImpact!$C$7,IF(F8=MatrixImpact!$B$8,MatrixImpact!$C$8,""))))) | L8: =INDIRECT(ADDRESS(ROW()+6,10,1,1,"Top 10 Risks")) -> 0 | M8: =IF(F8=MatrixImpact!$B$4,MatrixImpact!$D$4,IF(F8=MatrixImpact!$B$5,MatrixImpact!$D$5,IF(F8=MatrixImpact!$B$6,MatrixImpact!$D$6,IF(F8=MatrixImpact!$B$7,MatrixImpact!$D$7,IF(F8=MatrixImpact!$B$8,MatrixImpact!$D$8,""))))) | O8: =IF(G8=MatrixImpact!$B$10,MatrixImpact!$C$10,IF(G8=MatrixImpact!$B$11,MatrixImpact!$C$11,IF(G8=MatrixImpact!$B$12,MatrixImpact!$C$12,IF(G8=MatrixImpact!$B$13,MatrixImpact!$C$13,IF(G8=MatrixImpact!$B$14,MatrixImpact!$C$14,""))))) | P8: =INDIRECT(ADDRESS(ROW()+6,8,1,1,"Top 10 Risks")) -> 0 | Q8: =IF(IF(G8=MatrixImpact!$B$10,MatrixImpact!$D$10,IF(G8=MatrixImpact!$B$11,MatrixImpact!$D$11,IF(G8=MatrixImpact!$B$12,MatrixImpact!$D$12,IF(G8=MatrixImpact!$B$13,MatrixImpact!$D$13,IF(G8=MatrixImpact!$B$14,MatrixImpact!$D$14,"")))))<P8,P8,IF(G8=MatrixImpact!$B$10,MatrixImpact!$D$10,IF(G8=MatrixImpact!$B$11,MatrixImpact!$D$11,IF(G8=MatrixImpact!$B$12,MatrixImpact!$D$12,IF(G8=MatrixImpact!$B$13,MatrixImpact!$D$13,IF(G8=MatrixImpact!$B$14,MatrixImpact!$D$14,"")))))) | S8: =N8*R8 -> 0 | U8: 1 | V8: 2 | W8: =INDEX(MatrixImpact!C$4:C$8,MATCH($U8,MatrixImpact!$B$4:$B$8,0),1)*INDEX(MatrixImpact!C$10:C$14,MATCH($V8,MatrixImpact!$B$10:$B$14,0),1) -> 0 | X8: =INDEX(MatrixImpact!D$4:D$8,MATCH($U8,MatrixImpact!$B$4:$B$8,0),1)*INDEX(MatrixImpact!D$10:D$14,MATCH($V8,MatrixImpact!$B$10:$B$14,0),1) -> 0.5 | Y8: =IF(AND($AE$4>=W8,$AD$4<=X8),TRUE(),FALSE()) -> TRUE | AB8: =AB7-5% -> 0.75 | AC8: =AC7 -> 0 | AG8: Political Risk | AH8: Information for decision making Risk
B9: 7 | E9: =RiskList!A8&": "&RiskList!B8 -> Company 107: | F9: =IF($L9=0%,"",IF(AND($L9>MatrixImpact!$C$8,$L9<=MatrixImpact!$D$8),5,IF(AND($L9>MatrixImpact!$C$7,$L9<=MatrixImpact!$D$7),4,IF(AND($L9>MatrixImpact!$C$6,$L9<=MatrixImpact!$D$6),3,IF(AND($L9>MatrixImpact!$C$5,$L9<=MatrixImpact!$D$5),2,IF(AND($L9>MatrixImpact!$C$4,$L9<=MatrixImpact!$D$4),1,"")))))) | G9: =IF($P9>MatrixImpact!$C$14,5,IF(AND($P9>MatrixImpact!$C$13,$P9<=MatrixImpact!$D$13),4,IF(AND($P9>MatrixImpact!$C$12,$P9<=MatrixImpact!$D$12),3,IF(AND($P9>MatrixImpact!$C$11,$P9<=MatrixImpact!$D$11),2,IF(AND($P9>MatrixImpact!$C$10,$P9<=MatrixImpact!$D$10),1,""))))) | H9: =INDIRECT(ADDRESS(ROW()+6,9,1,1,"Top 10 Risks")) -> 0 | J9: =B9 -> 7 | K9: =IF(F9=MatrixImpact!$B$4,MatrixImpact!$C$4,IF(F9=MatrixImpact!$B$5,MatrixImpact!$C$5,IF(F9=MatrixImpact!$B$6,MatrixImpact!$C$6,IF(F9=MatrixImpact!$B$7,MatrixImpact!$C$7,IF(F9=MatrixImpact!$B$8,MatrixImpact!$C$8,""))))) | L9: =INDIRECT(ADDRESS(ROW()+6,10,1,1,"Top 10 Risks")) -> 0 | M9: =IF(F9=MatrixImpact!$B$4,MatrixImpact!$D$4,IF(F9=MatrixImpact!$B$5,MatrixImpact!$D$5,IF(F9=MatrixImpact!$B$6,MatrixImpact!$D$6,IF(F9=MatrixImpact!$B$7,MatrixImpact!$D$7,IF(F9=MatrixImpact!$B$8,MatrixImpact!$D$8,""))))) | O9: =IF(G9=MatrixImpact!$B$10,MatrixImpact!$C$10,IF(G9=MatrixImpact!$B$11,MatrixImpact!$C$11,IF(G9=MatrixImpact!$B$12,MatrixImpact!$C$12,IF(G9=MatrixImpact!$B$13,MatrixImpact!$C$13,IF(G9=MatrixImpact!$B$14,MatrixImpact!$C$14,""))))) | P9: =INDIRECT(ADDRESS(ROW()+6,8,1,1,"Top 10 Risks")) -> 0 | Q9: =IF(IF(G9=MatrixImpact!$B$10,MatrixImpact!$D$10,IF(G9=MatrixImpact!$B$11,MatrixImpact!$D$11,IF(G9=MatrixImpact!$B$12,MatrixImpact!$D$12,IF(G9=MatrixImpact!$B$13,MatrixImpact!$D$13,IF(G9=MatrixImpact!$B$14,MatrixImpact!$D$14,"")))))<P9,P9,IF(G9=MatrixImpact!$B$10,MatrixImpact!$D$10,IF(G9=MatrixImpact!$B$11,MatrixImpact!$D$11,IF(G9=MatrixImpact!$B$12,MatrixImpact!$D$12,IF(G9=MatrixImpact!$B$13,MatrixImpact!$D$13,IF(G9=MatrixImpact!$B$14,MatrixImpact!$D$14,"")))))) | S9: =N9*R9 -> 0 | U9: 2 | V9: 2 | W9: =INDEX(MatrixImpact!C$4:C$8,MATCH($U9,MatrixImpact!$B$4:$B$8,0),1)*INDEX(MatrixImpact!C$10:C$14,MATCH($V9,MatrixImpact!$B$10:$B$14,0),1) -> 0.2 | X9: =INDEX(MatrixImpact!D$4:D$8,MATCH($U9,MatrixImpact!$B$4:$B$8,0),1)*INDEX(MatrixImpact!D$10:D$14,MATCH($V9,MatrixImpact!$B$10:$B$14,0),1) -> 1.5 | Y9: =IF(AND($AE$4>=W9,$AD$4<=X9),TRUE(),FALSE()) -> FALSE | AB9: =AB8-5% -> 0.7 | AC9: =AC8 -> 0 | AG9: Exogenous Risk | AH9: Alignment Risk
B10: 8 | E10: =RiskList!A9&": "&RiskList!B9 -> Company 108: | F10: =IF($L10=0%,"",IF(AND($L10>MatrixImpact!$C$8,$L10<=MatrixImpact!$D$8),5,IF(AND($L10>MatrixImpact!$C$7,$L10<=MatrixImpact!$D$7),4,IF(AND($L10>MatrixImpact!$C$6,$L10<=MatrixImpact!$D$6),3,IF(AND($L10>MatrixImpact!$C$5,$L10<=MatrixImpact!$D$5),2,IF(AND($L10>MatrixImpact!$C$4,$L10<=MatrixImpact!$D$4),1,"")))))) | G10: =IF($P10>MatrixImpact!$C$14,5,IF(AND($P10>MatrixImpact!$C$13,$P10<=MatrixImpact!$D$13),4,IF(AND($P10>MatrixImpact!$C$12,$P10<=MatrixImpact!$D$12),3,IF(AND($P10>MatrixImpact!$C$11,$P10<=MatrixImpact!$D$11),2,IF(AND($P10>MatrixImpact!$C$10,$P10<=MatrixImpact!$D$10),1,""))))) | H10: =INDIRECT(ADDRESS(ROW()+6,9,1,1,"Top 10 Risks")) -> 0 | J10: =B10 -> 8 | K10: =IF(F10=MatrixImpact!$B$4,MatrixImpact!$C$4,IF(F10=MatrixImpact!$B$5,MatrixImpact!$C$5,IF(F10=MatrixImpact!$B$6,MatrixImpact!$C$6,IF(F10=MatrixImpact!$B$7,MatrixImpact!$C$7,IF(F10=MatrixImpact!$B$8,MatrixImpact!$C$8,""))))) | L10: =INDIRECT(ADDRESS(ROW()+6,10,1,1,"Top 10 Risks")) -> 0 | M10: =IF(F10=MatrixImpact!$B$4,MatrixImpact!$D$4,IF(F10=MatrixImpact!$B$5,MatrixImpact!$D$5,IF(F10=MatrixImpact!$B$6,MatrixImpact!$D$6,IF(F10=MatrixImpact!$B$7,MatrixImpact!$D$7,IF(F10=MatrixImpact!$B$8,MatrixImpact!$D$8,""))))) | O10: =IF(G10=MatrixImpact!$B$10,MatrixImpact!$C$10,IF(G10=MatrixImpact!$B$11,MatrixImpact!$C$11,IF(G10=MatrixImpact!$B$12,MatrixImpact!$C$12,IF(G10=MatrixImpact!$B$13,MatrixImpact!$C$13,IF(G10=MatrixImpact!$B$14,MatrixImpact!$C$14,""))))) | P10: =INDIRECT(ADDRESS(ROW()+6,8,1,1,"Top 10 Risks")) -> 0 | Q10: =IF(IF(G10=MatrixImpact!$B$10,MatrixImpact!$D$10,IF(G10=MatrixImpact!$B$11,MatrixImpact!$D$11,IF(G10=MatrixImpact!$B$12,MatrixImpact!$D$12,IF(G10=MatrixImpact!$B$13,MatrixImpact!$D$13,IF(G10=MatrixImpact!$B$14,MatrixImpact!$D$14,"")))))<P10,P10,IF(G10=MatrixImpact!$B$10,MatrixImpact!$D$10,IF(G10=MatrixImpact!$B$11,MatrixImpact!$D$11,IF(G10=MatrixImpact!$B$12,MatrixImpact!$D$12,IF(G10=MatrixImpact!$B$13,MatrixImpact!$D$13,IF(G10=MatrixImpact!$B$14,MatrixImpact!$D$14,"")))))) | S10: =N10*R10 -> 0 | U10: 3 | V10: 2 | W10: =INDEX(MatrixImpact!C$4:C$8,MATCH($U10,MatrixImpact!$B$4:$B$8,0),1)*INDEX(MatrixImpact!C$10:C$14,MATCH($V10,MatrixImpact!$B$10:$B$14,0),1) -> 0.6 | X10: =INDEX(MatrixImpact!D$4:D$8,MATCH($U10,MatrixImpact!$B$4:$B$8,0),1)*INDEX(MatrixImpact!D$10:D$14,MATCH($V10,MatrixImpact!$B$10:$B$14,0),1) -> 2.5 | Y10: =IF(AND($AE$4>=W10,$AD$4<=X10),TRUE(),FALSE()) -> FALSE | AB10: =AB9-5% -> 0.65 | AC10: =AC9 -> 0 | AG10: Market Risk | AH10: R&D Risk
B11: 9 | E11: =RiskList!A10&": "&RiskList!B10 -> Company 109: | F11: =IF($L11=0%,"",IF(AND($L11>MatrixImpact!$C$8,$L11<=MatrixImpact!$D$8),5,IF(AND($L11>MatrixImpact!$C$7,$L11<=MatrixImpact!$D$7),4,IF(AND($L11>MatrixImpact!$C$6,$L11<=MatrixImpact!$D$6),3,IF(AND($L11>MatrixImpact!$C$5,$L11<=MatrixImpact!$D$5),2,IF(AND($L11>MatrixImpact!$C$4,$L11<=MatrixImpact!$D$4),1,"")))))) | G11: =IF($P11>MatrixImpact!$C$14,5,IF(AND($P11>MatrixImpact!$C$13,$P11<=MatrixImpact!$D$13),4,IF(AND($P11>MatrixImpact!$C$12,$P11<=MatrixImpact!$D$12),3,IF(AND($P11>MatrixImpact!$C$11,$P11<=MatrixImpact!$D$11),2,IF(AND($P11>MatrixImpact!$C$10,$P11<=MatrixImpact!$D$10),1,""))))) | H11: =INDIRECT(ADDRESS(ROW()+6,9,1,1,"Top 10 Risks")) -> 0 | J11: =B11 -> 9 | K11: =IF(F11=MatrixImpact!$B$4,MatrixImpact!$C$4,IF(F11=MatrixImpact!$B$5,MatrixImpact!$C$5,IF(F11=MatrixImpact!$B$6,MatrixImpact!$C$6,IF(F11=MatrixImpact!$B$7,MatrixImpact!$C$7,IF(F11=MatrixImpact!$B$8,MatrixImpact!$C$8,""))))) | L11: =INDIRECT(ADDRESS(ROW()+6,10,1,1,"Top 10 Risks")) -> 0 | M11: =IF(F11=MatrixImpact!$B$4,MatrixImpact!$D$4,IF(F11=MatrixImpact!$B$5,MatrixImpact!$D$5,IF(F11=MatrixImpact!$B$6,MatrixImpact!$D$6,IF(F11=MatrixImpact!$B$7,MatrixImpact!$D$7,IF(F11=MatrixImpact!$B$8,MatrixImpact!$D$8,""))))) | O11: =IF(G11=MatrixImpact!$B$10,MatrixImpact!$C$10,IF(G11=MatrixImpact!$B$11,MatrixImpact!$C$11,IF(G11=MatrixImpact!$B$12,MatrixImpact!$C$12,IF(G11=MatrixImpact!$B$13,MatrixImpact!$C$13,IF(G11=MatrixImpact!$B$14,MatrixImpact!$C$14,""))))) | P11: =INDIRECT(ADDRESS(ROW()+6,8,1,1,"Top 10 Risks")) -> 0 | Q11: =IF(IF(G11=MatrixImpact!$B$10,MatrixImpact!$D$10,IF(G11=MatrixImpact!$B$11,MatrixImpact!$D$11,IF(G11=MatrixImpact!$B$12,MatrixImpact!$D$12,IF(G11=MatrixImpact!$B$13,MatrixImpact!$D$13,IF(G11=MatrixImpact!$B$14,MatrixImpact!$D$14,"")))))<P11,P11,IF(G11=MatrixImpact!$B$10,MatrixImpact!$D$10,IF(G11=MatrixImpact!$B$11,MatrixImpact!$D$11,IF(G11=MatrixImpact!$B$12,MatrixImpact!$D$12,IF(G11=MatrixImpact!$B$13,MatrixImpact!$D$13,IF(G11=MatrixImpact!$B$14,MatrixImpact!$D$14,"")))))) | S11: =N11*R11 -> 0 | U11: 4 | V11: 2 | W11: =INDEX(MatrixImpact!C$4:C$8,MATCH($U11,MatrixImpact!$B$4:$B$8,0),1)*INDEX(MatrixImpact!C$10:C$14,MATCH($V11,MatrixImpact!$B$10:$B$14,0),1) -> 1 | X11: =INDEX(MatrixImpact!D$4:D$8,MATCH($U11,MatrixImpact!$B$4:$B$8,0),1)*INDEX(MatrixImpact!D$10:D$14,MATCH($V11,MatrixImpact!$B$10:$B$14,0),1) -> 4.5 | Y11: =IF(AND($AE$4>=W11,$AD$4<=X11),TRUE(),FALSE()) -> FALSE | AB11: =AB10-5% -> 0.6 | AC11: =AC10 -> 0 | AG11: Credit Risk | AH11: Business Relations Risk
B12: 10 | E12: =RiskList!A11&": "&RiskList!B11 -> Company 110: | F12: =IF($L12=0%,"",IF(AND($L12>MatrixImpact!$C$8,$L12<=MatrixImpact!$D$8),5,IF(AND($L12>MatrixImpact!$C$7,$L12<=MatrixImpact!$D$7),4,IF(AND($L12>MatrixImpact!$C$6,$L12<=MatrixImpact!$D$6),3,IF(AND($L12>MatrixImpact!$C$5,$L12<=MatrixImpact!$D$5),2,IF(AND($L12>MatrixImpact!$C$4,$L12<=MatrixImpact!$D$4),1,"")))))) | G12: =IF($P12>MatrixImpact!$C$14,5,IF(AND($P12>MatrixImpact!$C$13,$P12<=MatrixImpact!$D$13),4,IF(AND($P12>MatrixImpact!$C$12,$P12<=MatrixImpact!$D$12),3,IF(AND($P12>MatrixImpact!$C$11,$P12<=MatrixImpact!$D$11),2,IF(AND($P12>MatrixImpact!$C$10,$P12<=MatrixImpact!$D$10),1,""))))) | H12: =INDIRECT(ADDRESS(ROW()+6,9,1,1,"Top 10 Risks")) -> 0 | J12: =B12 -> 10 | K12: =IF(F12=MatrixImpact!$B$4,MatrixImpact!$C$4,IF(F12=MatrixImpact!$B$5,MatrixImpact!$C$5,IF(F12=MatrixImpact!$B$6,MatrixImpact!$C$6,IF(F12=MatrixImpact!$B$7,MatrixImpact!$C$7,IF(F12=MatrixImpact!$B$8,MatrixImpact!$C$8,""))))) | L12: =INDIRECT(ADDRESS(ROW()+6,10,1,1,"Top 10 Risks")) -> 0 | M12: =IF(F12=MatrixImpact!$B$4,MatrixImpact!$D$4,IF(F12=MatrixImpact!$B$5,MatrixImpact!$D$5,IF(F12=MatrixImpact!$B$6,MatrixImpact!$D$6,IF(F12=MatrixImpact!$B$7,MatrixImpact!$D$7,IF(F12=MatrixImpact!$B$8,MatrixImpact!$D$8,""))))) | O12: =IF(G12=MatrixImpact!$B$10,MatrixImpact!$C$10,IF(G12=MatrixImpact!$B$11,MatrixImpact!$C$11,IF(G12=MatrixImpact!$B$12,MatrixImpact!$C$12,IF(G12=MatrixImpact!$B$13,MatrixImpact!$C$13,IF(G12=MatrixImpact!$B$14,MatrixImpact!$C$14,""))))) | P12: =INDIRECT(ADDRESS(ROW()+6,8,1,1,"Top 10 Risks")) -> 0 | Q12: =IF(IF(G12=MatrixImpact!$B$10,MatrixImpact!$D$10,IF(G12=MatrixImpact!$B$11,MatrixImpact!$D$11,IF(G12=MatrixImpact!$B$12,MatrixImpact!$D$12,IF(G12=MatrixImpact!$B$13,MatrixImpact!$D$13,IF(G12=MatrixImpact!$B$14,MatrixImpact!$D$14,"")))))<P12,P12,IF(G12=MatrixImpact!$B$10,MatrixImpact!$D$10,IF(G12=MatrixImpact!$B$11,MatrixImpact!$D$11,IF(G12=MatrixImpact!$B$12,MatrixImpact!$D$12,IF(G12=MatrixImpact!$B$13,MatrixImpact!$D$13,IF(G12=MatrixImpact!$B$14,MatrixImpact!$D$14,"")))))) | S12: =N12*R12 -> 0 | U12: 5 | V12: 2 | W12: =INDEX(MatrixImpact!C$4:C$8,MATCH($U12,MatrixImpact!$B$4:$B$8,0),1)*INDEX(MatrixImpact!C$10:C$14,MATCH($V12,MatrixImpact!$B$10:$B$14,0),1) -> 1.8 | X12: =INDEX(MatrixImpact!D$4:D$8,MATCH($U12,MatrixImpact!$B$4:$B$8,0),1)*INDEX(MatrixImpact!D$10:D$14,MATCH($V12,MatrixImpact!$B$10:$B$14,0),1) -> 5 | Y12: =IF(AND($AE$4>=W12,$AD$4<=X12),TRUE(),FALSE()) -> FALSE | AB12: =AB11-5% -> 0.55 | AC12: =AC11 -> 0 | AH12: Image Risk
B13: 11 | E13: =RiskList!A12&": "&RiskList!B12 -> Company 111: | F13: =IF($L13=0%,"",IF(AND($L13>MatrixImpact!$C$8,$L13<=MatrixImpact!$D$8),5,IF(AND($L13>MatrixImpact!$C$7,$L13<=MatrixImpact!$D$7),4,IF(AND($L13>MatrixImpact!$C$6,$L13<=MatrixImpact!$D$6),3,IF(AND($L13>MatrixImpact!$C$5,$L13<=MatrixImpact!$D$5),2,IF(AND($L13>MatrixImpact!$C$4,$L13<=MatrixImpact!$D$4),1,"")))))) | G13: =IF($P13>MatrixImpact!$C$14,5,IF(AND($P13>MatrixImpact!$C$13,$P13<=MatrixImpact!$D$13),4,IF(AND($P13>MatrixImpact!$C$12,$P13<=MatrixImpact!$D$12),3,IF(AND($P13>MatrixImpact!$C$11,$P13<=MatrixImpact!$D$11),2,IF(AND($P13>MatrixImpact!$C$10,$P13<=MatrixImpact!$D$10),1,""))))) | H13: =INDIRECT(ADDRESS(ROW()+6,9,1,1,"Top 10 Risks")) -> 0 | J13: =B13 -> 11 | K13: =IF(F13=MatrixImpact!$B$4,MatrixImpact!$C$4,IF(F13=MatrixImpact!$B$5,MatrixImpact!$C$5,IF(F13=MatrixImpact!$B$6,MatrixImpact!$C$6,IF(F13=MatrixImpact!$B$7,MatrixImpact!$C$7,IF(F13=MatrixImpact!$B$8,MatrixImpact!$C$8,""))))) | L13: =INDIRECT(ADDRESS(ROW()+6,10,1,1,"Top 10 Risks")) -> 0 | M13: =IF(F13=MatrixImpact!$B$4,MatrixImpact!$D$4,IF(F13=MatrixImpact!$B$5,MatrixImpact!$D$5,IF(F13=MatrixImpact!$B$6,MatrixImpact!$D$6,IF(F13=MatrixImpact!$B$7,MatrixImpact!$D$7,IF(F13=MatrixImpact!$B$8,MatrixImpact!$D$8,""))))) | O13: =IF(G13=MatrixImpact!$B$10,MatrixImpact!$C$10,IF(G13=MatrixImpact!$B$11,MatrixImpact!$C$11,IF(G13=MatrixImpact!$B$12,MatrixImpact!$C$12,IF(G13=MatrixImpact!$B$13,MatrixImpact!$C$13,IF(G13=MatrixImpact!$B$14,MatrixImpact!$C$14,""))))) | P13: =INDIRECT(ADDRESS(ROW()+6,8,1,1,"Top 10 Risks")) -> 0 | Q13: =IF(IF(G13=MatrixImpact!$B$10,MatrixImpact!$D$10,IF(G13=MatrixImpact!$B$11,MatrixImpact!$D$11,IF(G13=MatrixImpact!$B$12,MatrixImpact!$D$12,IF(G13=MatrixImpact!$B$13,MatrixImpact!$D$13,IF(G13=MatrixImpact!$B$14,MatrixImpact!$D$14,"")))))<P13,P13,IF(G13=MatrixImpact!$B$10,MatrixImpact!$D$10,IF(G13=MatrixImpact!$B$11,MatrixImpact!$D$11,IF(G13=MatrixImpact!$B$12,MatrixImpact!$D$12,IF(G13=MatrixImpact!$B$13,MatrixImpact!$D$13,IF(G13=MatrixImpact!$B$14,MatrixImpact!$D$14,"")))))) | S13: =N13*R13 -> 0 | U13: 1 | V13: 3 | W13: =INDEX(MatrixImpact!C$4:C$8,MATCH($U13,MatrixImpact!$B$4:$B$8,0),1)*INDEX(MatrixImpact!C$10:C$14,MATCH($V13,MatrixImpact!$B$10:$B$14,0),1) -> 0 | X13: =INDEX(MatrixImpact!D$4:D$8,MATCH($U13,MatrixImpact!$B$4:$B$8,0),1)*INDEX(MatrixImpact!D$10:D$14,MATCH($V13,MatrixImpact!$B$10:$B$14,0),1) -> 1 | Y13: =IF(AND($AE$4>=W13,$AD$4<=X13),TRUE(),FALSE()) -> TRUE | AB13: =AB12-5% -> 0.5 | AC13: =AC12 -> 0 | AH13: Stakeholder Satisfaction Risk
B14: 12 | E14: =RiskList!A13&": "&RiskList!B13 -> Company 112: | F14: =IF($L14=0%,"",IF(AND($L14>MatrixImpact!$C$8,$L14<=MatrixImpact!$D$8),5,IF(AND($L14>MatrixImpact!$C$7,$L14<=MatrixImpact!$D$7),4,IF(AND($L14>MatrixImpact!$C$6,$L14<=MatrixImpact!$D$6),3,IF(AND($L14>MatrixImpact!$C$5,$L14<=MatrixImpact!$D$5),2,IF(AND($L14>MatrixImpact!$C$4,$L14<=MatrixImpact!$D$4),1,"")))))) | G14: =IF($P14>MatrixImpact!$C$14,5,IF(AND($P14>MatrixImpact!$C$13,$P14<=MatrixImpact!$D$13),4,IF(AND($P14>MatrixImpact!$C$12,$P14<=MatrixImpact!$D$12),3,IF(AND($P14>MatrixImpact!$C$11,$P14<=MatrixImpact!$D$11),2,IF(AND($P14>MatrixImpact!$C$10,$P14<=MatrixImpact!$D$10),1,""))))) | H14: =INDIRECT(ADDRESS(ROW()+6,9,1,1,"Top 10 Risks")) -> 0 | J14: =B14 -> 12 | K14: =IF(F14=MatrixImpact!$B$4,MatrixImpact!$C$4,IF(F14=MatrixImpact!$B$5,MatrixImpact!$C$5,IF(F14=MatrixImpact!$B$6,MatrixImpact!$C$6,IF(F14=MatrixImpact!$B$7,MatrixImpact!$C$7,IF(F14=MatrixImpact!$B$8,MatrixImpact!$C$8,""))))) | L14: =INDIRECT(ADDRESS(ROW()+6,10,1,1,"Top 10 Risks")) -> 0 | M14: =IF(F14=MatrixImpact!$B$4,MatrixImpact!$D$4,IF(F14=MatrixImpact!$B$5,MatrixImpact!$D$5,IF(F14=MatrixImpact!$B$6,MatrixImpact!$D$6,IF(F14=MatrixImpact!$B$7,MatrixImpact!$D$7,IF(F14=MatrixImpact!$B$8,MatrixImpact!$D$8,""))))) | O14: =IF(G14=MatrixImpact!$B$10,MatrixImpact!$C$10,IF(G14=MatrixImpact!$B$11,MatrixImpact!$C$11,IF(G14=MatrixImpact!$B$12,MatrixImpact!$C$12,IF(G14=MatrixImpact!$B$13,MatrixImpact!$C$13,IF(G14=MatrixImpact!$B$14,MatrixImpact!$C$14,""))))) | P14: =INDIRECT(ADDRESS(ROW()+6,8,1,1,"Top 10 Risks")) -> 0 | Q14: =IF(IF(G14=MatrixImpact!$B$10,MatrixImpact!$D$10,IF(G14=MatrixImpact!$B$11,MatrixImpact!$D$11,IF(G14=MatrixImpact!$B$12,MatrixImpact!$D$12,IF(G14=MatrixImpact!$B$13,MatrixImpact!$D$13,IF(G14=MatrixImpact!$B$14,MatrixImpact!$D$14,"")))))<P14,P14,IF(G14=MatrixImpact!$B$10,MatrixImpact!$D$10,IF(G14=MatrixImpact!$B$11,MatrixImpact!$D$11,IF(G14=MatrixImpact!$B$12,MatrixImpact!$D$12,IF(G14=MatrixImpact!$B$13,MatrixImpact!$D$13,IF(G14=MatrixImpact!$B$14,MatrixImpact!$D$14,"")))))) | S14: =N14*R14 -> 0 | U14: 2 | V14: 3 | W14: =INDEX(MatrixImpact!C$4:C$8,MATCH($U14,MatrixImpact!$B$4:$B$8,0),1)*INDEX(MatrixImpact!C$10:C$14,MATCH($V14,MatrixImpact!$B$10:$B$14,0),1) -> 0.5 | X14: =INDEX(MatrixImpact!D$4:D$8,MATCH($U14,MatrixImpact!$B$4:$B$8,0),1)*INDEX(MatrixImpact!D$10:D$14,MATCH($V14,MatrixImpact!$B$10:$B$14,0),1) -> 3 | Y14: =IF(AND($AE$4>=W14,$AD$4<=X14),TRUE(),FALSE()) -> FALSE | AB14: =AB13-5% -> 0.45 | AC14: =AC13 -> 0 | AH14: Employee Relations Risk
B15: 13 | E15: =RiskList!A14&": "&RiskList!B14 -> Company 113: | F15: =IF($L15=0%,"",IF(AND($L15>MatrixImpact!$C$8,$L15<=MatrixImpact!$D$8),5,IF(AND($L15>MatrixImpact!$C$7,$L15<=MatrixImpact!$D$7),4,IF(AND($L15>MatrixImpact!$C$6,$L15<=MatrixImpact!$D$6),3,IF(AND($L15>MatrixImpact!$C$5,$L15<=MatrixImpact!$D$5),2,IF(AND($L15>MatrixImpact!$C$4,$L15<=MatrixImpact!$D$4),1,"")))))) | G15: =IF($P15>MatrixImpact!$C$14,5,IF(AND($P15>MatrixImpact!$C$13,$P15<=MatrixImpact!$D$13),4,IF(AND($P15>MatrixImpact!$C$12,$P15<=MatrixImpact!$D$12),3,IF(AND($P15>MatrixImpact!$C$11,$P15<=MatrixImpact!$D$11),2,IF(AND($P15>MatrixImpact!$C$10,$P15<=MatrixImpact!$D$10),1,""))))) | H15: =INDIRECT(ADDRESS(ROW()+6,9,1,1,"Top 10 Risks")) -> 0 | J15: =B15 -> 13 | K15: =IF(F15=MatrixImpact!$B$4,MatrixImpact!$C$4,IF(F15=MatrixImpact!$B$5,MatrixImpact!$C$5,IF(F15=MatrixImpact!$B$6,MatrixImpact!$C$6,IF(F15=MatrixImpact!$B$7,MatrixImpact!$C$7,IF(F15=MatrixImpact!$B$8,MatrixImpact!$C$8,""))))) | L15: =INDIRECT(ADDRESS(ROW()+6,10,1,1,"Top 10 Risks")) -> 0 | M15: =IF(F15=MatrixImpact!$B$4,MatrixImpact!$D$4,IF(F15=MatrixImpact!$B$5,MatrixImpact!$D$5,IF(F15=MatrixImpact!$B$6,MatrixImpact!$D$6,IF(F15=MatrixImpact!$B$7,MatrixImpact!$D$7,IF(F15=MatrixImpact!$B$8,MatrixImpact!$D$8,""))))) | O15: =IF(G15=MatrixImpact!$B$10,MatrixImpact!$C$10,IF(G15=MatrixImpact!$B$11,MatrixImpact!$C$11,IF(G15=MatrixImpact!$B$12,MatrixImpact!$C$12,IF(G15=MatrixImpact!$B$13,MatrixImpact!$C$13,IF(G15=MatrixImpact!$B$14,MatrixImpact!$C$14,""))))) | P15: =INDIRECT(ADDRESS(ROW()+6,8,1,1,"Top 10 Risks")) -> 0 | Q15: =IF(IF(G15=MatrixImpact!$B$10,MatrixImpact!$D$10,IF(G15=MatrixImpact!$B$11,MatrixImpact!$D$11,IF(G15=MatrixImpact!$B$12,MatrixImpact!$D$12,IF(G15=MatrixImpact!$B$13,MatrixImpact!$D$13,IF(G15=MatrixImpact!$B$14,MatrixImpact!$D$14,"")))))<P15,P15,IF(G15=MatrixImpact!$B$10,MatrixImpact!$D$10,IF(G15=MatrixImpact!$B$11,MatrixImpact!$D$11,IF(G15=MatrixImpact!$B$12,MatrixImpact!$D$12,IF(G15=MatrixImpact!$B$13,MatrixImpact!$D$13,IF(G15=MatrixImpact!$B$14,MatrixImpact!$D$14,"")))))) | S15: =N15*R15 -> 0 | U15: 3 | V15: 3 | W15: =INDEX(MatrixImpact!C$4:C$8,MATCH($U15,MatrixImpact!$B$4:$B$8,0),1)*INDEX(MatrixImpact!C$10:C$14,MATCH($V15,MatrixImpact!$B$10:$B$14,0),1) -> 1.5 | X15: =INDEX(MatrixImpact!D$4:D$8,MATCH($U15,MatrixImpact!$B$4:$B$8,0),1)*INDEX(MatrixImpact!D$10:D$14,MATCH($V15,MatrixImpact!$B$10:$B$14,0),1) -> 5 | Y15: =IF(AND($AE$4>=W15,$AD$4<=X15),TRUE(),FALSE()) -> FALSE | AB15: =AB14-5% -> 0.4 | AC15: =AC14 -> 0 | AH15: HR Risk
B16: 14 | E16: =RiskList!A15&": "&RiskList!B15 -> Company 114: | F16: =IF($L16=0%,"",IF(AND($L16>MatrixImpact!$C$8,$L16<=MatrixImpact!$D$8),5,IF(AND($L16>MatrixImpact!$C$7,$L16<=MatrixImpact!$D$7),4,IF(AND($L16>MatrixImpact!$C$6,$L16<=MatrixImpact!$D$6),3,IF(AND($L16>MatrixImpact!$C$5,$L16<=MatrixImpact!$D$5),2,IF(AND($L16>MatrixImpact!$C$4,$L16<=MatrixImpact!$D$4),1,"")))))) | G16: =IF($P16>MatrixImpact!$C$14,5,IF(AND($P16>MatrixImpact!$C$13,$P16<=MatrixImpact!$D$13),4,IF(AND($P16>MatrixImpact!$C$12,$P16<=MatrixImpact!$D$12),3,IF(AND($P16>MatrixImpact!$C$11,$P16<=MatrixImpact!$D$11),2,IF(AND($P16>MatrixImpact!$C$10,$P16<=MatrixImpact!$D$10),1,""))))) | H16: =INDIRECT(ADDRESS(ROW()+6,9,1,1,"Top 10 Risks")) -> 0 | J16: =B16 -> 14 | K16: =IF(F16=MatrixImpact!$B$4,MatrixImpact!$C$4,IF(F16=MatrixImpact!$B$5,MatrixImpact!$C$5,IF(F16=MatrixImpact!$B$6,MatrixImpact!$C$6,IF(F16=MatrixImpact!$B$7,MatrixImpact!$C$7,IF(F16=MatrixImpact!$B$8,MatrixImpact!$C$8,""))))) | L16: =INDIRECT(ADDRESS(ROW()+6,10,1,1,"Top 10 Risks")) -> 0 | M16: =IF(F16=MatrixImpact!$B$4,MatrixImpact!$D$4,IF(F16=MatrixImpact!$B$5,MatrixImpact!$D$5,IF(F16=MatrixImpact!$B$6,MatrixImpact!$D$6,IF(F16=MatrixImpact!$B$7,MatrixImpact!$D$7,IF(F16=MatrixImpact!$B$8,MatrixImpact!$D$8,""))))) | O16: =IF(G16=MatrixImpact!$B$10,MatrixImpact!$C$10,IF(G16=MatrixImpact!$B$11,MatrixImpact!$C$11,IF(G16=MatrixImpact!$B$12,MatrixImpact!$C$12,IF(G16=MatrixImpact!$B$13,MatrixImpact!$C$13,IF(G16=MatrixImpact!$B$14,MatrixImpact!$C$14,""))))) | P16: =INDIRECT(ADDRESS(ROW()+6,8,1,1,"Top 10 Risks")) -> 0 | Q16: =IF(IF(G16=MatrixImpact!$B$10,MatrixImpact!$D$10,IF(G16=MatrixImpact!$B$11,MatrixImpact!$D$11,IF(G16=MatrixImpact!$B$12,MatrixImpact!$D$12,IF(G16=MatrixImpact!$B$13,MatrixImpact!$D$13,IF(G16=MatrixImpact!$B$14,MatrixImpact!$D$14,"")))))<P16,P16,IF(G16=MatrixImpact!$B$10,MatrixImpact!$D$10,IF(G16=MatrixImpact!$B$11,MatrixImpact!$D$11,IF(G16=MatrixImpact!$B$12,MatrixImpact!$D$12,IF(G16=MatrixImpact!$B$13,MatrixImpact!$D$13,IF(G16=MatrixImpact!$B$14,MatrixImpact!$D$14,"")))))) | S16: =N16*R16 -> 0 | U16: 4 | V16: 3 | W16: =INDEX(MatrixImpact!C$4:C$8,MATCH($U16,MatrixImpact!$B$4:$B$8,0),1)*INDEX(MatrixImpact!C$10:C$14,MATCH($V16,MatrixImpact!$B$10:$B$14,0),1) -> 2.5 | X16: =INDEX(MatrixImpact!D$4:D$8,MATCH($U16,MatrixImpact!$B$4:$B$8,0),1)*INDEX(MatrixImpact!D$10:D$14,MATCH($V16,MatrixImpact!$B$10:$B$14,0),1) -> 9 | Y16: =IF(AND($AE$4>=W16,$AD$4<=X16),TRUE(),FALSE()) -> FALSE | AB16: =AB15-5% -> 0.35 | AC16: =AC15 -> 0
B17: 15 | E17: =RiskList!A16&": "&RiskList!B16 -> Company 115: | F17: =IF($L17=0%,"",IF(AND($L17>MatrixImpact!$C$8,$L17<=MatrixImpact!$D$8),5,IF(AND($L17>MatrixImpact!$C$7,$L17<=MatrixImpact!$D$7),4,IF(AND($L17>MatrixImpact!$C$6,$L17<=MatrixImpact!$D$6),3,IF(AND($L17>MatrixImpact!$C$5,$L17<=MatrixImpact!$D$5),2,IF(AND($L17>MatrixImpact!$C$4,$L17<=MatrixImpact!$D$4),1,"")))))) | G17: =IF($P17>MatrixImpact!$C$14,5,IF(AND($P17>MatrixImpact!$C$13,$P17<=MatrixImpact!$D$13),4,IF(AND($P17>MatrixImpact!$C$12,$P17<=MatrixImpact!$D$12),3,IF(AND($P17>MatrixImpact!$C$11,$P17<=MatrixImpact!$D$11),2,IF(AND($P17>MatrixImpact!$C$10,$P17<=MatrixImpact!$D$10),1,""))))) | H17: =INDIRECT(ADDRESS(ROW()+6,9,1,1,"Top 10 Risks")) -> 0 | J17: =B17 -> 15 | K17: =IF(F17=MatrixImpact!$B$4,MatrixImpact!$C$4,IF(F17=MatrixImpact!$B$5,MatrixImpact!$C$5,IF(F17=MatrixImpact!$B$6,MatrixImpact!$C$6,IF(F17=MatrixImpact!$B$7,MatrixImpact!$C$7,IF(F17=MatrixImpact!$B$8,MatrixImpact!$C$8,""))))) | L17: =INDIRECT(ADDRESS(ROW()+6,10,1,1,"Top 10 Risks")) -> 0 | M17: =IF(F17=MatrixImpact!$B$4,MatrixImpact!$D$4,IF(F17=MatrixImpact!$B$5,MatrixImpact!$D$5,IF(F17=MatrixImpact!$B$6,MatrixImpact!$D$6,IF(F17=MatrixImpact!$B$7,MatrixImpact!$D$7,IF(F17=MatrixImpact!$B$8,MatrixImpact!$D$8,""))))) | O17: =IF(G17=MatrixImpact!$B$10,MatrixImpact!$C$10,IF(G17=MatrixImpact!$B$11,MatrixImpact!$C$11,IF(G17=MatrixImpact!$B$12,MatrixImpact!$C$12,IF(G17=MatrixImpact!$B$13,MatrixImpact!$C$13,IF(G17=MatrixImpact!$B$14,MatrixImpact!$C$14,""))))) | P17: =INDIRECT(ADDRESS(ROW()+6,8,1,1,"Top 10 Risks")) -> 0 | Q17: =IF(IF(G17=MatrixImpact!$B$10,MatrixImpact!$D$10,IF(G17=MatrixImpact!$B$11,MatrixImpact!$D$11,IF(G17=MatrixImpact!$B$12,MatrixImpact!$D$12,IF(G17=MatrixImpact!$B$13,MatrixImpact!$D$13,IF(G17=MatrixImpact!$B$14,MatrixImpact!$D$14,"")))))<P17,P17,IF(G17=MatrixImpact!$B$10,MatrixImpact!$D$10,IF(G17=MatrixImpact!$B$11,MatrixImpact!$D$11,IF(G17=MatrixImpact!$B$12,MatrixImpact!$D$12,IF(G17=MatrixImpact!$B$13,MatrixImpact!$D$13,IF(G17=MatrixImpact!$B$14,MatrixImpact!$D$14,"")))))) | S17: =N17*R17 -> 0 | U17: 5 | V17: 3 | W17: =INDEX(MatrixImpact!C$4:C$8,MATCH($U17,MatrixImpact!$B$4:$B$8,0),1)*INDEX(MatrixImpact!C$10:C$14,MATCH($V17,MatrixImpact!$B$10:$B$14,0),1) -> 4.5 | X17: =INDEX(MatrixImpact!D$4:D$8,MATCH($U17,MatrixImpact!$B$4:$B$8,0),1)*INDEX(MatrixImpact!D$10:D$14,MATCH($V17,MatrixImpact!$B$10:$B$14,0),1) -> 10 | Y17: =IF(AND($AE$4>=W17,$AD$4<=X17),TRUE(),FALSE()) -> FALSE | AB17: =AB16-5% -> 0.3 | AC17: =AC16 -> 0 | AG17: Strategic Risk | AH17: Industry Risk
B18: 16 | E18: =RiskList!A17&": "&RiskList!B17 -> Company 116: | F18: =IF($L18=0%,"",IF(AND($L18>MatrixImpact!$C$8,$L18<=MatrixImpact!$D$8),5,IF(AND($L18>MatrixImpact!$C$7,$L18<=MatrixImpact!$D$7),4,IF(AND($L18>MatrixImpact!$C$6,$L18<=MatrixImpact!$D$6),3,IF(AND($L18>MatrixImpact!$C$5,$L18<=MatrixImpact!$D$5),2,IF(AND($L18>MatrixImpact!$C$4,$L18<=MatrixImpact!$D$4),1,"")))))) | G18: =IF($P18>MatrixImpact!$C$14,5,IF(AND($P18>MatrixImpact!$C$13,$P18<=MatrixImpact!$D$13),4,IF(AND($P18>MatrixImpact!$C$12,$P18<=MatrixImpact!$D$12),3,IF(AND($P18>MatrixImpact!$C$11,$P18<=MatrixImpact!$D$11),2,IF(AND($P18>MatrixImpact!$C$10,$P18<=MatrixImpact!$D$10),1,""))))) | H18: =INDIRECT(ADDRESS(ROW()+6,9,1,1,"Top 10 Risks")) -> 0 | J18: =B18 -> 16 | K18: =IF(F18=MatrixImpact!$B$4,MatrixImpact!$C$4,IF(F18=MatrixImpact!$B$5,MatrixImpact!$C$5,IF(F18=MatrixImpact!$B$6,MatrixImpact!$C$6,IF(F18=MatrixImpact!$B$7,MatrixImpact!$C$7,IF(F18=MatrixImpact!$B$8,MatrixImpact!$C$8,""))))) | L18: =INDIRECT(ADDRESS(ROW()+6,10,1,1,"Top 10 Risks")) -> 0 | M18: =IF(F18=MatrixImpact!$B$4,MatrixImpact!$D$4,IF(F18=MatrixImpact!$B$5,MatrixImpact!$D$5,IF(F18=MatrixImpact!$B$6,MatrixImpact!$D$6,IF(F18=MatrixImpact!$B$7,MatrixImpact!$D$7,IF(F18=MatrixImpact!$B$8,MatrixImpact!$D$8,""))))) | O18: =IF(G18=MatrixImpact!$B$10,MatrixImpact!$C$10,IF(G18=MatrixImpact!$B$11,MatrixImpact!$C$11,IF(G18=MatrixImpact!$B$12,MatrixImpact!$C$12,IF(G18=MatrixImpact!$B$13,MatrixImpact!$C$13,IF(G18=MatrixImpact!$B$14,MatrixImpact!$C$14,""))))) | P18: =INDIRECT(ADDRESS(ROW()+6,8,1,1,"Top 10 Risks")) -> 0 | Q18: =IF(IF(G18=MatrixImpact!$B$10,MatrixImpact!$D$10,IF(G18=MatrixImpact!$B$11,MatrixImpact!$D$11,IF(G18=MatrixImpact!$B$12,MatrixImpact!$D$12,IF(G18=MatrixImpact!$B$13,MatrixImpact!$D$13,IF(G18=MatrixImpact!$B$14,MatrixImpact!$D$14,"")))))<P18,P18,IF(G18=MatrixImpact!$B$10,MatrixImpact!$D$10,IF(G18=MatrixImpact!$B$11,MatrixImpact!$D$11,IF(G18=MatrixImpact!$B$12,MatrixImpact!$D$12,IF(G18=MatrixImpact!$B$13,MatrixImpact!$D$13,IF(G18=MatrixImpact!$B$14,MatrixImpact!$D$14,"")))))) | S18: =N18*R18 -> 0 | U18: 1 | V18: 4 | W18: =INDEX(MatrixImpact!C$4:C$8,MATCH($U18,MatrixImpact!$B$4:$B$8,0),1)*INDEX(MatrixImpact!C$10:C$14,MATCH($V18,MatrixImpact!$B$10:$B$14,0),1) -> 0 | X18: =INDEX(MatrixImpact!D$4:D$8,MATCH($U18,MatrixImpact!$B$4:$B$8,0),1)*INDEX(MatrixImpact!D$10:D$14,MATCH($V18,MatrixImpact!$B$10:$B$14,0),1) -> 3 | Y18: =IF(AND($AE$4>=W18,$AD$4<=X18),TRUE(),FALSE()) -> TRUE | AB18: =AB17-5% -> 0.25 | AC18: =AC17 -> 0 | AG18: Management Risk | AH18: Market Risk: Competitors
B19: 17 | E19: =RiskList!A18&": "&RiskList!B18 -> Company 117: | F19: =IF($L19=0%,"",IF(AND($L19>MatrixImpact!$C$8,$L19<=MatrixImpact!$D$8),5,IF(AND($L19>MatrixImpact!$C$7,$L19<=MatrixImpact!$D$7),4,IF(AND($L19>MatrixImpact!$C$6,$L19<=MatrixImpact!$D$6),3,IF(AND($L19>MatrixImpact!$C$5,$L19<=MatrixImpact!$D$5),2,IF(AND($L19>MatrixImpact!$C$4,$L19<=MatrixImpact!$D$4),1,"")))))) | G19: =IF($P19>MatrixImpact!$C$14,5,IF(AND($P19>MatrixImpact!$C$13,$P19<=MatrixImpact!$D$13),4,IF(AND($P19>MatrixImpact!$C$12,$P19<=MatrixImpact!$D$12),3,IF(AND($P19>MatrixImpact!$C$11,$P19<=MatrixImpact!$D$11),2,IF(AND($P19>MatrixImpact!$C$10,$P19<=MatrixImpact!$D$10),1,""))))) | H19: =INDIRECT(ADDRESS(ROW()+6,9,1,1,"Top 10 Risks")) -> 0 | J19: =B19 -> 17 | K19: =IF(F19=MatrixImpact!$B$4,MatrixImpact!$C$4,IF(F19=MatrixImpact!$B$5,MatrixImpact!$C$5,IF(F19=MatrixImpact!$B$6,MatrixImpact!$C$6,IF(F19=MatrixImpact!$B$7,MatrixImpact!$C$7,IF(F19=MatrixImpact!$B$8,MatrixImpact!$C$8,""))))) | L19: =INDIRECT(ADDRESS(ROW()+6,10,1,1,"Top 10 Risks")) -> 0 | M19: =IF(F19=MatrixImpact!$B$4,MatrixImpact!$D$4,IF(F19=MatrixImpact!$B$5,MatrixImpact!$D$5,IF(F19=MatrixImpact!$B$6,MatrixImpact!$D$6,IF(F19=MatrixImpact!$B$7,MatrixImpact!$D$7,IF(F19=MatrixImpact!$B$8,MatrixImpact!$D$8,""))))) | O19: =IF(G19=MatrixImpact!$B$10,MatrixImpact!$C$10,IF(G19=MatrixImpact!$B$11,MatrixImpact!$C$11,IF(G19=MatrixImpact!$B$12,MatrixImpact!$C$12,IF(G19=MatrixImpact!$B$13,MatrixImpact!$C$13,IF(G19=MatrixImpact!$B$14,MatrixImpact!$C$14,""))))) | P19: =INDIRECT(ADDRESS(ROW()+6,8,1,1,"Top 10 Risks")) -> 0 | Q19: =IF(IF(G19=MatrixImpact!$B$10,MatrixImpact!$D$10,IF(G19=MatrixImpact!$B$11,MatrixImpact!$D$11,IF(G19=MatrixImpact!$B$12,MatrixImpact!$D$12,IF(G19=MatrixImpact!$B$13,MatrixImpact!$D$13,IF(G19=MatrixImpact!$B$14,MatrixImpact!$D$14,"")))))<P19,P19,IF(G19=MatrixImpact!$B$10,MatrixImpact!$D$10,IF(G19=MatrixImpact!$B$11,MatrixImpact!$D$11,IF(G19=MatrixImpact!$B$12,MatrixImpact!$D$12,IF(G19=MatrixImpact!$B$13,MatrixImpact!$D$13,IF(G19=MatrixImpact!$B$14,MatrixImpact!$D$14,"")))))) | S19: =N19*R19 -> 0 | U19: 2 | V19: 4 | W19: =INDEX(MatrixImpact!C$4:C$8,MATCH($U19,MatrixImpact!$B$4:$B$8,0),1)*INDEX(MatrixImpact!C$10:C$14,MATCH($V19,MatrixImpact!$B$10:$B$14,0),1) -> 1 | X19: =INDEX(MatrixImpact!D$4:D$8,MATCH($U19,MatrixImpact!$B$4:$B$8,0),1)*INDEX(MatrixImpact!D$10:D$14,MATCH($V19,MatrixImpact!$B$10:$B$14,0),1) -> 9 | Y19: =IF(AND($AE$4>=W19,$AD$4<=X19),TRUE(),FALSE()) -> FALSE | AB19: =AB18-5% -> 0.2 | AC19: =AC18 -> 0 | AG19: Operations Risk | AH19: Market Risk: Products
B20: 18 | E20: =RiskList!A19&": "&RiskList!B19 -> Company 118: | F20: =IF($L20=0%,"",IF(AND($L20>MatrixImpact!$C$8,$L20<=MatrixImpact!$D$8),5,IF(AND($L20>MatrixImpact!$C$7,$L20<=MatrixImpact!$D$7),4,IF(AND($L20>MatrixImpact!$C$6,$L20<=MatrixImpact!$D$6),3,IF(AND($L20>MatrixImpact!$C$5,$L20<=MatrixImpact!$D$5),2,IF(AND($L20>MatrixImpact!$C$4,$L20<=MatrixImpact!$D$4),1,"")))))) | G20: =IF($P20>MatrixImpact!$C$14,5,IF(AND($P20>MatrixImpact!$C$13,$P20<=MatrixImpact!$D$13),4,IF(AND($P20>MatrixImpact!$C$12,$P20<=MatrixImpact!$D$12),3,IF(AND($P20>MatrixImpact!$C$11,$P20<=MatrixImpact!$D$11),2,IF(AND($P20>MatrixImpact!$C$10,$P20<=MatrixImpact!$D$10),1,""))))) | H20: =INDIRECT(ADDRESS(ROW()+6,9,1,1,"Top 10 Risks")) -> 0 | J20: =B20 -> 18 | K20: =IF(F20=MatrixImpact!$B$4,MatrixImpact!$C$4,IF(F20=MatrixImpact!$B$5,MatrixImpact!$C$5,IF(F20=MatrixImpact!$B$6,MatrixImpact!$C$6,IF(F20=MatrixImpact!$B$7,MatrixImpact!$C$7,IF(F20=MatrixImpact!$B$8,MatrixImpact!$C$8,""))))) | L20: =INDIRECT(ADDRESS(ROW()+6,10,1,1,"Top 10 Risks")) -> 0 | M20: =IF(F20=MatrixImpact!$B$4,MatrixImpact!$D$4,IF(F20=MatrixImpact!$B$5,MatrixImpact!$D$5,IF(F20=MatrixImpact!$B$6,MatrixImpact!$D$6,IF(F20=MatrixImpact!$B$7,MatrixImpact!$D$7,IF(F20=MatrixImpact!$B$8,MatrixImpact!$D$8,""))))) | O20: =IF(G20=MatrixImpact!$B$10,MatrixImpact!$C$10,IF(G20=MatrixImpact!$B$11,MatrixImpact!$C$11,IF(G20=MatrixImpact!$B$12,MatrixImpact!$C$12,IF(G20=MatrixImpact!$B$13,MatrixImpact!$C$13,IF(G20=MatrixImpact!$B$14,MatrixImpact!$C$14,""))))) | P20: =INDIRECT(ADDRESS(ROW()+6,8,1,1,"Top 10 Risks")) -> 0 | Q20: =IF(IF(G20=MatrixImpact!$B$10,MatrixImpact!$D$10,IF(G20=MatrixImpact!$B$11,MatrixImpact!$D$11,IF(G20=MatrixImpact!$B$12,MatrixImpact!$D$12,IF(G20=MatrixImpact!$B$13,MatrixImpact!$D$13,IF(G20=MatrixImpact!$B$14,MatrixImpact!$D$14,"")))))<P20,P20,IF(G20=MatrixImpact!$B$10,MatrixImpact!$D$10,IF(G20=MatrixImpact!$B$11,MatrixImpact!$D$11,IF(G20=MatrixImpact!$B$12,MatrixImpact!$D$12,IF(G20=MatrixImpact!$B$13,MatrixImpact!$D$13,IF(G20=MatrixImpact!$B$14,MatrixImpact!$D$14,"")))))) | S20: =N20*R20 -> 0 | U20: 3 | V20: 4 | W20: =INDEX(MatrixImpact!C$4:C$8,MATCH($U20,MatrixImpact!$B$4:$B$8,0),1)*INDEX(MatrixImpact!C$10:C$14,MATCH($V20,MatrixImpact!$B$10:$B$14,0),1) -> 3 | X20: =INDEX(MatrixImpact!D$4:D$8,MATCH($U20,MatrixImpact!$B$4:$B$8,0),1)*INDEX(MatrixImpact!D$10:D$14,MATCH($V20,MatrixImpact!$B$10:$B$14,0),1) -> 15 | Y20: =IF(AND($AE$4>=W20,$AD$4<=X20),TRUE(),FALSE()) -> FALSE | AB20: =AB19-5% -> 0.15 | AC20: =AC19 -> 0 | AG20: Legal Risk | AH20: Market Risk: Customers
B21: 19 | E21: =RiskList!A20&": "&RiskList!B20 -> Company 119: | F21: =IF($L21=0%,"",IF(AND($L21>MatrixImpact!$C$8,$L21<=MatrixImpact!$D$8),5,IF(AND($L21>MatrixImpact!$C$7,$L21<=MatrixImpact!$D$7),4,IF(AND($L21>MatrixImpact!$C$6,$L21<=MatrixImpact!$D$6),3,IF(AND($L21>MatrixImpact!$C$5,$L21<=MatrixImpact!$D$5),2,IF(AND($L21>MatrixImpact!$C$4,$L21<=MatrixImpact!$D$4),1,"")))))) | G21: =IF($P21>MatrixImpact!$C$14,5,IF(AND($P21>MatrixImpact!$C$13,$P21<=MatrixImpact!$D$13),4,IF(AND($P21>MatrixImpact!$C$12,$P21<=MatrixImpact!$D$12),3,IF(AND($P21>MatrixImpact!$C$11,$P21<=MatrixImpact!$D$11),2,IF(AND($P21>MatrixImpact!$C$10,$P21<=MatrixImpact!$D$10),1,""))))) | H21: =INDIRECT(ADDRESS(ROW()+6,9,1,1,"Top 10 Risks")) -> 0 | J21: =B21 -> 19 | K21: =IF(F21=MatrixImpact!$B$4,MatrixImpact!$C$4,IF(F21=MatrixImpact!$B$5,MatrixImpact!$C$5,IF(F21=MatrixImpact!$B$6,MatrixImpact!$C$6,IF(F21=MatrixImpact!$B$7,MatrixImpact!$C$7,IF(F21=MatrixImpact!$B$8,MatrixImpact!$C$8,""))))) | L21: =INDIRECT(ADDRESS(ROW()+6,10,1,1,"Top 10 Risks")) -> 0 | M21: =IF(F21=MatrixImpact!$B$4,MatrixImpact!$D$4,IF(F21=MatrixImpact!$B$5,MatrixImpact!$D$5,IF(F21=MatrixImpact!$B$6,MatrixImpact!$D$6,IF(F21=MatrixImpact!$B$7,MatrixImpact!$D$7,IF(F21=MatrixImpact!$B$8,MatrixImpact!$D$8,""))))) | O21: =IF(G21=MatrixImpact!$B$10,MatrixImpact!$C$10,IF(G21=MatrixImpact!$B$11,MatrixImpact!$C$11,IF(G21=MatrixImpact!$B$12,MatrixImpact!$C$12,IF(G21=MatrixImpact!$B$13,MatrixImpact!$C$13,IF(G21=MatrixImpact!$B$14,MatrixImpact!$C$14,""))))) | P21: =INDIRECT(ADDRESS(ROW()+6,8,1,1,"Top 10 Risks")) -> 0 | Q21: =IF(IF(G21=MatrixImpact!$B$10,MatrixImpact!$D$10,IF(G21=MatrixImpact!$B$11,MatrixImpact!$D$11,IF(G21=MatrixImpact!$B$12,MatrixImpact!$D$12,IF(G21=MatrixImpact!$B$13,MatrixImpact!$D$13,IF(G21=MatrixImpact!$B$14,MatrixImpact!$D$14,"")))))<P21,P21,IF(G21=MatrixImpact!$B$10,MatrixImpact!$D$10,IF(G21=MatrixImpact!$B$11,MatrixImpact!$D$11,IF(G21=MatrixImpact!$B$12,MatrixImpact!$D$12,IF(G21=MatrixImpact!$B$13,MatrixImpact!$D$13,IF(G21=MatrixImpact!$B$14,MatrixImpact!$D$14,"")))))) | S21: =N21*R21 -> 0 | U21: 4 | V21: 4 | W21: =INDEX(MatrixImpact!C$4:C$8,MATCH($U21,MatrixImpact!$B$4:$B$8,0),1)*INDEX(MatrixImpact!C$10:C$14,MATCH($V21,MatrixImpact!$B$10:$B$14,0),1) -> 5 | X21: =INDEX(MatrixImpact!D$4:D$8,MATCH($U21,MatrixImpact!$B$4:$B$8,0),1)*INDEX(MatrixImpact!D$10:D$14,MATCH($V21,MatrixImpact!$B$10:$B$14,0),1) -> 27 | Y21: =IF(AND($AE$4>=W21,$AD$4<=X21),TRUE(),FALSE()) -> FALSE | AB21: =AB20-5% -> 0.1 | AC21: =AC20 -> 0 | AG21: Political Risk | AH21: Information for decision making Risk
B22: 20 | E22: =RiskList!A21&": "&RiskList!B21 -> Company 120: | F22: =IF($L22=0%,"",IF(AND($L22>MatrixImpact!$C$8,$L22<=MatrixImpact!$D$8),5,IF(AND($L22>MatrixImpact!$C$7,$L22<=MatrixImpact!$D$7),4,IF(AND($L22>MatrixImpact!$C$6,$L22<=MatrixImpact!$D$6),3,IF(AND($L22>MatrixImpact!$C$5,$L22<=MatrixImpact!$D$5),2,IF(AND($L22>MatrixImpact!$C$4,$L22<=MatrixImpact!$D$4),1,"")))))) | G22: =IF($P22>MatrixImpact!$C$14,5,IF(AND($P22>MatrixImpact!$C$13,$P22<=MatrixImpact!$D$13),4,IF(AND($P22>MatrixImpact!$C$12,$P22<=MatrixImpact!$D$12),3,IF(AND($P22>MatrixImpact!$C$11,$P22<=MatrixImpact!$D$11),2,IF(AND($P22>MatrixImpact!$C$10,$P22<=MatrixImpact!$D$10),1,""))))) | H22: =INDIRECT(ADDRESS(ROW()+6,9,1,1,"Top 10 Risks")) -> 0 | J22: =B22 -> 20 | K22: =IF(F22=MatrixImpact!$B$4,MatrixImpact!$C$4,IF(F22=MatrixImpact!$B$5,MatrixImpact!$C$5,IF(F22=MatrixImpact!$B$6,MatrixImpact!$C$6,IF(F22=MatrixImpact!$B$7,MatrixImpact!$C$7,IF(F22=MatrixImpact!$B$8,MatrixImpact!$C$8,""))))) | L22: =INDIRECT(ADDRESS(ROW()+6,10,1,1,"Top 10 Risks")) -> 0 | M22: =IF(F22=MatrixImpact!$B$4,MatrixImpact!$D$4,IF(F22=MatrixImpact!$B$5,MatrixImpact!$D$5,IF(F22=MatrixImpact!$B$6,MatrixImpact!$D$6,IF(F22=MatrixImpact!$B$7,MatrixImpact!$D$7,IF(F22=MatrixImpact!$B$8,MatrixImpact!$D$8,""))))) | O22: =IF(G22=MatrixImpact!$B$10,MatrixImpact!$C$10,IF(G22=MatrixImpact!$B$11,MatrixImpact!$C$11,IF(G22=MatrixImpact!$B$12,MatrixImpact!$C$12,IF(G22=MatrixImpact!$B$13,MatrixImpact!$C$13,IF(G22=MatrixImpact!$B$14,MatrixImpact!$C$14,""))))) | P22: =INDIRECT(ADDRESS(ROW()+6,8,1,1,"Top 10 Risks")) -> 0 | Q22: =IF(IF(G22=MatrixImpact!$B$10,MatrixImpact!$D$10,IF(G22=MatrixImpact!$B$11,MatrixImpact!$D$11,IF(G22=MatrixImpact!$B$12,MatrixImpact!$D$12,IF(G22=MatrixImpact!$B$13,MatrixImpact!$D$13,IF(G22=MatrixImpact!$B$14,MatrixImpact!$D$14,"")))))<P22,P22,IF(G22=MatrixImpact!$B$10,MatrixImpact!$D$10,IF(G22=MatrixImpact!$B$11,MatrixImpact!$D$11,IF(G22=MatrixImpact!$B$12,MatrixImpact!$D$12,IF(G22=MatrixImpact!$B$13,MatrixImpact!$D$13,IF(G22=MatrixImpact!$B$14,MatrixImpact!$D$14,"")))))) | S22: =N22*R22 -> 0 | U22: 5 | V22: 4 | W22: =INDEX(MatrixImpact!C$4:C$8,MATCH($U22,MatrixImpact!$B$4:$B$8,0),1)*INDEX(MatrixImpact!C$10:C$14,MATCH($V22,MatrixImpact!$B$10:$B$14,0),1) -> 9 | X22: =INDEX(MatrixImpact!D$4:D$8,MATCH($U22,MatrixImpact!$B$4:$B$8,0),1)*INDEX(MatrixImpact!D$10:D$14,MATCH($V22,MatrixImpact!$B$10:$B$14,0),1) -> 30 | Y22: =IF(AND($AE$4>=W22,$AD$4<=X22),TRUE(),FALSE()) -> FALSE | AB22: =AB21-5% -> 0.05 | AC22: =AC21 -> 0 | AG22: Exogenous Risk | AH22: Alignment Risk
